Workbook
Name IQ_CH: 110000
Name IQ_CQ: 5000
Name IQ_CY: 10000
Name IQ_DAILY: 500000
Name IQ_FH: 100000
Name IQ_FQ: 500
Name IQ_FY: 1000
Name IQ_LTM: 2000
Name IQ_MONTH: 15000
Name IQ_NTM: 6000
Name IQ_WEEK: 50000
Name IQ_YTD: 3000
Name UPDATE: '[1]Data Sheet'!$E$1
Name UPDATE: #REF!
Name UPDATE: 'Data Sheet'!$E$1

Sheet Quarters
A1: ='Profit & Loss'!A1 -> NTPC LTD | E1: =UPDATE | J1: SCREENER.IN
A3: Narration | B3: ='Data Sheet'!B42 -> 44834 | C3: ='Data Sheet'!C42 -> 44926 | D3: ='Data Sheet'!D42 -> 45016 | E3: ='Data Sheet'!E42 -> 45107 | F3: ='Data Sheet'!F42 -> 45199 | G3: ='Data Sheet'!G42 -> 45291 | H3: ='Data Sheet'!H42 -> 45382 | I3: ='Data Sheet'!I42 -> 45473 | ... K3: ='Data Sheet'!K42 -> 45657
A4: Sales | B4: ='Data Sheet'!B43 -> 44175.03 | C4: ='Data Sheet'!C43 -> 44601.84 | D4: ='Data Sheet'!D43 -> 44252.92 | E4: ='Data Sheet'!E43 -> 43075.09 | F4: ='Data Sheet'!F43 -> 44983.35 | G4: ='Data Sheet'!G43 -> 42820.38 | H4: ='Data Sheet'!H43 -> 47622.06 | I4: ='Data Sheet'!I43 -> 48520.57 | ... K4: ='Data Sheet'!K43 -> 45052.82
A5: Expenses | B5: ='Data Sheet'!B44 -> 33808.14 | C5: ='Data Sheet'!C44 -> 31782.94 | D5: ='Data Sheet'!D44 -> 32310.52 | E5: ='Data Sheet'!E44 -> 30664.22 | F5: ='Data Sheet'!F44 -> 32303.16 | G5: ='Data Sheet'!G44 -> 31458.23 | H5: ='Data Sheet'!H44 -> 33638.23 | I5: ='Data Sheet'!I44 -> 35091.26 | ... K5: ='Data Sheet'!K44 -> 31728.79
A6: Operating Profit | B6: ='Data Sheet'!B51 -> 10366.89 | C6: ='Data Sheet'!C51 -> 12818.9 | D6: ='Data Sheet'!D51 -> 11942.4 | E6: ='Data Sheet'!E51 -> 12410.87 | F6: ='Data Sheet'!F51 -> 12680.19 | G6: ='Data Sheet'!G51 -> 11362.15 | H6: ='Data Sheet'!H51 -> 13983.83 | I6: ='Data Sheet'!I51 -> 13429.31 | ... K6: ='Data Sheet'!K51 -> 13324.03
A7: Other Income | B7: ='Data Sheet'!B45 -> 1380.15 | C7: ='Data Sheet'!C45 -> 747.49 | D7: ='Data Sheet'!D45 -> 1083.88 | E7: ='Data Sheet'!E45 -> 994.05 | F7: ='Data Sheet'!F45 -> 1024.05 | G7: ='Data Sheet'!G45 -> 2532.46 | H7: ='Data Sheet'!H45 -> 1405.89 | I7: ='Data Sheet'!I45 -> 1195.07 | ... K7: ='Data Sheet'!K45 -> 1002.62
A8: Depreciation | B8: ='Data Sheet'!B46 -> 3687.23 | C8: ='Data Sheet'!C46 -> 3715.08 | D8: ='Data Sheet'!D46 -> 3848.46 | E8: ='Data Sheet'!E46 -> 3821.28 | F8: ='Data Sheet'!F46 -> 4037.68 | G8: ='Data Sheet'!G46 -> 4073.91 | H8: ='Data Sheet'!H46 -> 4270.76 | I8: ='Data Sheet'!I46 -> 4204.2 | ... K8: ='Data Sheet'!K46 -> 4318.3
A9: Interest | B9: ='Data Sheet'!B47 -> 2651.54 | C9: ='Data Sheet'!C47 -> 3168.18 | D9: ='Data Sheet'!D47 -> 2859.54 | E9: ='Data Sheet'!E47 -> 2922.37 | F9: ='Data Sheet'!F47 -> 2920.51 | G9: ='Data Sheet'!G47 -> 3250.08 | H9: ='Data Sheet'!H47 -> 2955.25 | I9: ='Data Sheet'!I47 -> 3135.91 | ... K9: ='Data Sheet'!K47 -> 2763.54
A10: Profit before tax | B10: ='Data Sheet'!B48 -> 5408.27 | C10: ='Data Sheet'!C48 -> 6683.13 | D10: ='Data Sheet'!D48 -> 6318.28 | E10: ='Data Sheet'!E48 -> 6661.27 | F10: ='Data Sheet'!F48 -> 6746.05 | G10: ='Data Sheet'!G48 -> 6570.62 | H10: ='Data Sheet'!H48 -> 8163.71 | I10: ='Data Sheet'!I48 -> 7284.27 | ... K10: ='Data Sheet'!K48 -> 7244.81
A11: Tax | B11: ='Data Sheet'!B49 -> 1990.6 | C11: ='Data Sheet'!C49 -> 1828.77 | D11: ='Data Sheet'!D49 -> 1446.73 | E11: ='Data Sheet'!E49 -> 1754.14 | F11: ='Data Sheet'!F49 -> 2019.65 | G11: ='Data Sheet'!G49 -> 1361.75 | H11: ='Data Sheet'!H49 -> 1673.66 | I11: ='Data Sheet'!I49 -> 1778.2 | ... K11: ='Data Sheet'!K49 -> 2075.12
A12: Net profit | B12: ='Data Sheet'!B50 -> 3338.45 | C12: ='Data Sheet'!C50 -> 4776.61 | D12: ='Data Sheet'!D50 -> 4860.67 | E12: ='Data Sheet'!E50 -> 4873.24 | F12: ='Data Sheet'!F50 -> 4614.64 | G12: ='Data Sheet'!G50 -> 5155.28 | H12: ='Data Sheet'!H50 -> 6168.73 | I12: ='Data Sheet'!I50 -> 5474.14 | ... K12: ='Data Sheet'!K50 -> 5062.51
A14: OPM | B14: =IF(B4>0,B6/B4,"") -> 0.2346776 | C14: =IF(C4>0,C6/C4,"") -> 0.28740743 | D14: =IF(D4>0,D6/D4,"") -> 0.26986694 | E14: =IF(E4>0,E6/E4,"") -> 0.28812174 | F14: =IF(F4>0,F6/F4,"") -> 0.2818863 | G14: =IF(G4>0,G6/G4,"") -> 0.26534445 | H14: =IF(H4>0,H6/H4,"") -> 0.29364185 | I14: =IF(I4>0,I6/I4,"") -> 0.2767756 | ... K14: =IF(K4>0,K6/K4,"") -> 0.29574242

Sheet Cash Flow Statement
C2: 41334 | D2: 41699 | E2: 42064 | F2: 42430 | G2: 42795 | H2: 43160 | I2: 43525 | J2: 43891 | K2: 44256 | L2: 44621 | M2: 44986 | N2: 45352
B3: Cash from Operating Activity - | C3: 22163 | D3: 36151 | E3: 35531 | F3: 37900 | G3: 30199 | H3: 23857 | I3: 18891 | J3: 26633 | K3: 29001 | L3: 14283 | M3: 35388 | N3: 67915
B4: Profit from operations | C4: 24406 | D4: 36303 | E4: 43397 | F4: 38626 | G4: 28840 | H4: 33312 | I4: 28771 | J4: 23352 | K4: 31198 | L4: 26943 | M4: 41694 | N4: 65106
B5: Receivables | C5: -5177 | D5: 445 | E5: -3179 | F5: -2223 | G5: -4152 | H5: -10688 | I5: -9109 | J5: 9950 | K5: -5505 | L5: 185 | M5: -2213 | N5: -1875
B6: Inventory | C6: -2656 | D6: -2853 | E6: -3692 | F6: -5743 | G6: -6621 | H6: -3560 | I6: 2069 | J6: 2326 | K6: 3814 | L6: 472 | M6: -5665 | N6: -7265
B7: Payables | C7: 8132 | D7: 4694 | E7: 3598 | F7: 3947 | G7: 9301 | H7: 7320 | I7: -4692 | J7: -8085 | K7: 5748 | L7: -7012 | M7: 6945 | N7: 13706
B8: Loans Advances | C8: 0 | D8: 0 | E8: 0 | F8: -520 | G8: 0 | H8: 0 | I8: 0 | J8: 0 | K8: 0 | L8: 0 | M8: 0 | N8: 0
B9: Other WC items | C9: -303 | D9: 1870 | E9: -398 | F9: 5852 | G9: 4727 | H9: 494 | I9: 4512 | J9: 875 | K9: -4150 | L9: -4396 | M9: -2194 | N9: 2760
B10: Working capital changes | C10: -3 | D10: 4157 | E10: -3672 | F10: 1313 | G10: 3254 | H10: -6434 | I10: -7221 | J10: 5065 | K10: -93 | L10: -10750 | M10: -3127 | N10: 7325
B11: Direct taxes | C11: -2240 | D11: -4308 | E11: -4194 | F11: -2040 | G11: -1895 | H11: -3021 | I11: -2659 | J11: -1785 | K11: -2105 | L11: -1910 | M11: -3179 | N11: -4516
B12: Cash from Investing Activity - | C12: -22969 | D12: -27991 | E12: -36232 | F12: -36694 | G12: -39571 | H12: -25139 | I12: -20878 | J12: -33115 | K12: -25672 | L12: -4444 | M12: -15417 | N12: -22782
B13: Fixed assets purchased | C13: -18863 | D13: -26975 | E13: -31962 | F13: -31503 | G13: -16072 | H13: -35079 | I13: -35304 | J13: -29702 | K13: -20205 | L13: -15168 | M13: -19230 | N13: -31414
B14: Fixed assets sold | C14: 37 | D14: 50 | E14: 74 | F14: 59 | G14: 53 | H14: 30 | I14: 67 | J14: 171 | K14: 351 | L14: 230 | M14: 285 | N14: 231
... B33: Net Cash Flow | C33: -2499 | D33: 4277 | E33: 4500 | F33: -2589 | G33: -3167 | H33: 730 | I33: 6843 | J33: -3092 | K33: 13232 | L33: 6459 | M33: -6272 | N33: 8128

Sheet Company Profile
B2: ='Data Sheet'!B1 & " - " & "One Page Profile" -> NTPC LTD - One Page Profile
C4: ='Input Sheet'!C3 -> NTPC (National Thermal Power Corporation) Ltd along with its subsidiaries/ associates & JVs is primarily involved in generation and sale of bulk power to State power utilities. Other business of the group includes providing consultancy, project management & supervision, energy trading, oil & gas exploration and coal mining.
B5: INR (Crs.)
B6: Key Financial Matrix | C6: ='Data Sheet'!G16 -> 43921 | D6: ='Data Sheet'!H16 -> 44286 | E6: ='Data Sheet'!I16 -> 44651 | F6: ='Data Sheet'!J16 -> 45016 | G6: ='Data Sheet'!K16 -> 45382 | I6: Share Price - 5Y
B8: Total Sales | C8: ='Data Sheet'!G17 -> 109464.04 | D8: ='Data Sheet'!H17 -> 111531.15 | E8: ='Data Sheet'!I17 -> 132669.28 | F8: ='Data Sheet'!J17 -> 176207.18 | G8: ='Data Sheet'!K17 -> 178500.88
B9: Sales Growth (YoY) | C9: =HistoricalFS!H11 -> 0.091512779 | D9: =HistoricalFS!I11 -> 0.018883918 | E9: =HistoricalFS!J11 -> 0.18952669 | F9: =HistoricalFS!K11 -> 0.32816866 | G9: =HistoricalFS!L11 -> 0.013017063
B10: Gross Profit Margins (%) | C10: =HistoricalFS!H17 -> 0.30917934 | D10: =HistoricalFS!I17 -> 0.32654115 | E10: =HistoricalFS!J17 -> 0.31238196 | F10: =HistoricalFS!K17 -> 0.29075058 | G10: =HistoricalFS!L17 -> 0.29324113
B11: EBITDA Margins (%) | C11: =HistoricalFS!H23 -> 0.28854892 | D11: =HistoricalFS!I23 -> 0.30523957 | E11: =HistoricalFS!J23 -> 0.30422959 | F11: =HistoricalFS!K23 -> 0.27011357 | G11: =HistoricalFS!L23 -> 0.28826575
B12: EBIT Margins (%) | C12: =HistoricalFS!H32 -> 0.11913099 | D12: =HistoricalFS!I32 -> 0.11090355 | E12: =HistoricalFS!J32 -> 0.1296337 | F12: =HistoricalFS!K32 -> 0.12120125 | G12: =HistoricalFS!L32 -> 0.12857948
B13: Net Margins (%) | C13: =HistoricalFS!H38 -> 0.033737289 | D13: =HistoricalFS!I38 -> 0.08920082 | E13: =HistoricalFS!J38 -> 0.091590985 | F13: =HistoricalFS!K38 -> 0.082632331 | G13: =HistoricalFS!L38 -> 0.090432888
B14: Earinings Per Share (In Rs.) | C14: =HistoricalFS!H42 -> 3.7323591 | D14: =HistoricalFS!I42 -> 10.259851 | E14: =HistoricalFS!J42 -> 12.531387 | F14: =HistoricalFS!K42 -> 15.01584 | G14: =HistoricalFS!L42 -> 16.647261
B15: EPS Growth (YoY) | C15: =HistoricalFS!H43 -> -0.67075494 | D15: =HistoricalFS!I43 -> 1.7488918 | E15: =HistoricalFS!J43 -> 0.22140045 | F15: =HistoricalFS!K43 -> 0.19825846 | G15: =HistoricalFS!L43 -> 0.10864667
B16: Dividend Per Share | C16: =HistoricalFS!H45 -> 3.1499909 | D16: =HistoricalFS!I45 -> 6.1499789 | E16: =HistoricalFS!J45 -> 6.9999794 | F16: =HistoricalFS!K45 -> 7.249982 | G16: =HistoricalFS!L45 -> 7.7499768
B17: Dividend Growth (YoY) | C17: ='Profit & Loss'!G29 -> -0.48190708 | D17: ='Profit & Loss'!H29 -> 0.95237988 | E17: ='Profit & Loss'!I29 -> 0.13821194 | F17: ='Profit & Loss'!J29 -> 0.035714759 | G17: ='Profit & Loss'!K29 -> 0.068964978
B19: =B6 -> Key Financial Matrix | C19: =C6 -> 43921 | D19: =D6 -> 44286 | E19: =E6 -> 44651 | F19: =F6 -> 45016 | G19: =G6 -> 45382 | I19: Volume - 5Y
B21: Price to Earnings | C21: ='Profit & Loss'!G14 -> 7.1819724 | D21: ='Profit & Loss'!H14 -> 7.0598531 | E21: ='Profit & Loss'!I14 -> 7.8499781 | F21: ='Profit & Loss'!J14 -> 10.039244 | G21: ='Profit & Loss'!K14 -> 15.645633 | H21: ='Profit & Loss'!L14 -> 13.931809
B22: EV / EBITDA | C22: ='Profit & Loss'!G36 -> 7.167928 | D22: ='Profit & Loss'!H36 -> 7.981951 | E22: ='Profit & Loss'!I36 -> 7.5112529 | F22: ='Profit & Loss'!J36 -> 7.7631366 | G22: ='Profit & Loss'!K36 -> 9.9046156
B23: EV / Sales | C23: ='Profit & Loss'!G37 -> 2.5860781 | D23: ='Profit & Loss'!H37 -> 2.7717674 | E23: ='Profit & Loss'!I37 -> 2.5413112 | F23: ='Profit & Loss'!J37 -> 2.2005565 | G23: ='Profit & Loss'!K37 -> 3.1142638
B24: Price to Book Value | C24: ='Profit & Loss'!G39 -> 0.70105285 | D24: ='Profit & Loss'!H39 -> 0.82169235 | E24: ='Profit & Loss'!I39 -> 0.96699293 | F24: ='Profit & Loss'!J39 -> 1.1548467 | G24: ='Profit & Loss'!K39 -> 2.0261133
B25: Return on Equity (%) | C25: ='Ratio Analysis'!H28 -> 0.031075783 | D25: ='Ratio Analysis'!I28 -> 0.079121927 | E25: ='Ratio Analysis'!J28 -> 0.089761205 | F25: ='Ratio Analysis'!K28 -> 0.099034798 | G25: ='Ratio Analysis'!L28 -> 0.10044442 | H25: ='Ratio Analysis'!M28 -> 0
B26: Return on Capital Employed (%) | C26: ='Ratio Analysis'!H26 -> 0.065966506 | D26: ='Ratio Analysis'!I26 -> 0.064276366 | E26: ='Ratio Analysis'!J26 -> 0.076785908 | F26: ='Ratio Analysis'!K26 -> 0.088673854 | G26: ='Ratio Analysis'!L26 -> 0.088608581 | H26: ='Ratio Analysis'!M26 -> 0
B28: ="Top Shareholders of" & " - " & 'Data Sheet'!B1 -> Top Shareholders of - NTPC LTD | C28: ='Share Price - 5Y'!I21 -> N. Shares (In Crs.) | E28: % Holding | F28: ='Share Price - 5Y'!K21 -> Market Value (In Crs.) | I28: Shareholding Patterns
B30: ='Share Price - 5Y'!H22 -> President Of India | C30: ='Share Price - 5Y'!I22 -> 495.53463 | E30: ='Share Price - 5Y'!J22 -> 0.511 | F30: ='Share Price - 5Y'!K22 -> 161668.17
B31: ='Share Price - 5Y'!H23 -> Icici Prudential Equity & Debt Fund | C31: ='Share Price - 5Y'!I23 -> 41.249902 | E31: ='Share Price - 5Y'!J23 -> 0.0425 | F31: ='Share Price - 5Y'!K23 -> 13457.78
B32: ='Share Price - 5Y'!H24 -> Life Insurance Corporation Of India | C32: ='Share Price - 5Y'!I24 -> 38.442476 | E32: ='Share Price - 5Y'!J24 -> 0.0396 | F32: ='Share Price - 5Y'!K24 -> 12541.858
B33: ='Share Price - 5Y'!H25 -> Cpse Exchange Traded Scheme (cpse Etf) | C33: ='Share Price - 5Y'!I25 -> 36.730436 | E33: ='Share Price - 5Y'!J25 -> 0.0379 | F33: ='Share Price - 5Y'!K25 -> 11983.305
B34: ='Share Price - 5Y'!H26 -> Government Of Singapore | C34: ='Share Price - 5Y'!I26 -> 22.337466 | E34: ='Share Price - 5Y'!J26 -> 0.023 | F34: ='Share Price - 5Y'!K26 -> 7287.5982
B35: ='Share Price - 5Y'!H27 -> Sbi Nifty 50 Etf | C35: ='Share Price - 5Y'!I27 -> 18.66853 | E35: ='Share Price - 5Y'!J27 -> 0.0193 | F35: ='Share Price - 5Y'!K27 -> 6090.6078
B36: ='Share Price - 5Y'!H28 -> Hdfc Trustee Company Ltd. A/c Hdfc Balanced A | C36: ='Share Price - 5Y'!I28 -> 18.483343 | E36: ='Share Price - 5Y'!J28 -> 0.0191 | F36: ='Share Price - 5Y'!K28 -> 6030.1907
B37: ='Share Price - 5Y'!H29 -> Nps Trust- A/c Hdfc Pension Fund Management L | C37: ='Share Price - 5Y'!I29 -> 15.834972 | E37: ='Share Price - 5Y'!J29 -> 0.0163 | F37: ='Share Price - 5Y'!K29 -> 5166.1595
B38: ='Share Price - 5Y'!H30 -> Investor Education and Protection Fund (IEPF) | C38: ='Share Price - 5Y'!I30 -> 0.1788723 | E38: ='Share Price - 5Y'!J30 -> 0.0002 | F38: ='Share Price - 5Y'!K30 -> 58.357088
B40: Managerial Remuneration | C40: Designation | D40: Remuneration | F40: X of Median Salary | I40: Capital Structure
B42: Shri Gurdeep Singh | C42: CMD | D42: 1.59 | G42: N/A | I42: Share Price as on | K42: ='Data Sheet'!B8 -> 315.8
B43: Shri Dillip Kumar Patel | C43: Dir (HR) | D43: 1.09 | G43: N/A | I43: Number of Shares O/S | K43: ='Data Sheet'!B6 -> 969.66672
B44: Shri Ramesh Babu V | C44: Dir (Ops) | D44: 1.72 | G44: N/A | I44: Market Capitalization | K44: =K42*K43 -> 306220.75
B45: Shri Ujjwal Kanti Bhattacharya | C45: Dir (Proj) | D45: 1.51 | G45: N/A | I45: Less: Cash & Equivalents | K45: ='Data Sheet'!K70*-1 -> -6847.34
I46: Add: Total Debt | K46: ='Data Sheet'!K60 -> 237130.98
B47: Note: | I47: Add: Minority Interset | K47: 4413.01
B48: The median salary ratio isn’t provided due to government company exemptions. Instead, the table shows each director’s share of total employee payroll for transparency. | I48: Enterprise Value | K48: =SUM(K44:K47) -> 540917.4
B50: Recent Updates
B52: NTPC shares rise 0.25% to ₹325.95, outperforming market downturn.
B53: NTPC plans $62 billion investment to develop 30 GW of nuclear power capacity over the next two decades.
B54: NTPC collaborates with Nuclear Power Corp of India to build two 2.6 GW nuclear plants in Madhya Pradesh and Rajasthan.
B55: NTPC seeks land in eight states for potential nuclear power projects, aiming for at least 50 GW capacity.
B56: NTPC's newly formed unit, NTPC Parmanu Urja Nigam, to spearhead investments in the nuclear sector.
B57: NTPC's debt-equity ratio reaches a ten-period low of 1.44 times in Q3 FY24-25, indicating improved financial stability.
B58: NTPC's stock performance mixed among competitors; Tata Power fell 0.21%, while Torrent Power rose 2.33%.
B59: NTPC's trading volume reached 518,062, surpassing the 50-day average of 457,012.
B60: NTPC's current share price is 27.29% below its 52-week high of ₹448.30, achieved on September 30th.
B61: India proposes amendments to laws to facilitate private and foreign investment in the nuclear sector, benefiting NTPC's expansion plans.
B62: NTPC Green Energy's shares surge up to 14% on trading debut, valuing the company at approximately $12.08 billion.
... B75: Source
B76: Minority Int ( Non-controlling interests) | C76: Consolidated Balance Sheet | F76: Screener.in

Sheet HistoricalFS
B3: =B7 -> Historical Financial Statement - NTPC LTD
B7: ="Historical Financial Statement - " & 'Data Sheet'!B1 -> Historical Financial Statement - NTPC LTD
B8: Years | C8: ='Data Sheet'!B57 -> 42094 | D8: ='Data Sheet'!C57 -> 42460 | E8: ='Data Sheet'!D57 -> 42825 | F8: ='Data Sheet'!E57 -> 43190 | G8: ='Data Sheet'!F57 -> 43555 | H8: ='Data Sheet'!G57 -> 43921 | I8: ='Data Sheet'!H57 -> 44286 | J8: ='Data Sheet'!I57 -> 44651 | ... L8: ='Data Sheet'!K57 -> 45382 | M8: LTM
A9: # | B9: Income Statement
B10: Sales | C10: =IFERROR('Data Sheet'!B17,0) -> 79956.74 | D10: =IFERROR('Data Sheet'!C17,0) -> 73396.32 | E10: =IFERROR('Data Sheet'!D17,0) -> 82042.49 | F10: =IFERROR('Data Sheet'!E17,0) -> 88083.31 | G10: =IFERROR('Data Sheet'!F17,0) -> 100286.54 | H10: =IFERROR('Data Sheet'!G17,0) -> 109464.04 | I10: =IFERROR('Data Sheet'!H17,0) -> 111531.15 | J10: =IFERROR('Data Sheet'!I17,0) -> 132669.28 | ... L10: =IFERROR('Data Sheet'!K17,0) -> 178500.88 | M10: =IFERROR(SUM('Data Sheet'!H43:K43),0) -> 185891.75
B11: Sales Growth % | C11: - | D11: =D10/C10-1 -> -0.082049618 | E11: =E10/D10-1 -> 0.11780114 | F11: =F10/E10-1 -> 0.073630383 | G11: =G10/F10-1 -> 0.13854191 | H11: =H10/G10-1 -> 0.091512779 | I11: =I10/H10-1 -> 0.018883918 | J11: =J10/I10-1 -> 0.18952669 | K11: =K10/J10-1 -> 0.32816866 | ... M11: =M10/L10-1 -> 0.04140523
B13: Cost of Goods Sold | C13: =IFERROR(SUM('Data Sheet'!B18,'Data Sheet'!B20:B22)-1*'Data Sheet'!B19,0) -> 62480.32 | D13: =IFERROR(SUM('Data Sheet'!C18,'Data Sheet'!C20:C22)-1*'Data Sheet'!C19,0) -> 54652.18 | E13: =IFERROR(SUM('Data Sheet'!D18,'Data Sheet'!D20:D22)-1*'Data Sheet'!D19,0) -> 60357.15 | F13: =IFERROR(SUM('Data Sheet'!E18,'Data Sheet'!E20:E22)-1*'Data Sheet'!E19,0) -> 64386.18 | G13: =IFERROR(SUM('Data Sheet'!F18,'Data Sheet'!F20:F22)-1*'Data Sheet'!F19,0) -> 72237.19 | H13: =IFERROR(SUM('Data Sheet'!G18,'Data Sheet'!G20:G22)-1*'Data Sheet'!G19,0) -> 75620.02 | I13: =IFERROR(SUM('Data Sheet'!H18,'Data Sheet'!H20:H22)-1*'Data Sheet'!H19,0) -> 75111.64 | J13: =IFERROR(SUM('Data Sheet'!I18,'Data Sheet'!I20:I22)-1*'Data Sheet'!I19,0) -> 91225.79 | ... M13: =IFERROR(SUM('Data Sheet'!L18,'Data Sheet'!L20:L22)-1*'Data Sheet'!L19,0) -> 0
B14: COGS % Sales | C14: =C13/C10 -> 0.78142656 | D14: =D13/D10 -> 0.74461744 | E14: =E13/E10 -> 0.7356816 | F14: =F13/F10 -> 0.73096912 | G14: =G13/G10 -> 0.72030793 | H14: =H13/H10 -> 0.69082066 | I14: =I13/I10 -> 0.67345885 | J14: =J13/J10 -> 0.68761804 | ... M14: =M13/M10 -> 0
B16: Gross Profit | C16: =C10-C13 -> 17476.42 | D16: =D10-D13 -> 18744.14 | E16: =E10-E13 -> 21685.34 | F16: =F10-F13 -> 23697.13 | G16: =G10-G13 -> 28049.35 | H16: =H10-H13 -> 33844.02 | I16: =I10-I13 -> 36419.51 | J16: =J10-J13 -> 41443.49 | ... M16: =M10-M13 -> 185891.75
B17: Gross Margin | C17: =C16/C10 -> 0.21857344 | D17: =D16/D10 -> 0.25538256 | E17: =E16/E10 -> 0.2643184 | F17: =F16/F10 -> 0.26903088 | G17: =G16/G10 -> 0.27969207 | H17: =H16/H10 -> 0.30917934 | I17: =I16/I10 -> 0.32654115 | J17: =J16/J10 -> 0.31238196 | ... M17: =M16/M10 -> 1
B19: Selling & Genenral Expenses | C19: =IFERROR(SUM('Data Sheet'!B23:B24),0) -> 124.3 | D19: =IFERROR(SUM('Data Sheet'!C23:C24),0) -> 176.64 | E19: =IFERROR(SUM('Data Sheet'!D23:D24),0) -> 87.81 | F19: =IFERROR(SUM('Data Sheet'!E23:E24),0) -> 1211.72 | G19: =IFERROR(SUM('Data Sheet'!F23:F24),0) -> 5338.98 | H19: =IFERROR(SUM('Data Sheet'!G23:G24),0) -> 2258.29 | I19: =IFERROR(SUM('Data Sheet'!H23:H24),0) -> 2375.79 | J19: =IFERROR(SUM('Data Sheet'!I23:I24),0) -> 1081.57 | ... L19: =IFERROR(SUM('Data Sheet'!K23:K24),0) -> 888.11
B20: S&G Exp % Sales | C20: =C19/C10 -> 0.0015545906 | D20: =D19/D10 -> 0.0024066602 | E20: =E19/E10 -> 0.0010702991 | F20: =F19/F10 -> 0.013756522 | G20: =G19/G10 -> 0.053237254 | H20: =H19/H10 -> 0.020630428 | I20: =I19/I10 -> 0.021301583 | J20: =J19/J10 -> 0.0081523771 | ... M20: =M19/M10 -> 0
B22: EBITDA | C22: =C16-C19 -> 17352.12 | D22: =D16-D19 -> 18567.5 | E22: =E16-E19 -> 21597.53 | F22: =F16-F19 -> 22485.41 | G22: =G16-G19 -> 22710.37 | H22: =H16-H19 -> 31585.73 | I22: =I16-I19 -> 34043.72 | J22: =J16-J19 -> 40361.92 | ... L22: =L16-L19 -> 51455.69 | M22: =IFERROR(SUM('Data Sheet'!H28:K28),0) -> 91456.44
B23: EBITDA % Sales | C23: =C22/C10 -> 0.21701885 | D23: =D22/D10 -> 0.2529759 | E23: =E22/E10 -> 0.2632481 | F23: =F22/F10 -> 0.25527435 | G23: =G22/G10 -> 0.22645482 | H23: =H22/H10 -> 0.28854892 | I23: =I22/I10 -> 0.30523957 | J23: =J22/J10 -> 0.30422959 | ... M23: =M22/M10 -> 0.49198762
B25: Interest | C25: =IFERROR('Data Sheet'!B27,0) -> 3668.98 | D25: =IFERROR('Data Sheet'!C27,0) -> 3366.03 | E25: =IFERROR('Data Sheet'!D27,0) -> 3752.8 | F25: =IFERROR('Data Sheet'!E27,0) -> 4446.59 | G25: =IFERROR('Data Sheet'!F27,0) -> 5604.65 | H25: =IFERROR('Data Sheet'!G27,0) -> 8189.01 | I25: =IFERROR('Data Sheet'!H27,0) -> 9224.21 | J25: =IFERROR('Data Sheet'!I27,0) -> 9375.68 | ... L25: =IFERROR('Data Sheet'!K27,0) -> 12300.51 | M25: =IFERROR(SUM('Data Sheet'!H47:L47),0) -> 12475.28
B26: Interest % Sales | C26: =C25/C10 -> 0.045887063 | D26: =D25/D10 -> 0.045861019 | E26: =E25/E10 -> 0.045742151 | F26: =F25/F10 -> 0.050481641 | G26: =G25/G10 -> 0.055886363 | H26: =H25/H10 -> 0.074810047 | I26: =I25/I10 -> 0.082705235 | J26: =J25/J10 -> 0.070669563 | ... M26: =M25/M10 -> 0.067110455
B28: Depericiation | C28: =IFERROR('Data Sheet'!B26,0) -> 5564.61 | D28: =IFERROR('Data Sheet'!C26,0) -> 5771.24 | E28: =IFERROR('Data Sheet'!D26,0) -> 6009.91 | F28: =IFERROR('Data Sheet'!E26,0) -> 7459.93 | G28: =IFERROR('Data Sheet'!F26,0) -> 8669.03 | H28: =IFERROR('Data Sheet'!G26,0) -> 10356.16 | I28: =IFERROR('Data Sheet'!H26,0) -> 12450.31 | J28: =IFERROR('Data Sheet'!I26,0) -> 13787.83 | ... L28: =IFERROR('Data Sheet'!K26,0) -> 16203.63 | M28: =IFERROR(SUM('Data Sheet'!H46:K46),0) -> 17008.88
B29: Depericiation % Sales | C29: =C28/C10 -> 0.069595259 | D29: =D28/D10 -> 0.07863119 | E29: =E28/E10 -> 0.073253627 | F29: =F28/F10 -> 0.084691754 | G29: =G28/G10 -> 0.086442607 | H29: =H28/H10 -> 0.094607873 | I29: =I28/I10 -> 0.11163079 | J29: =J28/J10 -> 0.10392632 | ... M29: =M28/M10 -> 0.091498843
B31: Earnings Before Tax | C31: =IFERROR(C22-SUM(C28,C25),0) -> 8118.53 | D31: =IFERROR(D22-SUM(D28,D25),0) -> 9430.23 | E31: =IFERROR(E22-SUM(E28,E25),0) -> 11834.82 | F31: =IFERROR(F22-SUM(F28,F25),0) -> 10578.89 | G31: =IFERROR(G22-SUM(G28,G25),0) -> 8436.69 | H31: =IFERROR(H22-SUM(H28,H25),0) -> 13040.56 | I31: =IFERROR(I22-SUM(I28,I25),0) -> 12369.2 | J31: =IFERROR(J22-SUM(J28,J25),0) -> 17198.41 | ... M31: =IFERROR(M22-SUM(M28,M25),0) -> 61972.28
B32: EBT % Sales | C32: =C31/C10 -> 0.10153653 | D32: =D31/D10 -> 0.12848369 | E32: =E31/E10 -> 0.14425233 | F32: =F31/F10 -> 0.12010096 | G32: =G31/G10 -> 0.084125846 | H32: =H31/H10 -> 0.11913099 | I32: =I31/I10 -> 0.11090355 | J32: =J31/J10 -> 0.1296337 | ... M32: =M31/M10 -> 0.33337832
B34: Tax | C34: =IFERROR('Data Sheet'!B29,) -> 463.84 | D34: =IFERROR('Data Sheet'!C29,) -> -162.81 | E34: =IFERROR('Data Sheet'!D29,) -> 2712.39 | F34: =IFERROR('Data Sheet'!E29,) -> 5652.94 | G34: =IFERROR('Data Sheet'!F29,) -> -2779.94 | H34: =IFERROR('Data Sheet'!G29,) -> 9347.54 | I34: =IFERROR('Data Sheet'!H29,) -> 2420.53 | J34: =IFERROR('Data Sheet'!I29,) -> 5047.1 | ... L34: =IFERROR('Data Sheet'!K29,) -> 6809.2 | M34: =IFERROR(SUM('Data Sheet'!H49:K49),) -> 7193.2
B35: Effective Tax Rate | C35: =C34/C31 -> 0.057133496 | D35: =D34/D31 -> -0.01726469 | E35: =E34/E31 -> 0.22918726 | F35: =F34/F31 -> 0.53436041 | G35: =G34/G31 -> -0.329506 | H35: =H34/H31 -> 0.71680511 | I35: =I34/I31 -> 0.1956901 | J35: =J34/J31 -> 0.29346317 | ... M35: =M34/M31 -> 0.11607125
B37: Net Profit | C37: =C31-C34 -> 7654.69 | D37: =D31-D34 -> 9593.04 | E37: =E31-E34 -> 9122.43 | F37: =F31-F34 -> 4925.95 | G37: =G31-G34 -> 11216.63 | H37: =H31-H34 -> 3693.02 | I37: =I31-I34 -> 9948.67 | J37: =J31-J34 -> 12151.31 | ... M37: =M31-M34 -> 54779.08
B38: Net Margins | C38: =C37/C10 -> 0.095735394 | D38: =D37/D10 -> 0.13070192 | E38: =E37/E10 -> 0.11119153 | F38: =F37/F10 -> 0.055923761 | G38: =G37/G10 -> 0.11184582 | H38: =H37/H10 -> 0.033737289 | I38: =I37/I10 -> 0.08920082 | J38: =J37/J10 -> 0.091590985 | ... M38: =M37/M10 -> 0.29468268
B40: No of Equity Shares | C40: =IFERROR('Data Sheet'!B94,) -> 989.46 | D40: =IFERROR('Data Sheet'!C94,) -> 989.46 | E40: =IFERROR('Data Sheet'!D94,) -> 989.46 | F40: =IFERROR('Data Sheet'!E94,) -> 989.46 | G40: =IFERROR('Data Sheet'!F94,) -> 989.46 | H40: =IFERROR('Data Sheet'!G94,) -> 989.46 | I40: =IFERROR('Data Sheet'!H94,) -> 969.67 | J40: =IFERROR('Data Sheet'!I94,) -> 969.67 | ... L40: =IFERROR('Data Sheet'!K94,) -> 969.67 | M40: =L40 -> 969.67
B42: EPS | C42: =IFERROR(C37/C40,0) -> 7.7362299 | D42: =IFERROR(D37/D40,0) -> 9.6952277 | E42: =IFERROR(E37/E40,0) -> 9.2196046 | F42: =IFERROR(F37/F40,0) -> 4.9784226 | G42: =IFERROR(G37/G40,0) -> 11.336113 | H42: =IFERROR(H37/H40,0) -> 3.7323591 | I42: =IFERROR(I37/I40,0) -> 10.259851 | J42: =IFERROR(J37/J40,0) -> 12.531387 | ... M42: =IFERROR(M37/M40,0) -> 56.492497
B43: EPS Growth % | C43: - | D43: =IFERROR(D42/C42-1,0) -> 0.25322384 | E43: =IFERROR(E42/D42-1,0) -> -0.049057442 | F43: =IFERROR(F42/E42-1,0) -> -0.46001778 | G43: =IFERROR(G42/F42-1,0) -> 1.2770491 | H43: =IFERROR(H42/G42-1,0) -> -0.67075494 | I43: =IFERROR(I42/H42-1,0) -> 1.7488918 | J43: =IFERROR(J42/I42-1,0) -> 0.22140045 | K43: =IFERROR(K42/J42-1,0) -> 0.19825846 | ... M43: =IFERROR(M42/L42-1,0) -> 2.3935009
B45: Dividend per share | C45: =IFERROR('Data Sheet'!B31/HistoricalFS!C40,0) -> 2.0833182 | D45: =IFERROR('Data Sheet'!C31/HistoricalFS!D40,0) -> 2.791654 | E45: =IFERROR('Data Sheet'!D31/HistoricalFS!E40,0) -> 3.9833141 | F45: =IFERROR('Data Sheet'!E31/HistoricalFS!F40,0) -> 4.2666505 | G45: =IFERROR('Data Sheet'!F31/HistoricalFS!G40,0) -> 6.0799729 | H45: =IFERROR('Data Sheet'!G31/HistoricalFS!H40,0) -> 3.1499909 | I45: =IFERROR('Data Sheet'!H31/HistoricalFS!I40,0) -> 6.1499789 | J45: =IFERROR('Data Sheet'!I31/HistoricalFS!J40,0) -> 6.9999794 | ... M45: =IFERROR('Data Sheet'!L31/HistoricalFS!M40,0) -> 0
B46: Dividend payout ratio | C46: =IFERROR(C45/C42,0) -> 0.26929373 | D46: =IFERROR(D45/D42,0) -> 0.28794105 | E46: =IFERROR(E45/E42,0) -> 0.43204826 | F46: =IFERROR(F45/F42,0) -> 0.85702859 | G46: =IFERROR(G45/G42,0) -> 0.53633667 | H46: =IFERROR(H45/H42,0) -> 0.84396781 | I46: =IFERROR(I45/I42,0) -> 0.59942183 | J46: =IFERROR(J45/J42,0) -> 0.55859574 | ... M46: =IFERROR(M45/M42,0) -> 0
B48: Retained Earnings | C48: =IFERROR(IF(C42>C45,1-C46,0),0) -> 0.73070627 | D48: =IFERROR(IF(D42>D45,1-D46,0),0) -> 0.71205895 | E48: =IFERROR(IF(E42>E45,1-E46,0),0) -> 0.56795174 | F48: =IFERROR(IF(F42>F45,1-F46,0),0) -> 0.14297141 | G48: =IFERROR(IF(G42>G45,1-G46,0),0) -> 0.46366333 | H48: =IFERROR(IF(H42>H45,1-H46,0),0) -> 0.15603219 | I48: =IFERROR(IF(I42>I45,1-I46,0),0) -> 0.40057817 | J48: =IFERROR(IF(J42>J45,1-J46,0),0) -> 0.44140426 | ... M48: =IFERROR(IF(M42>M45,1-M46,0),0) -> 1
A53: # | B53: Balance Sheet
B54: Equity Share Capital | C54: =IFERROR('Data Sheet'!B58,0) -> 8245.46 | D54: =IFERROR('Data Sheet'!C58,0) -> 8245.46 | E54: =IFERROR('Data Sheet'!D58,0) -> 8245.46 | F54: =IFERROR('Data Sheet'!E58,0) -> 8245.46 | G54: =IFERROR('Data Sheet'!F58,0) -> 9894.56 | H54: =IFERROR('Data Sheet'!G58,0) -> 9894.56 | I54: =IFERROR('Data Sheet'!H58,0) -> 9696.67 | J54: =IFERROR('Data Sheet'!I58,0) -> 9696.67 | ... L54: =IFERROR('Data Sheet'!K58,0) -> 9696.67
B55: Reserves | C55: =IFERROR('Data Sheet'!B59,0) -> 73848.52 | D55: =IFERROR('Data Sheet'!C59,0) -> 83330.12 | E55: =IFERROR('Data Sheet'!D59,0) -> 89592.56 | F55: =IFERROR('Data Sheet'!E59,0) -> 95318.01 | G55: =IFERROR('Data Sheet'!F59,0) -> 101461.65 | H55: =IFERROR('Data Sheet'!G59,0) -> 108944.6 | I55: =IFERROR('Data Sheet'!H59,0) -> 116041.8 | J55: =IFERROR('Data Sheet'!I59,0) -> 125677.07 | ... L55: =IFERROR('Data Sheet'!K59,0) -> 151012.6
B56: Borrowings | C56: =IFERROR('Data Sheet'!B60,0) -> 102252 | D56: =IFERROR('Data Sheet'!C60,0) -> 99423.55 | E56: =IFERROR('Data Sheet'!D60,0) -> 113773.2 | F56: =IFERROR('Data Sheet'!E60,0) -> 130048.56 | G56: =IFERROR('Data Sheet'!F60,0) -> 173058.23 | H56: =IFERROR('Data Sheet'!G60,0) -> 202984.31 | I56: =IFERROR('Data Sheet'!H60,0) -> 210207.87 | J56: =IFERROR('Data Sheet'!I60,0) -> 210706.56 | ... L56: =IFERROR('Data Sheet'!K60,0) -> 237130.98
B57: Other Liabilities | C57: =IFERROR('Data Sheet'!B61,0) -> 35366.06 | D57: =IFERROR('Data Sheet'!C61,0) -> 33665.93 | E57: =IFERROR('Data Sheet'!D61,0) -> 36989.6 | F57: =IFERROR('Data Sheet'!E61,0) -> 48880.23 | G57: =IFERROR('Data Sheet'!F61,0) -> 62508.55 | H57: =IFERROR('Data Sheet'!G61,0) -> 55745.53 | I57: =IFERROR('Data Sheet'!H61,0) -> 62075.45 | J57: =IFERROR('Data Sheet'!I61,0) -> 69751.12 | ... L57: =IFERROR('Data Sheet'!K61,0) -> 81437.47
B58: Total Liability | C58: =IFERROR('Data Sheet'!B62,0) -> 219712.04 | D58: =IFERROR('Data Sheet'!C62,0) -> 224665.06 | E58: =IFERROR('Data Sheet'!D62,0) -> 248600.82 | F58: =IFERROR('Data Sheet'!E62,0) -> 282492.26 | G58: =IFERROR('Data Sheet'!F62,0) -> 346922.99 | H58: =IFERROR('Data Sheet'!G62,0) -> 377569 | I58: =IFERROR('Data Sheet'!H62,0) -> 398021.79 | J58: =IFERROR('Data Sheet'!I62,0) -> 415831.42 | ... L58: =IFERROR('Data Sheet'!K62,0) -> 479277.72
B60: Fixed Assets Net Block | C60: =IFERROR('Data Sheet'!B63,0) -> 91853.02 | D60: =IFERROR('Data Sheet'!C63,0) -> 92929.36 | E60: =IFERROR('Data Sheet'!D63,0) -> 104531.66 | F60: =IFERROR('Data Sheet'!E63,0) -> 128245.42 | G60: =IFERROR('Data Sheet'!F63,0) -> 150984.53 | H60: =IFERROR('Data Sheet'!G63,0) -> 187802.79 | I60: =IFERROR('Data Sheet'!H63,0) -> 203245.18 | J60: =IFERROR('Data Sheet'!I63,0) -> 224923.02 | ... L60: =IFERROR('Data Sheet'!K63,0) -> 258933.63
B61: Capital Work in Progress | C61: =IFERROR('Data Sheet'!B64,0) -> 67554.69 | D61: =IFERROR('Data Sheet'!C64,0) -> 75045.53 | E61: =IFERROR('Data Sheet'!D64,0) -> 86895.71 | F61: =IFERROR('Data Sheet'!E64,0) -> 83386.1 | G61: =IFERROR('Data Sheet'!F64,0) -> 118396.86 | H61: =IFERROR('Data Sheet'!G64,0) -> 98508.47 | I61: =IFERROR('Data Sheet'!H64,0) -> 97506.03 | J61: =IFERROR('Data Sheet'!I64,0) -> 91126.26 | ... L61: =IFERROR('Data Sheet'!K64,0) -> 87664.45
B62: Investments | C62: =IFERROR('Data Sheet'!B65,0) -> 1901.51 | D62: =IFERROR('Data Sheet'!C65,0) -> 6473.36 | E62: =IFERROR('Data Sheet'!D65,0) -> 7613.92 | F62: =IFERROR('Data Sheet'!E65,0) -> 8875.61 | G62: =IFERROR('Data Sheet'!F65,0) -> 8132.31 | H62: =IFERROR('Data Sheet'!G65,0) -> 9306.59 | I62: =IFERROR('Data Sheet'!H65,0) -> 10589.25 | J62: =IFERROR('Data Sheet'!I65,0) -> 10626.24 | ... L62: =IFERROR('Data Sheet'!K65,0) -> 15884.56
B63: Other Assets | C63: =IFERROR('Data Sheet'!B66-SUM('Data Sheet'!B68:B70),0) -> 26841.59 | D63: =IFERROR('Data Sheet'!C66-SUM('Data Sheet'!C68:C70),0) -> 29845.15 | E63: =IFERROR('Data Sheet'!D66-SUM('Data Sheet'!D68:D70),0) -> 30604.59 | F63: =IFERROR('Data Sheet'!E66-SUM('Data Sheet'!E68:E70),0) -> 42514.46 | G63: =IFERROR('Data Sheet'!F66-SUM('Data Sheet'!F68:F70),0) -> 45598.89 | H63: =IFERROR('Data Sheet'!G66-SUM('Data Sheet'!G68:G70),0) -> 47103.57 | I63: =IFERROR('Data Sheet'!H66-SUM('Data Sheet'!H68:H70),0) -> 44074.06 | J63: =IFERROR('Data Sheet'!I66-SUM('Data Sheet'!I68:I70),0) -> 46356.95 | ... L63: =IFERROR('Data Sheet'!K66-SUM('Data Sheet'!K68:K70),0) -> 58327.89
B64: Total Non Current Assets | C64: =IFERROR(SUM(C60:C63),0) -> 188150.81 | D64: =IFERROR(SUM(D60:D63),0) -> 204293.4 | E64: =IFERROR(SUM(E60:E63),0) -> 229645.88 | F64: =IFERROR(SUM(F60:F63),0) -> 263021.59 | G64: =IFERROR(SUM(G60:G63),0) -> 323112.59 | H64: =IFERROR(SUM(H60:H63),0) -> 342721.42 | I64: =IFERROR(SUM(I60:I63),0) -> 355414.52 | J64: =IFERROR(SUM(J60:J63),0) -> 373032.47 | ... L64: =IFERROR(SUM(L60:L63),0) -> 420810.53
B66: Receivables | C66: =IFERROR('Data Sheet'!B68,0) -> 9249.92 | D66: =IFERROR('Data Sheet'!C68,0) -> 8288.79 | E66: =IFERROR('Data Sheet'!D68,0) -> 8963.89 | F66: =IFERROR('Data Sheet'!E68,0) -> 8812.19 | G66: =IFERROR('Data Sheet'!F68,0) -> 12363.52 | H66: =IFERROR('Data Sheet'!G68,0) -> 20314.59 | I66: =IFERROR('Data Sheet'!H68,0) -> 28199.83 | J66: =IFERROR('Data Sheet'!I68,0) -> 27970.87 | ... L66: =IFERROR('Data Sheet'!K68,0) -> 33349.68
B67: Inventory | C67: =IFERROR('Data Sheet'!B69,0) -> 8059.7 | D67: =IFERROR('Data Sheet'!C69,0) -> 7144.55 | E67: =IFERROR('Data Sheet'!D69,0) -> 6689.59 | F67: =IFERROR('Data Sheet'!E69,0) -> 6270.88 | G67: =IFERROR('Data Sheet'!F69,0) -> 8513.45 | H67: =IFERROR('Data Sheet'!G69,0) -> 11318.7 | I67: =IFERROR('Data Sheet'!H69,0) -> 10019.64 | J67: =IFERROR('Data Sheet'!I69,0) -> 10370 | ... L67: =IFERROR('Data Sheet'!K69,0) -> 18270.17
B68: Cash & Bank | C68: =IFERROR('Data Sheet'!B70,0) -> 14251.61 | D68: =IFERROR('Data Sheet'!C70,0) -> 4938.32 | E68: =IFERROR('Data Sheet'!D70,0) -> 3301.46 | F68: =IFERROR('Data Sheet'!E70,0) -> 4387.6 | G68: =IFERROR('Data Sheet'!F70,0) -> 2933.43 | H68: =IFERROR('Data Sheet'!G70,0) -> 3214.29 | I68: =IFERROR('Data Sheet'!H70,0) -> 4387.8 | J68: =IFERROR('Data Sheet'!I70,0) -> 4458.08 | ... L68: =IFERROR('Data Sheet'!K70,0) -> 6847.34
B69: Total Current Assets | C69: =IFERROR(SUM(C66:C68),0) -> 31561.23 | D69: =IFERROR(SUM(D66:D68),0) -> 20371.66 | E69: =IFERROR(SUM(E66:E68),0) -> 18954.94 | F69: =IFERROR(SUM(F66:F68),0) -> 19470.67 | G69: =IFERROR(SUM(G66:G68),0) -> 23810.4 | H69: =IFERROR(SUM(H66:H68),0) -> 34847.58 | I69: =IFERROR(SUM(I66:I68),0) -> 42607.27 | J69: =IFERROR(SUM(J66:J68),0) -> 42798.95 | ... L69: =IFERROR(SUM(L66:L68),0) -> 58467.19
B71: Total Assets | C71: =IFERROR(SUM(C69+C64),0) -> 219712.04 | D71: =IFERROR(SUM(D69,D64),0) -> 224665.06 | E71: =IFERROR(SUM(E69,E64),0) -> 248600.82 | F71: =IFERROR(SUM(F69,F64),0) -> 282492.26 | G71: =IFERROR(SUM(G69,G64),0) -> 346922.99 | H71: =IFERROR(SUM(H69,H64),0) -> 377569 | I71: =IFERROR(SUM(I69,I64),0) -> 398021.79 | J71: =IFERROR(SUM(J69,J64),0) -> 415831.42 | K71: =IFERROR(SUM(K69,K64),0) -> 447188.89 | L71: =IFERROR(SUM(L69,L64),0) -> 479277.72
B73: Check | C73: =C71=C58 -> TRUE | D73: =D71=D58 -> TRUE | E73: =E71=E58 -> TRUE | F73: =F71=F58 -> TRUE | G73: =G71=G58 -> TRUE | H73: =H71=H58 -> TRUE | I73: =I71=I58 -> TRUE | J73: =J71=J58 -> TRUE | ... L73: =L71=L58 -> TRUE
A75: # | B75: Cash Flow Statement
B76: Operating Activities
B77: Profit from operations | C77: =IFERROR('Cash Flow Statement'!E4,0) -> 43397 | D77: =IFERROR('Cash Flow Statement'!F4,0) -> 38626 | E77: =IFERROR('Cash Flow Statement'!G4,0) -> 28840 | F77: =IFERROR('Cash Flow Statement'!H4,0) -> 33312 | G77: =IFERROR('Cash Flow Statement'!I4,0) -> 28771 | H77: =IFERROR('Cash Flow Statement'!J4,0) -> 23352 | I77: =IFERROR('Cash Flow Statement'!K4,0) -> 31198 | J77: =IFERROR('Cash Flow Statement'!L4,0) -> 26943 | ... L77: =IFERROR('Cash Flow Statement'!N4,0) -> 65106
B78: Receivables | C78: =IFERROR('Cash Flow Statement'!E5,0) -> -3179 | D78: =IFERROR('Cash Flow Statement'!F5,0) -> -2223 | E78: =IFERROR('Cash Flow Statement'!G5,0) -> -4152 | F78: =IFERROR('Cash Flow Statement'!H5,0) -> -10688 | G78: =IFERROR('Cash Flow Statement'!I5,0) -> -9109 | H78: =IFERROR('Cash Flow Statement'!J5,0) -> 9950 | I78: =IFERROR('Cash Flow Statement'!K5,0) -> -5505 | J78: =IFERROR('Cash Flow Statement'!L5,0) -> 185 | ... L78: =IFERROR('Cash Flow Statement'!N5,0) -> -1875
B79: Inventory | C79: =IFERROR('Cash Flow Statement'!E6,0) -> -3692 | D79: =IFERROR('Cash Flow Statement'!F6,0) -> -5743 | E79: =IFERROR('Cash Flow Statement'!G6,0) -> -6621 | F79: =IFERROR('Cash Flow Statement'!H6,0) -> -3560 | G79: =IFERROR('Cash Flow Statement'!I6,0) -> 2069 | H79: =IFERROR('Cash Flow Statement'!J6,0) -> 2326 | I79: =IFERROR('Cash Flow Statement'!K6,0) -> 3814 | J79: =IFERROR('Cash Flow Statement'!L6,0) -> 472 | ... L79: =IFERROR('Cash Flow Statement'!N6,0) -> -7265
B80: Payables | C80: =IFERROR('Cash Flow Statement'!E7,0) -> 3598 | D80: =IFERROR('Cash Flow Statement'!F7,0) -> 3947 | E80: =IFERROR('Cash Flow Statement'!G7,0) -> 9301 | F80: =IFERROR('Cash Flow Statement'!H7,0) -> 7320 | G80: =IFERROR('Cash Flow Statement'!I7,0) -> -4692 | H80: =IFERROR('Cash Flow Statement'!J7,0) -> -8085 | I80: =IFERROR('Cash Flow Statement'!K7,0) -> 5748 | J80: =IFERROR('Cash Flow Statement'!L7,0) -> -7012 | ... L80: =IFERROR('Cash Flow Statement'!N7,0) -> 13706
B81: Loans Advances | C81: =IFERROR('Cash Flow Statement'!E8,0) -> 0 | D81: =IFERROR('Cash Flow Statement'!F8,0) -> -520 | E81: =IFERROR('Cash Flow Statement'!G8,0) -> 0 | F81: =IFERROR('Cash Flow Statement'!H8,0) -> 0 | G81: =IFERROR('Cash Flow Statement'!I8,0) -> 0 | H81: =IFERROR('Cash Flow Statement'!J8,0) -> 0 | I81: =IFERROR('Cash Flow Statement'!K8,0) -> 0 | J81: =IFERROR('Cash Flow Statement'!L8,0) -> 0 | ... L81: =IFERROR('Cash Flow Statement'!N8,0) -> 0
B82: Other WC items | C82: =IFERROR('Cash Flow Statement'!E9,0) -> -398 | D82: =IFERROR('Cash Flow Statement'!F9,0) -> 5852 | E82: =IFERROR('Cash Flow Statement'!G9,0) -> 4727 | F82: =IFERROR('Cash Flow Statement'!H9,0) -> 494 | G82: =IFERROR('Cash Flow Statement'!I9,0) -> 4512 | H82: =IFERROR('Cash Flow Statement'!J9,0) -> 875 | I82: =IFERROR('Cash Flow Statement'!K9,0) -> -4150 | J82: =IFERROR('Cash Flow Statement'!L9,0) -> -4396 | ... L82: =IFERROR('Cash Flow Statement'!N9,0) -> 2760
B83: Working capital changes | C83: =IFERROR('Cash Flow Statement'!E10,0) -> -3672 | D83: =IFERROR('Cash Flow Statement'!F10,0) -> 1313 | E83: =IFERROR('Cash Flow Statement'!G10,0) -> 3254 | F83: =IFERROR('Cash Flow Statement'!H10,0) -> -6434 | G83: =IFERROR('Cash Flow Statement'!I10,0) -> -7221 | H83: =IFERROR('Cash Flow Statement'!J10,0) -> 5065 | I83: =IFERROR('Cash Flow Statement'!K10,0) -> -93 | J83: =IFERROR('Cash Flow Statement'!L10,0) -> -10750 | ... L83: =IFERROR('Cash Flow Statement'!N10,0) -> 7325
B84: Direct taxes | C84: =IFERROR('Cash Flow Statement'!E11,0) -> -4194 | D84: =IFERROR('Cash Flow Statement'!F11,0) -> -2040 | E84: =IFERROR('Cash Flow Statement'!G11,0) -> -1895 | F84: =IFERROR('Cash Flow Statement'!H11,0) -> -3021 | G84: =IFERROR('Cash Flow Statement'!I11,0) -> -2659 | H84: =IFERROR('Cash Flow Statement'!J11,0) -> -1785 | I84: =IFERROR('Cash Flow Statement'!K11,0) -> -2105 | J84: =IFERROR('Cash Flow Statement'!L11,0) -> -1910 | ... L84: =IFERROR('Cash Flow Statement'!N11,0) -> -4516
B85: Cash From operating Activities | C85: =IFERROR('Cash Flow Statement'!E3,0) -> 35531 | D85: =IFERROR('Cash Flow Statement'!F3,0) -> 37900 | E85: =IFERROR('Cash Flow Statement'!G3,0) -> 30199 | F85: =IFERROR('Cash Flow Statement'!H3,0) -> 23857 | G85: =IFERROR('Cash Flow Statement'!I3,0) -> 18891 | H85: =IFERROR('Cash Flow Statement'!J3,0) -> 26633 | I85: =IFERROR('Cash Flow Statement'!K3,0) -> 29001 | J85: =IFERROR('Cash Flow Statement'!L3,0) -> 14283 | ... L85: =IFERROR('Cash Flow Statement'!N3,0) -> 67915
B87: Investing Activites
B88: Fixed assets purchased | C88: =IFERROR('Cash Flow Statement'!E13,0) -> -31962 | D88: =IFERROR('Cash Flow Statement'!F13,0) -> -31503 | E88: =IFERROR('Cash Flow Statement'!G13,0) -> -16072 | F88: =IFERROR('Cash Flow Statement'!H13,0) -> -35079 | G88: =IFERROR('Cash Flow Statement'!I13,0) -> -35304 | H88: =IFERROR('Cash Flow Statement'!J13,0) -> -29702 | I88: =IFERROR('Cash Flow Statement'!K13,0) -> -20205 | J88: =IFERROR('Cash Flow Statement'!L13,0) -> -15168 | ... L88: =IFERROR('Cash Flow Statement'!N13,0) -> -31414
B89: Fixed assets sold | C89: =IFERROR('Cash Flow Statement'!E14,0) -> 74 | D89: =IFERROR('Cash Flow Statement'!F14,0) -> 59 | E89: =IFERROR('Cash Flow Statement'!G14,0) -> 53 | F89: =IFERROR('Cash Flow Statement'!H14,0) -> 30 | G89: =IFERROR('Cash Flow Statement'!I14,0) -> 67 | H89: =IFERROR('Cash Flow Statement'!J14,0) -> 171 | I89: =IFERROR('Cash Flow Statement'!K14,0) -> 351 | J89: =IFERROR('Cash Flow Statement'!L14,0) -> 230 | ... L89: =IFERROR('Cash Flow Statement'!N14,0) -> 231
B90: Investments purchased | C90: =IFERROR('Cash Flow Statement'!E15,0) -> -5461 | D90: =IFERROR('Cash Flow Statement'!F15,0) -> -4728 | E90: =IFERROR('Cash Flow Statement'!G15,0) -> -6 | F90: =IFERROR('Cash Flow Statement'!H15,0) -> -329 | G90: =IFERROR('Cash Flow Statement'!I15,0) -> -130 | H90: =IFERROR('Cash Flow Statement'!J15,0) -> -1439 | I90: =IFERROR('Cash Flow Statement'!K15,0) -> -7530 | J90: =IFERROR('Cash Flow Statement'!L15,0) -> -3008 | ... L90: =IFERROR('Cash Flow Statement'!N15,0) -> -74
B91: Investments sold | C91: =IFERROR('Cash Flow Statement'!E16,0) -> 42 | D91: =IFERROR('Cash Flow Statement'!F16,0) -> 89 | E91: =IFERROR('Cash Flow Statement'!G16,0) -> 1965 | F91: =IFERROR('Cash Flow Statement'!H16,0) -> 2381 | G91: =IFERROR('Cash Flow Statement'!I16,0) -> 5644 | H91: =IFERROR('Cash Flow Statement'!J16,0) -> 21 | I91: =IFERROR('Cash Flow Statement'!K16,0) -> 226 | J91: =IFERROR('Cash Flow Statement'!L16,0) -> 104 | ... L91: =IFERROR('Cash Flow Statement'!N16,0) -> 10820
B92: Interest received | C92: =IFERROR('Cash Flow Statement'!E17,0) -> 698 | D92: =IFERROR('Cash Flow Statement'!F17,0) -> 731 | E92: =IFERROR('Cash Flow Statement'!G17,0) -> 638 | F92: =IFERROR('Cash Flow Statement'!H17,0) -> 690 | G92: =IFERROR('Cash Flow Statement'!I17,0) -> 761 | H92: =IFERROR('Cash Flow Statement'!J17,0) -> 1104 | I92: =IFERROR('Cash Flow Statement'!K17,0) -> 428 | J92: =IFERROR('Cash Flow Statement'!L17,0) -> 653 | ... L92: =IFERROR('Cash Flow Statement'!N17,0) -> 2493
B93: Dividends received | C93: =IFERROR('Cash Flow Statement'!E18,0) -> 80 | D93: =IFERROR('Cash Flow Statement'!F18,0) -> 58 | E93: =IFERROR('Cash Flow Statement'!G18,0) -> 620 | F93: =IFERROR('Cash Flow Statement'!H18,0) -> 1797 | G93: =IFERROR('Cash Flow Statement'!I18,0) -> 232 | H93: =IFERROR('Cash Flow Statement'!J18,0) -> 21 | I93: =IFERROR('Cash Flow Statement'!K18,0) -> 18 | J93: =IFERROR('Cash Flow Statement'!L18,0) -> 32 | ... L93: =IFERROR('Cash Flow Statement'!N18,0) -> 47
B94: Investment in group cos | C94: =IFERROR('Cash Flow Statement'!E19,0) -> -160 | D94: =IFERROR('Cash Flow Statement'!F19,0) -> 0 | E94: =IFERROR('Cash Flow Statement'!G19,0) -> -107 | F94: =IFERROR('Cash Flow Statement'!H19,0) -> -4 | G94: =IFERROR('Cash Flow Statement'!I19,0) -> -9 | H94: =IFERROR('Cash Flow Statement'!J19,0) -> -606 | I94: =IFERROR('Cash Flow Statement'!K19,0) -> -10 | J94: =IFERROR('Cash Flow Statement'!L19,0) -> 0 | ... L94: =IFERROR('Cash Flow Statement'!N19,0) -> -150
B95: Redemp n Canc of Shares | C95: =IFERROR('Cash Flow Statement'!E20,0) -> 0 | D95: =IFERROR('Cash Flow Statement'!F20,0) -> 0 | E95: =IFERROR('Cash Flow Statement'!G20,0) -> 0 | F95: =IFERROR('Cash Flow Statement'!H20,0) -> 14 | G95: =IFERROR('Cash Flow Statement'!I20,0) -> 533 | H95: =IFERROR('Cash Flow Statement'!J20,0) -> 0 | I95: =IFERROR('Cash Flow Statement'!K20,0) -> 0 | J95: =IFERROR('Cash Flow Statement'!L20,0) -> 0 | ... L95: =IFERROR('Cash Flow Statement'!N20,0) -> 108
B96: Acquisition of companies | C96: =IFERROR('Cash Flow Statement'!E21,0) -> 0 | D96: =IFERROR('Cash Flow Statement'!F21,0) -> -111 | E96: =IFERROR('Cash Flow Statement'!G21,0) -> 0 | F96: =IFERROR('Cash Flow Statement'!H21,0) -> 0 | G96: =IFERROR('Cash Flow Statement'!I21,0) -> -8 | H96: =IFERROR('Cash Flow Statement'!J21,0) -> -27 | I96: =IFERROR('Cash Flow Statement'!K21,0) -> 0 | J96: =IFERROR('Cash Flow Statement'!L21,0) -> -98 | ... L96: =IFERROR('Cash Flow Statement'!N21,0) -> 0
B97: Inter corporate deposits | C97: =IFERROR('Cash Flow Statement'!E22,0) -> 0 | D97: =IFERROR('Cash Flow Statement'!F22,0) -> 0 | E97: =IFERROR('Cash Flow Statement'!G22,0) -> 0 | F97: =IFERROR('Cash Flow Statement'!H22,0) -> 0 | G97: =IFERROR('Cash Flow Statement'!I22,0) -> 0 | H97: =IFERROR('Cash Flow Statement'!J22,0) -> 0 | I97: =IFERROR('Cash Flow Statement'!K22,0) -> 0 | J97: =IFERROR('Cash Flow Statement'!L22,0) -> 0 | ... L97: =IFERROR('Cash Flow Statement'!N22,0) -> -24
B98: Other investing items | C98: =IFERROR('Cash Flow Statement'!E23,0) -> 456 | D98: =IFERROR('Cash Flow Statement'!F23,0) -> -1289 | E98: =IFERROR('Cash Flow Statement'!G23,0) -> -26663 | F98: =IFERROR('Cash Flow Statement'!H23,0) -> 5360 | G98: =IFERROR('Cash Flow Statement'!I23,0) -> 7335 | H98: =IFERROR('Cash Flow Statement'!J23,0) -> -2659 | I98: =IFERROR('Cash Flow Statement'!K23,0) -> 1051 | J98: =IFERROR('Cash Flow Statement'!L23,0) -> 12813 | ... L98: =IFERROR('Cash Flow Statement'!N23,0) -> -4817
B99: Cash form Investing Activites | C99: =IFERROR('Cash Flow Statement'!E12,0) -> -36232 | D99: =IFERROR('Cash Flow Statement'!F12,0) -> -36694 | E99: =IFERROR('Cash Flow Statement'!G12,0) -> -39571 | F99: =IFERROR('Cash Flow Statement'!H12,0) -> -25139 | G99: =IFERROR('Cash Flow Statement'!I12,0) -> -20878 | H99: =IFERROR('Cash Flow Statement'!J12,0) -> -33115 | I99: =IFERROR('Cash Flow Statement'!K12,0) -> -25672 | J99: =IFERROR('Cash Flow Statement'!L12,0) -> -4444 | ... L99: =IFERROR('Cash Flow Statement'!N12,0) -> -22782
B101: Financing Activties
B102: Proceeds from shares | C102: =IFERROR('Cash Flow Statement'!E24,0) -> 5201 | D102: =IFERROR('Cash Flow Statement'!F24,0) -> -3795 | E102: =IFERROR('Cash Flow Statement'!G24,0) -> 6205 | F102: =IFERROR('Cash Flow Statement'!H24,0) -> 2012 | G102: =IFERROR('Cash Flow Statement'!I24,0) -> 8830 | H102: =IFERROR('Cash Flow Statement'!J24,0) -> 3390 | I102: =IFERROR('Cash Flow Statement'!K24,0) -> 9904 | J102: =IFERROR('Cash Flow Statement'!L24,0) -> -3380 | ... L102: =IFERROR('Cash Flow Statement'!N24,0) -> -37006
B103: Redemption of debentures | C103: =IFERROR('Cash Flow Statement'!E25,0) -> 0 | D103: =IFERROR('Cash Flow Statement'!F25,0) -> 7433 | E103: =IFERROR('Cash Flow Statement'!G25,0) -> 5 | F103: =IFERROR('Cash Flow Statement'!H25,0) -> 0 | G103: =IFERROR('Cash Flow Statement'!I25,0) -> 0 | H103: =IFERROR('Cash Flow Statement'!J25,0) -> 3889 | I103: =IFERROR('Cash Flow Statement'!K25,0) -> 2603 | J103: =IFERROR('Cash Flow Statement'!L25,0) -> 19 | ... L103: =IFERROR('Cash Flow Statement'!N25,0) -> 82
B104: Proceeds from borrowings | C104: =IFERROR('Cash Flow Statement'!E26,0) -> -744 | D104: =IFERROR('Cash Flow Statement'!F26,0) -> 0 | E104: =IFERROR('Cash Flow Statement'!G26,0) -> 0 | F104: =IFERROR('Cash Flow Statement'!H26,0) -> 0 | G104: =IFERROR('Cash Flow Statement'!I26,0) -> 0 | H104: =IFERROR('Cash Flow Statement'!J26,0) -> 0 | I104: =IFERROR('Cash Flow Statement'!K26,0) -> 0 | J104: =IFERROR('Cash Flow Statement'!L26,0) -> 0 | ... L104: =IFERROR('Cash Flow Statement'!N26,0) -> 0
B105: Repayment of borrowings | C105: =IFERROR('Cash Flow Statement'!E27,0) -> 36363 | D105: =IFERROR('Cash Flow Statement'!F27,0) -> 19519 | E105: =IFERROR('Cash Flow Statement'!G27,0) -> 33390 | F105: =IFERROR('Cash Flow Statement'!H27,0) -> 37482 | G105: =IFERROR('Cash Flow Statement'!I27,0) -> 51128 | H105: =IFERROR('Cash Flow Statement'!J27,0) -> 38297 | I105: =IFERROR('Cash Flow Statement'!K27,0) -> 46641 | J105: =IFERROR('Cash Flow Statement'!L27,0) -> 46578 | ... L105: =IFERROR('Cash Flow Statement'!N27,0) -> 18747
B106: Interest paid fin | C106: =IFERROR('Cash Flow Statement'!E28,0) -> -23332 | D106: =IFERROR('Cash Flow Statement'!F28,0) -> -24924 | E106: =IFERROR('Cash Flow Statement'!G28,0) -> -21732 | F106: =IFERROR('Cash Flow Statement'!H28,0) -> -29964 | G106: =IFERROR('Cash Flow Statement'!I28,0) -> -35198 | H106: =IFERROR('Cash Flow Statement'!J28,0) -> -29847 | I106: =IFERROR('Cash Flow Statement'!K28,0) -> -29709 | J106: =IFERROR('Cash Flow Statement'!L28,0) -> -42816 | ... L106: =IFERROR('Cash Flow Statement'!N28,0) -> -47332
B107: Dividends paid | C107: =IFERROR('Cash Flow Statement'!E29,0) -> -6307 | D107: =IFERROR('Cash Flow Statement'!F29,0) -> -5716 | E107: =IFERROR('Cash Flow Statement'!G29,0) -> -5336 | F107: =IFERROR('Cash Flow Statement'!H29,0) -> -5411 | G107: =IFERROR('Cash Flow Statement'!I29,0) -> -7005 | H107: =IFERROR('Cash Flow Statement'!J29,0) -> -7518 | I107: =IFERROR('Cash Flow Statement'!K29,0) -> -8123 | J107: =IFERROR('Cash Flow Statement'!L29,0) -> -9251 | ... L107: =IFERROR('Cash Flow Statement'!N29,0) -> -9332
B108: Financial liabilities | C108: =IFERROR('Cash Flow Statement'!E30,0) -> -720 | D108: =IFERROR('Cash Flow Statement'!F30,0) -> -108 | E108: =IFERROR('Cash Flow Statement'!G30,0) -> -121 | F108: =IFERROR('Cash Flow Statement'!H30,0) -> -96 | G108: =IFERROR('Cash Flow Statement'!I30,0) -> -95 | H108: =IFERROR('Cash Flow Statement'!J30,0) -> -57 | I108: =IFERROR('Cash Flow Statement'!K30,0) -> -30 | J108: =IFERROR('Cash Flow Statement'!L30,0) -> -100 | ... L108: =IFERROR('Cash Flow Statement'!N30,0) -> -1059
B109: Other financing items | C109: =IFERROR('Cash Flow Statement'!E31,0) -> 0 | D109: =IFERROR('Cash Flow Statement'!F31,0) -> 0 | E109: =IFERROR('Cash Flow Statement'!G31,0) -> 0 | F109: =IFERROR('Cash Flow Statement'!H31,0) -> 0 | G109: =IFERROR('Cash Flow Statement'!I31,0) -> 0 | H109: =IFERROR('Cash Flow Statement'!J31,0) -> -1346 | I109: =IFERROR('Cash Flow Statement'!K31,0) -> -1477 | J109: =IFERROR('Cash Flow Statement'!L31,0) -> -1559 | ... L109: =IFERROR('Cash Flow Statement'!N31,0) -> -1924
B110: Cash From Financing Activities | C110: =IFERROR('Cash Flow Statement'!E24,0) -> 5201 | D110: =IFERROR('Cash Flow Statement'!F24,0) -> -3795 | E110: =IFERROR('Cash Flow Statement'!G24,0) -> 6205 | F110: =IFERROR('Cash Flow Statement'!H24,0) -> 2012 | G110: =IFERROR('Cash Flow Statement'!I24,0) -> 8830 | H110: =IFERROR('Cash Flow Statement'!J24,0) -> 3390 | I110: =IFERROR('Cash Flow Statement'!K24,0) -> 9904 | J110: =IFERROR('Cash Flow Statement'!L24,0) -> -3380 | ... L110: =IFERROR('Cash Flow Statement'!N24,0) -> -37006
B112: Net Cash Flows | C112: =IFERROR(SUM(C85,C99,C110),0) -> 4500 | D112: =IFERROR(SUM(D85,D99,D110),0) -> -2589 | E112: =IFERROR(SUM(E85,E99,E110),0) -> -3167 | F112: =IFERROR(SUM(F85,F99,F110),0) -> 730 | G112: =IFERROR(SUM(G85,G99,G110),0) -> 6843 | H112: =IFERROR(SUM(H85,H99,H110),0) -> -3092 | I112: =IFERROR(SUM(I85,I99,I110),0) -> 13233 | J112: =IFERROR(SUM(J85,J99,J110),0) -> 6459 | ... L112: =IFERROR(SUM(L85,L99,L110),0) -> 8127
A125: # | B125: Cash Flow Statement
B126: Report Date | C126: 42094 | D126: 42460 | E126: 42825 | F126: 43190 | G126: 43555 | H126: 43921 | I126: 44286 | J126: 44651 | K126: 45016 | L126: 45382
B127: Cash from Operating Activity | C127: =IFERROR('Data Sheet'!B83,0) -> 14888.53 | D127: =IFERROR('Data Sheet'!C83,0) -> 24124.87 | E127: =IFERROR('Data Sheet'!D83,0) -> 20166.56 | F127: =IFERROR('Data Sheet'!E83,0) -> 19669.61 | G127: =IFERROR('Data Sheet'!F83,0) -> 18685.65 | H127: =IFERROR('Data Sheet'!G83,0) -> 23889.67 | I127: =IFERROR('Data Sheet'!H83,0) -> 32444.06 | J127: =IFERROR('Data Sheet'!I83,0) -> 41788.23 | ... L127: =IFERROR('Data Sheet'!K83,0) -> 40784.59
B128: Cash from Investing Activity | C128: =IFERROR('Data Sheet'!B84,0) -> -15977.16 | D128: =IFERROR('Data Sheet'!C84,0) -> -19161.54 | E128: =IFERROR('Data Sheet'!D84,0) -> -24480.13 | F128: =IFERROR('Data Sheet'!E84,0) -> -20678.11 | G128: =IFERROR('Data Sheet'!F84,0) -> -24063.28 | H128: =IFERROR('Data Sheet'!G84,0) -> -29628.15 | I128: =IFERROR('Data Sheet'!H84,0) -> -21034.45 | J128: =IFERROR('Data Sheet'!I84,0) -> -22890.92 | ... L128: =IFERROR('Data Sheet'!K84,0) -> -32141.37
B129: Cash from Financing Activity | C129: =IFERROR('Data Sheet'!B85,0) -> -1474.5 | D129: =IFERROR('Data Sheet'!C85,0) -> -3899.34 | E129: =IFERROR('Data Sheet'!D85,0) -> 3137.96 | F129: =IFERROR('Data Sheet'!E85,0) -> 1027.78 | G129: =IFERROR('Data Sheet'!F85,0) -> 4926.75 | H129: =IFERROR('Data Sheet'!G85,0) -> 6004.26 | I129: =IFERROR('Data Sheet'!H85,0) -> -11049.11 | J129: =IFERROR('Data Sheet'!I85,0) -> -19171.56 | ... L129: =IFERROR('Data Sheet'!K85,0) -> -8245.53
B130: Net Cash Flow | C130: =IFERROR('Data Sheet'!B86,0) -> -2563.13 | D130: =IFERROR('Data Sheet'!C86,0) -> 1063.99 | E130: =IFERROR('Data Sheet'!D86,0) -> -1175.61 | F130: =IFERROR('Data Sheet'!E86,0) -> 19.28 | G130: =IFERROR('Data Sheet'!F86,0) -> -450.88 | H130: =IFERROR('Data Sheet'!G86,0) -> 265.78 | I130: =IFERROR('Data Sheet'!H86,0) -> 360.5 | J130: =IFERROR('Data Sheet'!I86,0) -> -274.25 | ... L130: =IFERROR('Data Sheet'!K86,0) -> 397.69

Sheet Common Size Statement
B3: =B7 -> Common Size Income Statement -NTPC LTD
B7: ="Common Size Income Statement" & " "& "-" & 'Data Sheet'!$B$1 -> Common Size Income Statement -NTPC LTD
B9: Particulars | C9: ='Data Sheet'!B16 -> 42094 | D9: ='Data Sheet'!C16 -> 42460 | E9: ='Data Sheet'!D16 -> 42825 | F9: ='Data Sheet'!E16 -> 43190 | G9: ='Data Sheet'!F16 -> 43555 | H9: ='Data Sheet'!G16 -> 43921 | I9: ='Data Sheet'!H16 -> 44286 | J9: ='Data Sheet'!I16 -> 44651 | ... L9: ='Data Sheet'!K16 -> 45382
B11: ='Data Sheet'!A17 -> Sales | C11: ='Data Sheet'!B17/'Data Sheet'!B$17 -> 1 | D11: ='Data Sheet'!C17/'Data Sheet'!C$17 -> 1 | E11: ='Data Sheet'!D17/'Data Sheet'!D$17 -> 1 | F11: ='Data Sheet'!E17/'Data Sheet'!E$17 -> 1 | G11: ='Data Sheet'!F17/'Data Sheet'!F$17 -> 1 | H11: ='Data Sheet'!G17/'Data Sheet'!G$17 -> 1 | I11: ='Data Sheet'!H17/'Data Sheet'!H$17 -> 1 | J11: ='Data Sheet'!I17/'Data Sheet'!I$17 -> 1 | ... L11: ='Data Sheet'!K17/'Data Sheet'!K$17 -> 1
B12: ='Data Sheet'!A18 -> Raw Material Cost | C12: ='Data Sheet'!B18/'Data Sheet'!B$17 -> 0 | D12: ='Data Sheet'!C18/'Data Sheet'!C$17 -> 0 | E12: ='Data Sheet'!D18/'Data Sheet'!D$17 -> 0 | F12: ='Data Sheet'!E18/'Data Sheet'!E$17 -> 0 | G12: ='Data Sheet'!F18/'Data Sheet'!F$17 -> 0 | H12: ='Data Sheet'!G18/'Data Sheet'!G$17 -> 0 | I12: ='Data Sheet'!H18/'Data Sheet'!H$17 -> 0 | J12: ='Data Sheet'!I18/'Data Sheet'!I$17 -> 0 | ... L12: ='Data Sheet'!K18/'Data Sheet'!K$17 -> 0
B13: ='Data Sheet'!A19 -> Change in Inventory | C13: ='Data Sheet'!B19/'Data Sheet'!B$17 -> -5.803138e-05 | D13: ='Data Sheet'!C19/'Data Sheet'!C$17 -> 0 | E13: ='Data Sheet'!D19/'Data Sheet'!D$17 -> 0 | F13: ='Data Sheet'!E19/'Data Sheet'!E$17 -> 0 | G13: ='Data Sheet'!F19/'Data Sheet'!F$17 -> 0 | H13: ='Data Sheet'!G19/'Data Sheet'!G$17 -> 0 | I13: ='Data Sheet'!H19/'Data Sheet'!H$17 -> 0 | J13: ='Data Sheet'!I19/'Data Sheet'!I$17 -> 0 | ... L13: ='Data Sheet'!K19/'Data Sheet'!K$17 -> 0
B14: ='Data Sheet'!A20 -> Power and Fuel | C14: ='Data Sheet'!B20/'Data Sheet'!B$17 -> 0.67871952 | D14: ='Data Sheet'!C20/'Data Sheet'!C$17 -> 0.65026816 | E14: ='Data Sheet'!D20/'Data Sheet'!D$17 -> 0.64052724 | F14: ='Data Sheet'!E20/'Data Sheet'!E$17 -> 0.63224883 | G14: ='Data Sheet'!F20/'Data Sheet'!F$17 -> 0.62672967 | H14: ='Data Sheet'!G20/'Data Sheet'!G$17 -> 0.60204931 | I14: ='Data Sheet'!H20/'Data Sheet'!H$17 -> 0.58118974 | J14: ='Data Sheet'!I20/'Data Sheet'!I$17 -> 0.59829389 | ... L14: ='Data Sheet'!K20/'Data Sheet'!K$17 -> 0.62679198
B15: ='Data Sheet'!A21 -> Other Mfr. Exp | C15: ='Data Sheet'!B21/'Data Sheet'!B$17 -> 0.04158186 | D15: ='Data Sheet'!C21/'Data Sheet'!C$17 -> 0.030389807 | E15: ='Data Sheet'!D21/'Data Sheet'!D$17 -> 0.031246736 | F15: ='Data Sheet'!E21/'Data Sheet'!E$17 -> 0.033341844 | G15: ='Data Sheet'!F21/'Data Sheet'!F$17 -> 0.03460245 | H15: ='Data Sheet'!G21/'Data Sheet'!G$17 -> 0.0348963 | I15: ='Data Sheet'!H21/'Data Sheet'!H$17 -> 0.038337899 | J15: ='Data Sheet'!I21/'Data Sheet'!I$17 -> 0.0351027 | ... L15: ='Data Sheet'!K21/'Data Sheet'!K$17 -> 0.037754884
B16: ='Data Sheet'!A22 -> Employee Cost | C16: ='Data Sheet'!B22/'Data Sheet'!B$17 -> 0.061067147 | D16: ='Data Sheet'!C22/'Data Sheet'!C$17 -> 0.063959474 | E16: ='Data Sheet'!D22/'Data Sheet'!D$17 -> 0.063907617 | F16: ='Data Sheet'!E22/'Data Sheet'!E$17 -> 0.065378447 | G16: ='Data Sheet'!F22/'Data Sheet'!F$17 -> 0.058975811 | H16: ='Data Sheet'!G22/'Data Sheet'!G$17 -> 0.053875044 | I16: ='Data Sheet'!H22/'Data Sheet'!H$17 -> 0.053931211 | J16: ='Data Sheet'!I22/'Data Sheet'!I$17 -> 0.054221444 | ... L16: ='Data Sheet'!K22/'Data Sheet'!K$17 -> 0.042212005
B17: ='Data Sheet'!A23 -> Selling and admin | C17: ='Data Sheet'!B23/'Data Sheet'!B$17 -> 0.025848728 | D17: ='Data Sheet'!C23/'Data Sheet'!C$17 -> 0.022483144 | E17: ='Data Sheet'!D23/'Data Sheet'!D$17 -> 0.019891522 | F17: ='Data Sheet'!E23/'Data Sheet'!E$17 -> 0.02026729 | G17: ='Data Sheet'!F23/'Data Sheet'!F$17 -> 0.026082364 | H17: ='Data Sheet'!G23/'Data Sheet'!G$17 -> 0.030319455 | I17: ='Data Sheet'!H23/'Data Sheet'!H$17 -> 0.033858433 | J17: ='Data Sheet'!I23/'Data Sheet'!I$17 -> 0.034799465 | ... L17: ='Data Sheet'!K23/'Data Sheet'!K$17 -> 0.042781918
B18: ='Data Sheet'!A24 -> Other Expenses | C18: ='Data Sheet'!B24/'Data Sheet'!B$17 -> -0.024294137 | D18: ='Data Sheet'!C24/'Data Sheet'!C$17 -> -0.020076483 | E18: ='Data Sheet'!D24/'Data Sheet'!D$17 -> -0.018821223 | F18: ='Data Sheet'!E24/'Data Sheet'!E$17 -> -0.006510768 | G18: ='Data Sheet'!F24/'Data Sheet'!F$17 -> 0.02715489 | H18: ='Data Sheet'!G24/'Data Sheet'!G$17 -> -0.0096890266 | I18: ='Data Sheet'!H24/'Data Sheet'!H$17 -> -0.012556851 | J18: ='Data Sheet'!I24/'Data Sheet'!I$17 -> -0.026647088 | ... L18: ='Data Sheet'!K24/'Data Sheet'!K$17 -> -0.037806536
B19: ='Data Sheet'!A25 -> Other Income | C19: ='Data Sheet'!B25/'Data Sheet'!B$17 -> 0.02923681 | D19: ='Data Sheet'!C25/'Data Sheet'!C$17 -> 0.016181874 | E19: ='Data Sheet'!D25/'Data Sheet'!D$17 -> 0.019398607 | F19: ='Data Sheet'!E25/'Data Sheet'!E$17 -> 0.063298598 | G19: ='Data Sheet'!F25/'Data Sheet'!F$17 -> 0.028098088 | H19: ='Data Sheet'!G25/'Data Sheet'!G$17 -> 0.074992299 | I19: ='Data Sheet'!H25/'Data Sheet'!H$17 -> 0.045016392 | J19: ='Data Sheet'!I25/'Data Sheet'!I$17 -> 0.036247879 | ... L19: ='Data Sheet'!K25/'Data Sheet'!K$17 -> 0.029076047
B20: ='Data Sheet'!A26 -> Depreciation | C20: ='Data Sheet'!B26/'Data Sheet'!B$17 -> 0.069595259 | D20: ='Data Sheet'!C26/'Data Sheet'!C$17 -> 0.07863119 | E20: ='Data Sheet'!D26/'Data Sheet'!D$17 -> 0.073253627 | F20: ='Data Sheet'!E26/'Data Sheet'!E$17 -> 0.084691754 | G20: ='Data Sheet'!F26/'Data Sheet'!F$17 -> 0.086442607 | H20: ='Data Sheet'!G26/'Data Sheet'!G$17 -> 0.094607873 | I20: ='Data Sheet'!H26/'Data Sheet'!H$17 -> 0.11163079 | J20: ='Data Sheet'!I26/'Data Sheet'!I$17 -> 0.10392632 | ... L20: ='Data Sheet'!K26/'Data Sheet'!K$17 -> 0.090776191
B21: ='Data Sheet'!A27 -> Interest | C21: ='Data Sheet'!B27/'Data Sheet'!B$17 -> 0.045887063 | D21: ='Data Sheet'!C27/'Data Sheet'!C$17 -> 0.045861019 | E21: ='Data Sheet'!D27/'Data Sheet'!D$17 -> 0.045742151 | F21: ='Data Sheet'!E27/'Data Sheet'!E$17 -> 0.050481641 | G21: ='Data Sheet'!F27/'Data Sheet'!F$17 -> 0.055886363 | H21: ='Data Sheet'!G27/'Data Sheet'!G$17 -> 0.074810047 | I21: ='Data Sheet'!H27/'Data Sheet'!H$17 -> 0.082705235 | J21: ='Data Sheet'!I27/'Data Sheet'!I$17 -> 0.070669563 | ... L21: ='Data Sheet'!K27/'Data Sheet'!K$17 -> 0.06891008
B22: ='Data Sheet'!A28 -> Profit before tax | C22: ='Data Sheet'!B28/'Data Sheet'!B$17 -> 0.13077334 | D22: ='Data Sheet'!C28/'Data Sheet'!C$17 -> 0.14466556 | E22: ='Data Sheet'!D28/'Data Sheet'!D$17 -> 0.16365093 | F22: ='Data Sheet'!E28/'Data Sheet'!E$17 -> 0.18339956 | G22: ='Data Sheet'!F28/'Data Sheet'!F$17 -> 0.11222393 | H22: ='Data Sheet'!G28/'Data Sheet'!G$17 -> 0.19412329 | I22: ='Data Sheet'!H28/'Data Sheet'!H$17 -> 0.15591994 | J22: ='Data Sheet'!I28/'Data Sheet'!I$17 -> 0.16588158 | ... L22: ='Data Sheet'!K28/'Data Sheet'!K$17 -> 0.15765553
... B25: ='Data Sheet'!A31 -> Dividend Amount | C25: ='Data Sheet'!B31/'Data Sheet'!B$17 -> 0.025780941 | D25: ='Data Sheet'!C31/'Data Sheet'!C$17 -> 0.037634448 | E25: ='Data Sheet'!D31/'Data Sheet'!D$17 -> 0.048040107 | F25: ='Data Sheet'!E31/'Data Sheet'!E$17 -> 0.047928262 | G25: ='Data Sheet'!F31/'Data Sheet'!F$17 -> 0.059987013 | H25: ='Data Sheet'!G31/'Data Sheet'!G$17 -> 0.028473186 | I25: ='Data Sheet'!H31/'Data Sheet'!H$17 -> 0.053468919 | J25: ='Data Sheet'!I31/'Data Sheet'!I$17 -> 0.051162334 | ... L25: ='Data Sheet'!K31/'Data Sheet'!K$17 -> 0.042100185
B26: ='Data Sheet'!A34 -> EBITDA | C26: ='Data Sheet'!B34/'Data Sheet'!B$17 -> 0.24618025 | D26: ='Data Sheet'!C34/'Data Sheet'!C$17 -> 0.26943599 | E26: ='Data Sheet'!D34/'Data Sheet'!D$17 -> 0.28271619 | F26: ='Data Sheet'!E34/'Data Sheet'!E$17 -> 0.31905488 | G26: ='Data Sheet'!F34/'Data Sheet'!F$17 -> 0.25158331 | H26: ='Data Sheet'!G34/'Data Sheet'!G$17 -> 0.3607846 | I26: ='Data Sheet'!H34/'Data Sheet'!H$17 -> 0.34725438 | J26: ='Data Sheet'!I34/'Data Sheet'!I$17 -> 0.33833386 | ... L26: ='Data Sheet'!K34/'Data Sheet'!K$17 -> 0.31442551
B28: ="Common Size Balance Sheet" & " "& "-" & 'Data Sheet'!$B$1 -> Common Size Balance Sheet -NTPC LTD
B30: Particulars | C30: ='Data Sheet'!B57 -> 42094 | D30: ='Data Sheet'!C57 -> 42460 | E30: ='Data Sheet'!D57 -> 42825 | F30: ='Data Sheet'!E57 -> 43190 | G30: ='Data Sheet'!F57 -> 43555 | H30: ='Data Sheet'!G57 -> 43921 | I30: ='Data Sheet'!H57 -> 44286 | J30: ='Data Sheet'!I57 -> 44651 | ... L30: ='Data Sheet'!K57 -> 45382
B32: Total Liabilities | C32: ='Data Sheet'!B62/'Data Sheet'!B$62 -> 1 | D32: ='Data Sheet'!C62/'Data Sheet'!C$62 -> 1 | E32: ='Data Sheet'!D62/'Data Sheet'!D$62 -> 1 | F32: ='Data Sheet'!E62/'Data Sheet'!E$62 -> 1 | G32: ='Data Sheet'!F62/'Data Sheet'!F$62 -> 1 | H32: ='Data Sheet'!G62/'Data Sheet'!G$62 -> 1 | I32: ='Data Sheet'!H62/'Data Sheet'!H$62 -> 1 | J32: ='Data Sheet'!I62/'Data Sheet'!I$62 -> 1 | ... L32: ='Data Sheet'!K62/'Data Sheet'!K$62 -> 1
B33: ='Data Sheet'!A58 -> Equity Share Capital | C33: ='Data Sheet'!B58/'Data Sheet'!B$62 -> 0.037528485 | D33: ='Data Sheet'!C58/'Data Sheet'!C$62 -> 0.036701123 | E33: ='Data Sheet'!D58/'Data Sheet'!D$62 -> 0.033167469 | F33: ='Data Sheet'!E58/'Data Sheet'!E$62 -> 0.029188269 | G33: ='Data Sheet'!F58/'Data Sheet'!F$62 -> 0.028520912 | H33: ='Data Sheet'!G58/'Data Sheet'!G$62 -> 0.026205965 | I33: ='Data Sheet'!H58/'Data Sheet'!H$62 -> 0.024362159 | J33: ='Data Sheet'!I58/'Data Sheet'!I$62 -> 0.023318753 | ... L33: ='Data Sheet'!K58/'Data Sheet'!K$62 -> 0.02023184
B34: ='Data Sheet'!A59 -> Reserves | C34: ='Data Sheet'!B59/'Data Sheet'!B$62 -> 0.33611503 | D34: ='Data Sheet'!C59/'Data Sheet'!C$62 -> 0.37090823 | E34: ='Data Sheet'!D59/'Data Sheet'!D$62 -> 0.36038723 | F34: ='Data Sheet'!E59/'Data Sheet'!E$62 -> 0.33741813 | G34: ='Data Sheet'!F59/'Data Sheet'!F$62 -> 0.29246159 | H34: ='Data Sheet'!G59/'Data Sheet'!G$62 -> 0.28854223 | I34: ='Data Sheet'!H59/'Data Sheet'!H$62 -> 0.29154635 | J34: ='Data Sheet'!I59/'Data Sheet'!I$62 -> 0.30223082 | ... L34: ='Data Sheet'!K59/'Data Sheet'!K$62 -> 0.31508371
B35: ='Data Sheet'!A60 -> Borrowings | C35: ='Data Sheet'!B60/'Data Sheet'!B$62 -> 0.46539097 | D35: ='Data Sheet'!C60/'Data Sheet'!C$62 -> 0.44254122 | E35: ='Data Sheet'!D60/'Data Sheet'!D$62 -> 0.45765416 | F35: ='Data Sheet'!E60/'Data Sheet'!E$62 -> 0.4603615 | G35: ='Data Sheet'!F60/'Data Sheet'!F$62 -> 0.4988376 | H35: ='Data Sheet'!G60/'Data Sheet'!G$62 -> 0.53760852 | I35: ='Data Sheet'!H60/'Data Sheet'!H$62 -> 0.52813156 | J35: ='Data Sheet'!I60/'Data Sheet'!I$62 -> 0.50671149 | ... L35: ='Data Sheet'!K60/'Data Sheet'!K$62 -> 0.49476738
B36: ='Data Sheet'!A61 -> Other Liabilities | C36: ='Data Sheet'!B61/'Data Sheet'!B$62 -> 0.16096551 | D36: ='Data Sheet'!C61/'Data Sheet'!C$62 -> 0.14984942 | E36: ='Data Sheet'!D61/'Data Sheet'!D$62 -> 0.14879114 | F36: ='Data Sheet'!E61/'Data Sheet'!E$62 -> 0.1730321 | G36: ='Data Sheet'!F61/'Data Sheet'!F$62 -> 0.1801799 | H36: ='Data Sheet'!G61/'Data Sheet'!G$62 -> 0.14764329 | I36: ='Data Sheet'!H61/'Data Sheet'!H$62 -> 0.15595993 | J36: ='Data Sheet'!I61/'Data Sheet'!I$62 -> 0.16773894 | ... L36: ='Data Sheet'!K61/'Data Sheet'!K$62 -> 0.16991708
B38: Total Assets | C38: ='Data Sheet'!B76/'Data Sheet'!B$76 -> 1 | D38: ='Data Sheet'!C76/'Data Sheet'!C$76 -> 1 | E38: ='Data Sheet'!D76/'Data Sheet'!D$76 -> 1 | F38: ='Data Sheet'!E76/'Data Sheet'!E$76 -> 1 | G38: ='Data Sheet'!F76/'Data Sheet'!F$76 -> 1 | H38: ='Data Sheet'!G76/'Data Sheet'!G$76 -> 1 | I38: ='Data Sheet'!H76/'Data Sheet'!H$76 -> 1 | J38: ='Data Sheet'!I76/'Data Sheet'!I$76 -> 1 | ... L38: ='Data Sheet'!K76/'Data Sheet'!K$76 -> 1
B39: ='Data Sheet'!A63 -> Net Block | C39: ='Data Sheet'!B63/'Data Sheet'!B$76 -> 0.41806093 | D39: ='Data Sheet'!C63/'Data Sheet'!C$76 -> 0.41363512 | E39: ='Data Sheet'!D63/'Data Sheet'!D$76 -> 0.42047995 | F39: ='Data Sheet'!E63/'Data Sheet'!E$76 -> 0.45397853 | G39: ='Data Sheet'!F63/'Data Sheet'!F$76 -> 0.43521051 | H39: ='Data Sheet'!G63/'Data Sheet'!G$76 -> 0.49739992 | I39: ='Data Sheet'!H63/'Data Sheet'!H$76 -> 0.51063832 | J39: ='Data Sheet'!I63/'Data Sheet'!I$76 -> 0.54089953 | ... L39: ='Data Sheet'!K63/'Data Sheet'!K$76 -> 0.54025802
B40: ='Data Sheet'!A64 -> Capital Work in Progress | C40: ='Data Sheet'!B64/'Data Sheet'!B$76 -> 0.30746922 | D40: ='Data Sheet'!C64/'Data Sheet'!C$76 -> 0.33403294 | E40: ='Data Sheet'!D64/'Data Sheet'!D$76 -> 0.34953911 | F40: ='Data Sheet'!E64/'Data Sheet'!E$76 -> 0.29518012 | G40: ='Data Sheet'!F64/'Data Sheet'!F$76 -> 0.34127707 | H40: ='Data Sheet'!G64/'Data Sheet'!G$76 -> 0.2609019 | I40: ='Data Sheet'!H64/'Data Sheet'!H$76 -> 0.24497661 | J40: ='Data Sheet'!I64/'Data Sheet'!I$76 -> 0.21914231 | ... L40: ='Data Sheet'!K64/'Data Sheet'!K$76 -> 0.1829095
B41: ='Data Sheet'!A65 -> Investments | C41: ='Data Sheet'!B65/'Data Sheet'!B$76 -> 0.0086545553 | D41: ='Data Sheet'!C65/'Data Sheet'!C$76 -> 0.028813381 | E41: ='Data Sheet'!D65/'Data Sheet'!D$76 -> 0.030627091 | F41: ='Data Sheet'!E65/'Data Sheet'!E$76 -> 0.031418949 | G41: ='Data Sheet'!F65/'Data Sheet'!F$76 -> 0.023441254 | H41: ='Data Sheet'!G65/'Data Sheet'!G$76 -> 0.024648713 | I41: ='Data Sheet'!H65/'Data Sheet'!H$76 -> 0.026604699 | J41: ='Data Sheet'!I65/'Data Sheet'!I$76 -> 0.025554202 | ... L41: ='Data Sheet'!K65/'Data Sheet'!K$76 -> 0.033142705
B42: ='Data Sheet'!A66 -> Other Assets | C42: ='Data Sheet'!B75/'Data Sheet'!B$76 -> 0.12216713 | D42: ='Data Sheet'!C75/'Data Sheet'!C$76 -> 0.13284286 | E42: ='Data Sheet'!D75/'Data Sheet'!D$76 -> 0.12310736 | F42: ='Data Sheet'!E75/'Data Sheet'!E$76 -> 0.15049779 | G42: ='Data Sheet'!F75/'Data Sheet'!F$76 -> 0.13143808 | H42: ='Data Sheet'!G75/'Data Sheet'!G$76 -> 0.12475487 | I42: ='Data Sheet'!H75/'Data Sheet'!H$76 -> 0.11073278 | J42: ='Data Sheet'!I75/'Data Sheet'!I$76 -> 0.11148015 | ... L42: ='Data Sheet'!K75/'Data Sheet'!K$76 -> 0.12169956
B43: ='Data Sheet'!A68 -> Receivables | C43: ='Data Sheet'!B68/'Data Sheet'!B$76 -> 0.042100196 | D43: ='Data Sheet'!C68/'Data Sheet'!C$76 -> 0.036893988 | E43: ='Data Sheet'!D68/'Data Sheet'!D$76 -> 0.036057363 | F43: ='Data Sheet'!E68/'Data Sheet'!E$76 -> 0.031194448 | G43: ='Data Sheet'!F68/'Data Sheet'!F$76 -> 0.03563765 | H43: ='Data Sheet'!G68/'Data Sheet'!G$76 -> 0.053803649 | I43: ='Data Sheet'!H68/'Data Sheet'!H$76 -> 0.070849965 | J43: ='Data Sheet'!I68/'Data Sheet'!I$76 -> 0.067264927 | ... L43: ='Data Sheet'!K68/'Data Sheet'!K$76 -> 0.069583205
B44: ='Data Sheet'!A69 -> Inventory | C44: ='Data Sheet'!B69/'Data Sheet'!B$76 -> 0.036683015 | D44: ='Data Sheet'!C69/'Data Sheet'!C$76 -> 0.031800895 | E44: ='Data Sheet'!D69/'Data Sheet'!D$76 -> 0.026908962 | F44: ='Data Sheet'!E69/'Data Sheet'!E$76 -> 0.022198414 | G44: ='Data Sheet'!F69/'Data Sheet'!F$76 -> 0.024539884 | H44: ='Data Sheet'!G69/'Data Sheet'!G$76 -> 0.029977832 | I44: ='Data Sheet'!H69/'Data Sheet'!H$76 -> 0.025173597 | J44: ='Data Sheet'!I69/'Data Sheet'!I$76 -> 0.02493799 | ... L44: ='Data Sheet'!K69/'Data Sheet'!K$76 -> 0.038120216
B45: ='Data Sheet'!A70 -> Cash & Bank | C45: ='Data Sheet'!B70/'Data Sheet'!B$76 -> 0.064864948 | D45: ='Data Sheet'!C70/'Data Sheet'!C$76 -> 0.02198081 | E45: ='Data Sheet'!D70/'Data Sheet'!D$76 -> 0.013280165 | F45: ='Data Sheet'!E70/'Data Sheet'!E$76 -> 0.015531753 | G45: ='Data Sheet'!F70/'Data Sheet'!F$76 -> 0.0084555653 | H45: ='Data Sheet'!G70/'Data Sheet'!G$76 -> 0.0085131195 | I45: ='Data Sheet'!H70/'Data Sheet'!H$76 -> 0.01102402 | J45: ='Data Sheet'!I70/'Data Sheet'!I$76 -> 0.010720883 | ... L45: ='Data Sheet'!K70/'Data Sheet'!K$76 -> 0.01428679

Sheet Ratio Analysis
B3: =B7 -> Ratio Analysis - NTPC LTD
B7: ="Ratio Analysis - " & 'Data Sheet'!B1 -> Ratio Analysis - NTPC LTD
B8: Years | C8: ='Data Sheet'!B57 -> 42094 | D8: ='Data Sheet'!C57 -> 42460 | E8: ='Data Sheet'!D57 -> 42825 | F8: ='Data Sheet'!E57 -> 43190 | G8: ='Data Sheet'!F57 -> 43555 | H8: ='Data Sheet'!G57 -> 43921 | I8: ='Data Sheet'!H57 -> 44286 | J8: ='Data Sheet'!I57 -> 44651 | ... L8: ='Data Sheet'!K57 -> 45382 | M8: Trend | N8: Median | O8: Mean
B10: SalesGrowth | C10: - | D10: =IFERROR(HistoricalFS!D11,0) -> -0.082049618 | E10: =IFERROR(HistoricalFS!E11,0) -> 0.11780114 | F10: =IFERROR(HistoricalFS!F11,0) -> 0.073630383 | G10: =IFERROR(HistoricalFS!G11,0) -> 0.13854191 | H10: =IFERROR(HistoricalFS!H11,0) -> 0.091512779 | I10: =IFERROR(HistoricalFS!I11,0) -> 0.018883918 | J10: =IFERROR(HistoricalFS!J11,0) -> 0.18952669 | K10: =IFERROR(HistoricalFS!K11,0) -> 0.32816866 | L10: =IFERROR(HistoricalFS!L11,0) -> 0.013017063 | N10: =IFERROR(AVERAGE(D10:L10),0) -> 0.098781436 | O10: =IFERROR(MEDIAN(C10:L10),0) -> 0.091512779
B11: EBITDA growth | C11: - | D11: =IFERROR(HistoricalFS!D22/HistoricalFS!C22-1,0) -> 0.070042162 | E11: =IFERROR(HistoricalFS!E22/HistoricalFS!D22-1,0) -> 0.16318998 | F11: =IFERROR(HistoricalFS!F22/HistoricalFS!E22-1,0) -> 0.041110257 | G11: =IFERROR(HistoricalFS!G22/HistoricalFS!F22-1,0) -> 0.01000471 | H11: =IFERROR(HistoricalFS!H22/HistoricalFS!G22-1,0) -> 0.39080649 | I11: =IFERROR(HistoricalFS!I22/HistoricalFS!H22-1,0) -> 0.077819636 | J11: =IFERROR(HistoricalFS!J22/HistoricalFS!I22-1,0) -> 0.18559076 | K11: =IFERROR(HistoricalFS!K22/HistoricalFS!J22-1,0) -> 0.17922909 | L11: =IFERROR(HistoricalFS!L22/HistoricalFS!K22-1,0) -> 0.081093875 | N11: =IFERROR(AVERAGE(D11:L11),0) -> 0.13320966 | O11: =IFERROR(MEDIAN(C11:L11),0) -> 0.081093875
B12: EBIT Growth | C12: - | D12: =IFERROR(HistoricalFS!D31/HistoricalFS!C31-1,0) -> 0.16156866 | E12: =IFERROR(HistoricalFS!E31/HistoricalFS!D31-1,0) -> 0.25498742 | F12: =IFERROR(HistoricalFS!F31/HistoricalFS!E31-1,0) -> -0.1061216 | G12: =IFERROR(HistoricalFS!G31/HistoricalFS!F31-1,0) -> -0.20249762 | H12: =IFERROR(HistoricalFS!H31/HistoricalFS!G31-1,0) -> 0.54569624 | I12: =IFERROR(HistoricalFS!I31/HistoricalFS!H31-1,0) -> -0.051482452 | J12: =IFERROR(HistoricalFS!J31/HistoricalFS!I31-1,0) -> 0.39042218 | K12: =IFERROR(HistoricalFS!K31/HistoricalFS!J31-1,0) -> 0.24177351 | L12: =IFERROR(HistoricalFS!L31/HistoricalFS!K31-1,0) -> 0.074685354 | N12: =IFERROR(AVERAGE(D12:L12),0) -> 0.14544797 | O12: =IFERROR(MEDIAN(C12:L12),0) -> 0.16156866
B13: Net Profit Growth | C13: - | D13: =IFERROR(HistoricalFS!D37/HistoricalFS!C37-1,0) -> 0.25322384 | E13: =IFERROR(HistoricalFS!E37/HistoricalFS!D37-1,0) -> -0.049057442 | F13: =IFERROR(HistoricalFS!F37/HistoricalFS!E37-1,0) -> -0.46001778 | G13: =IFERROR(HistoricalFS!G37/HistoricalFS!F37-1,0) -> 1.2770491 | H13: =IFERROR(HistoricalFS!H37/HistoricalFS!G37-1,0) -> -0.67075494 | I13: =IFERROR(HistoricalFS!I37/HistoricalFS!H37-1,0) -> 1.6939118 | J13: =IFERROR(HistoricalFS!J37/HistoricalFS!I37-1,0) -> 0.22140045 | K13: =IFERROR(HistoricalFS!K37/HistoricalFS!J37-1,0) -> 0.19825846 | L13: =IFERROR(HistoricalFS!L37/HistoricalFS!K37-1,0) -> 0.10864667 | N13: =IFERROR(AVERAGE(D13:L13),0) -> 0.28585112 | O13: =IFERROR(AVERAGE(E13:M13),0) -> 0.28992953
B14: Dividend Growth | C14: - | D14: =IFERROR(HistoricalFS!D45/HistoricalFS!C45-1,0) -> 0.34000369 | E14: =IFERROR(HistoricalFS!E45/HistoricalFS!D45-1,0) -> 0.42686525 | F14: =IFERROR(HistoricalFS!F45/HistoricalFS!E45-1,0) -> 0.071130811 | G14: =IFERROR(HistoricalFS!G45/HistoricalFS!F45-1,0) -> 0.42499905 | H14: =IFERROR(HistoricalFS!H45/HistoricalFS!G45-1,0) -> -0.48190708 | I14: =IFERROR(HistoricalFS!I45/HistoricalFS!H45-1,0) -> 0.95237988 | J14: =IFERROR(HistoricalFS!J45/HistoricalFS!I45-1,0) -> 0.13821194 | K14: =IFERROR(HistoricalFS!K45/HistoricalFS!J45-1,0) -> 0.035714759 | L14: =IFERROR(HistoricalFS!L45/HistoricalFS!K45-1,0) -> 0.068964978 | N14: =IFERROR(AVERAGE(D14:L14),0) -> 0.21959592 | O14: =IFERROR(AVERAGE(E14:M14),0) -> 0.20454495
B16: Gross Margin | C16: =IFERROR(HistoricalFS!C17,0) -> 0.21857344 | D16: =IFERROR(HistoricalFS!D17,0) -> 0.25538256 | E16: =IFERROR(HistoricalFS!E17,0) -> 0.2643184 | F16: =IFERROR(HistoricalFS!F17,0) -> 0.26903088 | G16: =IFERROR(HistoricalFS!G17,0) -> 0.27969207 | H16: =IFERROR(HistoricalFS!H17,0) -> 0.30917934 | I16: =IFERROR(HistoricalFS!I17,0) -> 0.32654115 | J16: =IFERROR(HistoricalFS!J17,0) -> 0.31238196 | ... L16: =IFERROR(HistoricalFS!L17,0) -> 0.29324113 | N16: =IFERROR(AVERAGE(C16:L16),0) -> 0.28190915 | O16: =IFERROR(MEDIAN(C16:L16),0) -> 0.28522133
B17: EBITDA Margin | C17: =IFERROR(HistoricalFS!C23,0) -> 0.21701885 | D17: =IFERROR(HistoricalFS!D23,0) -> 0.2529759 | E17: =IFERROR(HistoricalFS!E23,0) -> 0.2632481 | F17: =IFERROR(HistoricalFS!F23,0) -> 0.25527435 | G17: =IFERROR(HistoricalFS!G23,0) -> 0.22645482 | H17: =IFERROR(HistoricalFS!H23,0) -> 0.28854892 | I17: =IFERROR(HistoricalFS!I23,0) -> 0.30523957 | J17: =IFERROR(HistoricalFS!J23,0) -> 0.30422959 | ... L17: =IFERROR(HistoricalFS!L23,0) -> 0.28826575 | N17: =IFERROR(AVERAGE(C17:L17),0) -> 0.26713694 | O17: =IFERROR(MEDIAN(C17:L17),0) -> 0.26668084
B18: EBIT Margin | C18: =IFERROR((HistoricalFS!C22-HistoricalFS!C28)/HistoricalFS!C10,0) -> 0.14742359 | D18: =IFERROR((HistoricalFS!D22-HistoricalFS!D28)/HistoricalFS!D10,0) -> 0.17434471 | E18: =IFERROR((HistoricalFS!E22-HistoricalFS!E28)/HistoricalFS!E10,0) -> 0.18999448 | F18: =IFERROR((HistoricalFS!F22-HistoricalFS!F28)/HistoricalFS!F10,0) -> 0.1705826 | G18: =IFERROR((HistoricalFS!G22-HistoricalFS!G28)/HistoricalFS!G10,0) -> 0.14001221 | H18: =IFERROR((HistoricalFS!H22-HistoricalFS!H28)/HistoricalFS!H10,0) -> 0.19394104 | I18: =IFERROR((HistoricalFS!I22-HistoricalFS!I28)/HistoricalFS!I10,0) -> 0.19360878 | J18: =IFERROR((HistoricalFS!J22-HistoricalFS!J28)/HistoricalFS!J10,0) -> 0.20030327 | ... L18: =IFERROR((HistoricalFS!L22-HistoricalFS!L28)/HistoricalFS!L10,0) -> 0.19748956 | N18: =IFERROR(AVERAGE(C18:L18),0) -> 0.17938656 | O18: =IFERROR(MEDIAN(C18:L18),0) -> 0.18807994
B19: EBT Margin | C19: =IFERROR(HistoricalFS!C32,0) -> 0.10153653 | D19: =IFERROR(HistoricalFS!D32,0) -> 0.12848369 | E19: =IFERROR(HistoricalFS!E32,0) -> 0.14425233 | F19: =IFERROR(HistoricalFS!F32,0) -> 0.12010096 | G19: =IFERROR(HistoricalFS!G32,0) -> 0.084125846 | H19: =IFERROR(HistoricalFS!H32,0) -> 0.11913099 | I19: =IFERROR(HistoricalFS!I32,0) -> 0.11090355 | J19: =IFERROR(HistoricalFS!J32,0) -> 0.1296337 | ... L19: =IFERROR(HistoricalFS!L32,0) -> 0.12857948 | N19: =IFERROR(AVERAGE(C19:L19),0) -> 0.11879483 | O19: =IFERROR(MEDIAN(C19:L19),0) -> 0.1206511
B20: Net Profit Margin | C20: =IFERROR(HistoricalFS!C38,0) -> 0.095735394 | D20: =IFERROR(HistoricalFS!D38,0) -> 0.13070192 | E20: =IFERROR(HistoricalFS!E38,0) -> 0.11119153 | F20: =IFERROR(HistoricalFS!F38,0) -> 0.055923761 | G20: =IFERROR(HistoricalFS!G38,0) -> 0.11184582 | H20: =IFERROR(HistoricalFS!H38,0) -> 0.033737289 | I20: =IFERROR(HistoricalFS!I38,0) -> 0.08920082 | J20: =IFERROR(HistoricalFS!J38,0) -> 0.091590985 | ... L20: =IFERROR(HistoricalFS!L38,0) -> 0.090432888 | N20: =IFERROR(AVERAGE(C20:L20),0) -> 0.089299274 | O20: =IFERROR(MEDIAN(C20:L20),0) -> 0.091011936
B22: Sales Expenses % Sales | C22: =IFERROR(HistoricalFS!C20,0) -> 0.0015545906 | D22: =IFERROR(HistoricalFS!D20,0) -> 0.0024066602 | E22: =IFERROR(HistoricalFS!E20,0) -> 0.0010702991 | F22: =IFERROR(HistoricalFS!F20,0) -> 0.013756522 | G22: =IFERROR(HistoricalFS!G20,0) -> 0.053237254 | H22: =IFERROR(HistoricalFS!H20,0) -> 0.020630428 | I22: =IFERROR(HistoricalFS!I20,0) -> 0.021301583 | J22: =IFERROR(HistoricalFS!J20,0) -> 0.0081523771 | ... L22: =IFERROR(HistoricalFS!L20,0) -> 0.0049753816 | N22: =IFERROR(AVERAGE(C22:L22),0) -> 0.014772211 | O22: =IFERROR(MEDIAN(C22:L22),0) -> 0.01095445
B23: Depericiation % sales | C23: =IFERROR(HistoricalFS!C29,0) -> 0.069595259 | D23: =IFERROR(HistoricalFS!D29,0) -> 0.07863119 | E23: =IFERROR(HistoricalFS!E29,0) -> 0.073253627 | F23: =IFERROR(HistoricalFS!F29,0) -> 0.084691754 | G23: =IFERROR(HistoricalFS!G29,0) -> 0.086442607 | H23: =IFERROR(HistoricalFS!H29,0) -> 0.094607873 | I23: =IFERROR(HistoricalFS!I29,0) -> 0.11163079 | J23: =IFERROR(HistoricalFS!J29,0) -> 0.10392632 | ... L23: =IFERROR(HistoricalFS!L29,0) -> 0.090776191 | N23: =IFERROR(AVERAGE(C23:L23),0) -> 0.087750378 | O23: =IFERROR(MEDIAN(C23:L23),0) -> 0.085567181
B24: Operating Income % Sales | C24: =C18 -> 0.14742359 | D24: =D18 -> 0.17434471 | E24: =E18 -> 0.18999448 | F24: =F18 -> 0.1705826 | G24: =G18 -> 0.14001221 | H24: =H18 -> 0.19394104 | I24: =I18 -> 0.19360878 | J24: =J18 -> 0.20030327 | ... L24: =L18 -> 0.19748956 | N24: =IFERROR(AVERAGE(C24:L24),0) -> 0.17938656 | O24: =IFERROR(MEDIAN(C24:L24),0) -> 0.18807994
B26: Return on Capital Employed | C26: =IFERROR((HistoricalFS!C22-HistoricalFS!C28)/(SUM(HistoricalFS!C54:C56)),0) -> 0.063942322 | D26: =IFERROR((HistoricalFS!D22-HistoricalFS!D28)/(SUM(HistoricalFS!D54:D56)),0) -> 0.066996431 | E26: =IFERROR((HistoricalFS!E22-HistoricalFS!E28)/(SUM(HistoricalFS!E54:E56)),0) -> 0.073661595 | F26: =IFERROR((HistoricalFS!F22-HistoricalFS!F28)/(SUM(HistoricalFS!F54:F56)),0) -> 0.064318092 | G26: =IFERROR((HistoricalFS!G22-HistoricalFS!G28)/(SUM(HistoricalFS!G54:G56)),0) -> 0.049369294 | H26: =IFERROR((HistoricalFS!H22-HistoricalFS!H28)/(SUM(HistoricalFS!H54:H56)),0) -> 0.065966506 | I26: =IFERROR((HistoricalFS!I22-HistoricalFS!I28)/(SUM(HistoricalFS!I54:I56)),0) -> 0.064276366 | J26: =IFERROR((HistoricalFS!J22-HistoricalFS!J28)/(SUM(HistoricalFS!J54:J56)),0) -> 0.076785908 | ... L26: =IFERROR((HistoricalFS!L22-HistoricalFS!L28)/(SUM(HistoricalFS!L54:L56)),0) -> 0.088608581 | N26: =IFERROR(AVERAGE(C26:L26),0) -> 0.070259895 | O26: =IFERROR(MEDIAN(C26:L26),0) -> 0.066481469
B27: Retained Earnings% | C27: =IFERROR(HistoricalFS!C48,0) -> 0.73070627 | D27: =IFERROR(HistoricalFS!D48,0) -> 0.71205895 | E27: =IFERROR(HistoricalFS!E48,0) -> 0.56795174 | F27: =IFERROR(HistoricalFS!F48,0) -> 0.14297141 | G27: =IFERROR(HistoricalFS!G48,0) -> 0.46366333 | H27: =IFERROR(HistoricalFS!H48,0) -> 0.15603219 | I27: =IFERROR(HistoricalFS!I48,0) -> 0.40057817 | J27: =IFERROR(HistoricalFS!J48,0) -> 0.44140426 | ... L27: =IFERROR(HistoricalFS!L48,0) -> 0.53445936 | N27: =IFERROR(AVERAGE(C27:L27),0) -> 0.46670034 | O27: =IFERROR(MEDIAN(C27:L27),0) -> 0.49042054
B28: Return on Equity % | C28: =IFERROR(HistoricalFS!C37/SUM(HistoricalFS!C54:C55),0) -> 0.093243012 | D28: =IFERROR(HistoricalFS!D37/SUM(HistoricalFS!D54:D55),0) -> 0.10475544 | E28: =IFERROR(HistoricalFS!E37/SUM(HistoricalFS!E54:E55),0) -> 0.093240133 | F28: =IFERROR(HistoricalFS!F37/SUM(HistoricalFS!F54:F55),0) -> 0.047564551 | G28: =IFERROR(HistoricalFS!G37/SUM(HistoricalFS!G54:G55),0) -> 0.10072748 | H28: =IFERROR(HistoricalFS!H37/SUM(HistoricalFS!H54:H55),0) -> 0.031075783 | I28: =IFERROR(HistoricalFS!I37/SUM(HistoricalFS!I54:I55),0) -> 0.079121927 | J28: =IFERROR(HistoricalFS!J37/SUM(HistoricalFS!J54:J55),0) -> 0.089761205 | ... L28: =IFERROR(HistoricalFS!L37/SUM(HistoricalFS!L54:L55),0) -> 0.10044442 | N28: =IFERROR(AVERAGE(C28:L28),0) -> 0.083896875 | O28: =IFERROR(MEDIAN(C28:L28),0) -> 0.093241573
B29: Self Sustainedd Growth Rate | C29: =IFERROR(C27*C28,0) -> 0.068133254 | D29: =IFERROR(D27*D28,0) -> 0.074592047 | E29: =IFERROR(E27*E28,0) -> 0.052955896 | F29: =IFERROR(F27*F28,0) -> 0.0068003708 | G29: =IFERROR(G27*G28,0) -> 0.046703637 | H29: =IFERROR(H27*H28,0) -> 0.0048488226 | I29: =IFERROR(I27*I28,0) -> 0.031694516 | J29: =IFERROR(J27*J28,0) -> 0.039620978 | ... L29: =IFERROR(L27*L28,0) -> 0.053683462 | N29: =IFERROR(AVERAGE(C29:L29),0) -> 0.043025158 | O29: =IFERROR(MEDIAN(C29:L29),0) -> 0.048961115
B30: Interst Coverage Ratio | C30: =IFERROR((HistoricalFS!C22-HistoricalFS!C28)/HistoricalFS!C25,0) -> 3.2127485 | D30: =IFERROR((HistoricalFS!D22-HistoricalFS!D28)/HistoricalFS!D25,0) -> 3.8015882 | E30: =IFERROR((HistoricalFS!E22-HistoricalFS!E28)/HistoricalFS!E25,0) -> 4.1535973 | F30: =IFERROR((HistoricalFS!F22-HistoricalFS!F28)/HistoricalFS!F25,0) -> 3.3791017 | G30: =IFERROR((HistoricalFS!G22-HistoricalFS!G28)/HistoricalFS!G25,0) -> 2.5053018 | H30: =IFERROR((HistoricalFS!H22-HistoricalFS!H28)/HistoricalFS!H25,0) -> 2.5924465 | I30: =IFERROR((HistoricalFS!I22-HistoricalFS!I28)/HistoricalFS!I25,0) -> 2.3409495 | J30: =IFERROR((HistoricalFS!J22-HistoricalFS!J28)/HistoricalFS!J25,0) -> 2.834364 | ... L30: =IFERROR((HistoricalFS!L22-HistoricalFS!L28)/HistoricalFS!L25,0) -> 2.8659023 | N30: =IFERROR(AVERAGE(C30:L30),0) -> 3.0551663 | O30: =IFERROR(MEDIAN(C30:L30),0) -> 2.8657829
B32: Debtor Turnover Ratio | C32: =HistoricalFS!C10/HistoricalFS!C78 -> -25.151538 | D32: =HistoricalFS!D10/HistoricalFS!D78 -> -33.016788 | E32: =HistoricalFS!E10/HistoricalFS!E78 -> -19.759752 | F32: =HistoricalFS!F10/HistoricalFS!F78 -> -8.2413277 | G32: =HistoricalFS!G10/HistoricalFS!G78 -> -11.00961 | H32: =HistoricalFS!H10/HistoricalFS!H78 -> 11.001411 | I32: =HistoricalFS!I10/HistoricalFS!I78 -> -20.259973 | J32: =HistoricalFS!J10/HistoricalFS!J78 -> 717.13124 | ... L32: =HistoricalFS!L10/HistoricalFS!L78 -> -95.200469 | N32: =IFERROR(AVERAGE(C32:L32),0) -> 43.586953 | O32: =IFERROR(MEDIAN(C32:L32),0) -> -20.009862
B33: Creditor Turnover Ratio | C33: =IFERROR(HistoricalFS!C10/HistoricalFS!C57,0) -> 2.2608326 | D33: =IFERROR(HistoricalFS!D10/HistoricalFS!D57,0) -> 2.1801364 | E33: =IFERROR(HistoricalFS!E10/HistoricalFS!E57,0) -> 2.217988 | F33: =IFERROR(HistoricalFS!F10/HistoricalFS!F57,0) -> 1.8020232 | G33: =IFERROR(HistoricalFS!G10/HistoricalFS!G57,0) -> 1.6043652 | H33: =IFERROR(HistoricalFS!H10/HistoricalFS!H57,0) -> 1.963638 | I33: =IFERROR(HistoricalFS!I10/HistoricalFS!I57,0) -> 1.796703 | J33: =IFERROR(HistoricalFS!J10/HistoricalFS!J57,0) -> 1.902038 | ... L33: =IFERROR(HistoricalFS!L10/HistoricalFS!L57,0) -> 2.1918765 | N33: =IFERROR(AVERAGE(C33:L33),0) -> 2.0200524 | O33: =IFERROR(MEDIAN(C33:L33),0) -> 2.0718872
B34: Inventory Turnover Ratio | C34: =IFERROR(HistoricalFS!C10/HistoricalFS!C67,0) -> 9.9205603 | D34: =IFERROR(HistoricalFS!D10/HistoricalFS!D67,0) -> 10.27305 | E34: =IFERROR(HistoricalFS!E10/HistoricalFS!E67,0) -> 12.264203 | F34: =IFERROR(HistoricalFS!F10/HistoricalFS!F67,0) -> 14.046403 | G34: =IFERROR(HistoricalFS!G10/HistoricalFS!G67,0) -> 11.779777 | H34: =IFERROR(HistoricalFS!H10/HistoricalFS!H67,0) -> 9.6710788 | I34: =IFERROR(HistoricalFS!I10/HistoricalFS!I67,0) -> 11.131253 | J34: =IFERROR(HistoricalFS!J10/HistoricalFS!J67,0) -> 12.793566 | ... L34: =IFERROR(HistoricalFS!L10/HistoricalFS!L67,0) -> 9.7700722 | N34: =IFERROR(AVERAGE(C34:L34),0) -> 11.384098 | O34: =IFERROR(MEDIAN(C34:L34),0) -> 11.455515
B35: Fixed asset Turnover | C35: =IFERROR(HistoricalFS!C10/HistoricalFS!C60,0) -> 0.8704857 | D35: =IFERROR(HistoricalFS!D10/HistoricalFS!D60,0) -> 0.78980766 | E35: =IFERROR(HistoricalFS!E10/HistoricalFS!E60,0) -> 0.78485781 | F35: =IFERROR(HistoricalFS!F10/HistoricalFS!F60,0) -> 0.68683396 | G35: =IFERROR(HistoricalFS!G10/HistoricalFS!G60,0) -> 0.66421732 | H35: =IFERROR(HistoricalFS!H10/HistoricalFS!H60,0) -> 0.58286695 | I35: =IFERROR(HistoricalFS!I10/HistoricalFS!I60,0) -> 0.54875176 | J35: =IFERROR(HistoricalFS!J10/HistoricalFS!J60,0) -> 0.58984305 | ... L35: =IFERROR(HistoricalFS!L10/HistoricalFS!L60,0) -> 0.68936924 | N35: =IFERROR(AVERAGE(C35:L35),0) -> 0.6939934 | O35: =IFERROR(MEDIAN(C35:L35),0) -> 0.6881016
B36: Capital Turnover Ratio(in days) | C36: =IFERROR(HistoricalFS!C10/SUM(HistoricalFS!C54:C55),0) -> 0.97396594 | D36: =IFERROR(HistoricalFS!D10/SUM(HistoricalFS!D54:D55),0) -> 0.80148354 | E36: =IFERROR(HistoricalFS!E10/SUM(HistoricalFS!E54:E55),0) -> 0.83855428 | G36: =IFERROR(HistoricalFS!G10/SUM(HistoricalFS!G54:G55),0) -> 0.90059225 | H36: =IFERROR(HistoricalFS!H10/SUM(HistoricalFS!H54:H55),0) -> 0.92111085 | I36: =IFERROR(HistoricalFS!I10/SUM(HistoricalFS!I54:I55),0) -> 0.88700896 | J36: =IFERROR(HistoricalFS!J10/SUM(HistoricalFS!J54:J55),0) -> 0.98002227 | K36: =IFERROR(HistoricalFS!K10/SUM(HistoricalFS!K54:K55),0) -> 1.1984994 | L36: =IFERROR(HistoricalFS!L10/SUM(HistoricalFS!L54:L55),0) -> 1.1107068 | N36: =IFERROR(AVERAGE(C36:L36),0) -> 0.9568827 | O36: =IFERROR(MEDIAN(C36:L36),0) -> 0.92111085
B38: (in days)
B39: Debtor days | C39: =IFERROR(365/C32,0) -> -14.512035 | D39: =IFERROR(365/D32,0) -> -11.054982 | E39: =IFERROR(365/E32,0) -> -18.471892 | F39: =IFERROR(365/F32,0) -> -44.288981 | G39: =IFERROR(365/G32,0) -> -33.152854 | H39: =IFERROR(365/H32,0) -> 33.177562 | I39: =IFERROR(365/I32,0) -> -18.015819 | J39: =IFERROR(365/J32,0) -> 0.50897239 | ... L39: =IFERROR(365/L32,0) -> -3.8340147 | N39: =IFERROR(AVERAGE(C39:L39),0) -> -11.422811 | O39: =IFERROR(MEDIAN(C39:L39),0) -> -12.783508
B40: Payable Days | C40: =IFERROR(365/C33,0) -> 161.44495 | D40: =IFERROR(365/D33,0) -> 167.42072 | E40: =IFERROR(365/E33,0) -> 164.56356 | F40: =IFERROR(365/F33,0) -> 202.55011 | G40: =IFERROR(365/G33,0) -> 227.50432 | H40: =IFERROR(365/H33,0) -> 185.87948 | I40: =IFERROR(365/I33,0) -> 203.14988 | J40: =IFERROR(365/J33,0) -> 191.89943 | ... L40: =IFERROR(365/L33,0) -> 166.52398 | N40: =IFERROR(AVERAGE(C40:L40),0) -> 183.09593 | O40: =IFERROR(MEDIAN(C40:L40),0) -> 176.6501
B41: Inventory Days | C41: =IFERROR(365/C34,0) -> 36.792277 | D41: =IFERROR(365/D34,0) -> 35.529857 | E41: =IFERROR(365/E34,0) -> 29.761412 | F41: =IFERROR(365/F34,0) -> 25.9853 | G41: =IFERROR(365/G34,0) -> 30.985307 | H41: =IFERROR(365/H34,0) -> 37.741394 | I41: =IFERROR(365/I34,0) -> 32.790558 | J41: =IFERROR(365/J34,0) -> 28.529966 | ... L41: =IFERROR(365/L34,0) -> 37.358987 | N41: =IFERROR(AVERAGE(C41:L41),0) -> 32.541515 | O41: =IFERROR(MEDIAN(C41:L41),0) -> 31.887932
B42: Cash Conversion Days | C42: =SUM(C39+C41)-C40 -> -139.16471 | D42: =SUM(D39+D41)-D40 -> -142.94584 | E42: =SUM(E39+E41)-E40 -> -153.27404 | F42: =SUM(F39+F41)-F40 -> -220.85379 | G42: =SUM(G39+G41)-G40 -> -229.67186 | H42: =SUM(H39+H41)-H40 -> -114.96052 | I42: =SUM(I39+I41)-I40 -> -188.37514 | J42: =SUM(J39+J41)-J40 -> -162.86049 | ... L42: =SUM(L39+L41)-L40 -> -132.99901 | N42: =IFERROR(AVERAGE(C42:L42),0) -> -161.97723 | O42: =IFERROR(MEDIAN(C42:L42),0) -> -148.10994
B44: CFO/Sales | C44: =IFERROR(HistoricalFS!C127/HistoricalFS!C10,0) -> 0.18620732 | D44: =IFERROR(HistoricalFS!D127/HistoricalFS!D10,0) -> 0.32869318 | E44: =IFERROR(HistoricalFS!E127/HistoricalFS!E10,0) -> 0.24580629 | F44: =IFERROR(HistoricalFS!F127/HistoricalFS!F10,0) -> 0.22330689 | G44: =IFERROR(HistoricalFS!G127/HistoricalFS!G10,0) -> 0.18632261 | H44: =IFERROR(HistoricalFS!H127/HistoricalFS!H10,0) -> 0.21824217 | I44: =IFERROR(HistoricalFS!I127/HistoricalFS!I10,0) -> 0.29089685 | J44: =IFERROR(HistoricalFS!J127/HistoricalFS!J10,0) -> 0.31498045 | ... L44: =IFERROR(HistoricalFS!L127/HistoricalFS!L10,0) -> 0.22848397 | N44: =IFERROR(AVERAGE(C44:L44),0) -> 0.24905326 | O44: =IFERROR(MEDIAN(C44:L44),0) -> 0.23714513
B45: CFO/Total Asssets | C45: =IFERROR(HistoricalFS!C127/HistoricalFS!C71,0) -> 0.067763833 | D45: =IFERROR(HistoricalFS!D127/HistoricalFS!D71,0) -> 0.10738149 | E45: =IFERROR(HistoricalFS!E127/HistoricalFS!E71,0) -> 0.081120247 | F45: =IFERROR(HistoricalFS!F127/HistoricalFS!F71,0) -> 0.069628846 | G45: =IFERROR(HistoricalFS!G127/HistoricalFS!G71,0) -> 0.053861089 | H45: =IFERROR(HistoricalFS!H127/HistoricalFS!H71,0) -> 0.063272329 | I45: =IFERROR(HistoricalFS!I127/HistoricalFS!I71,0) -> 0.081513276 | J45: =IFERROR(HistoricalFS!J127/HistoricalFS!J71,0) -> 0.1004932 | ... L45: =IFERROR(HistoricalFS!L127/HistoricalFS!L71,0) -> 0.085095944 | N45: =IFERROR(AVERAGE(C45:L45),0) -> 0.081557067 | O45: =IFERROR(MEDIAN(C45:L45),0) -> 0.081316762
B46: CFO/Total Debt | C46: =IFERROR(HistoricalFS!C127/HistoricalFS!C56,0) -> 0.14560625 | D46: =IFERROR(HistoricalFS!D127/HistoricalFS!D56,0) -> 0.24264744 | E46: =IFERROR(HistoricalFS!E127/HistoricalFS!E56,0) -> 0.17725229 | F46: =IFERROR(HistoricalFS!F127/HistoricalFS!F56,0) -> 0.1512482 | G46: =IFERROR(HistoricalFS!G127/HistoricalFS!G56,0) -> 0.10797319 | H46: =IFERROR(HistoricalFS!H127/HistoricalFS!H56,0) -> 0.1176922 | I46: =IFERROR(HistoricalFS!I127/HistoricalFS!I56,0) -> 0.15434275 | J46: =IFERROR(HistoricalFS!J127/HistoricalFS!J56,0) -> 0.1983243 | ... L46: =IFERROR(HistoricalFS!L127/HistoricalFS!L56,0) -> 0.17199182 | N46: =IFERROR(AVERAGE(C46:L46),0) -> 0.16786038 | O46: =IFERROR(MEDIAN(C46:L46),0) -> 0.16316729

Sheet Profit & Loss
A1: ='Data Sheet'!B1 -> NTPC LTD | H1: =UPDATE | M1: SCREENER.IN
A3: Narration | B3: ='Data Sheet'!B16 -> 42094 | C3: ='Data Sheet'!C16 -> 42460 | D3: ='Data Sheet'!D16 -> 42825 | E3: ='Data Sheet'!E16 -> 43190 | F3: ='Data Sheet'!F16 -> 43555 | G3: ='Data Sheet'!G16 -> 43921 | H3: ='Data Sheet'!H16 -> 44286 | I3: ='Data Sheet'!I16 -> 44651 | ... K3: ='Data Sheet'!K16 -> 45382 | L3: Trailing | M3: Best Case | N3: Worst Case
A4: Sales | B4: ='Data Sheet'!B17 -> 79956.74 | C4: ='Data Sheet'!C17 -> 73396.32 | D4: ='Data Sheet'!D17 -> 82042.49 | E4: ='Data Sheet'!E17 -> 88083.31 | F4: ='Data Sheet'!F17 -> 100286.54 | G4: ='Data Sheet'!G17 -> 109464.04 | H4: ='Data Sheet'!H17 -> 111531.15 | I4: ='Data Sheet'!I17 -> 132669.28 | ... K4: ='Data Sheet'!K17 -> 178500.88 | L4: =SUM(Quarters!H4:K4) -> 185891.75 | M4: =$K4+M23*K4 -> 208795.8 | N4: =$K4+N23*L4 -> 186197.77
A5: Expenses | B5: =SUM('Data Sheet'!B18,'Data Sheet'!B20:B24, -1*'Data Sheet'!B19) -> 62604.62 | C5: =SUM('Data Sheet'!C18,'Data Sheet'!C20:C24, -1*'Data Sheet'!C19) -> 54828.82 | D5: =SUM('Data Sheet'!D18,'Data Sheet'!D20:D24, -1*'Data Sheet'!D19) -> 60444.96 | E5: =SUM('Data Sheet'!E18,'Data Sheet'!E20:E24, -1*'Data Sheet'!E19) -> 65597.9 | F5: =SUM('Data Sheet'!F18,'Data Sheet'!F20:F24, -1*'Data Sheet'!F19) -> 77576.17 | G5: =SUM('Data Sheet'!G18,'Data Sheet'!G20:G24, -1*'Data Sheet'!G19) -> 77878.31 | H5: =SUM('Data Sheet'!H18,'Data Sheet'!H20:H24, -1*'Data Sheet'!H19) -> 77487.43 | I5: =SUM('Data Sheet'!I18,'Data Sheet'!I20:I24, -1*'Data Sheet'!I19) -> 92307.36 | ... K5: =SUM('Data Sheet'!K18,'Data Sheet'!K20:K24, -1*'Data Sheet'!K19) -> 127045.19 | L5: =SUM(Quarters!H5:K5) -> 133499.35 | M5: =M4-M6 -> 149070.07 | N5: =N4-N6 -> 135582.5
A6: Operating Profit | B6: =B4-B5 -> 17352.12 | C6: =C4-C5 -> 18567.5 | D6: =D4-D5 -> 21597.53 | E6: =E4-E5 -> 22485.41 | F6: =F4-F5 -> 22710.37 | G6: =G4-G5 -> 31585.73 | H6: =H4-H5 -> 34043.72 | I6: =I4-I5 -> 40361.92 | ... K6: =K4-K5 -> 51455.69 | L6: =SUM(Quarters!H6:K6) -> 52392.4 | M6: =M4*M24 -> 59725.726 | N6: =N4*N24 -> 50615.273
A7: Other Income | B7: ='Data Sheet'!B25 -> 2337.68 | C7: ='Data Sheet'!C25 -> 1187.69 | D7: ='Data Sheet'!D25 -> 1591.51 | E7: ='Data Sheet'!E25 -> 5575.55 | F7: ='Data Sheet'!F25 -> 2817.86 | G7: ='Data Sheet'!G25 -> 8208.96 | H7: ='Data Sheet'!H25 -> 5020.73 | I7: ='Data Sheet'!I25 -> 4808.98 | ... K7: ='Data Sheet'!K25 -> 5190.1 | L7: =SUM(Quarters!H7:K7) -> 6831.02 | M7: 0 | N7: 0
A8: Depreciation | B8: ='Data Sheet'!B26 -> 5564.61 | C8: ='Data Sheet'!C26 -> 5771.24 | D8: ='Data Sheet'!D26 -> 6009.91 | E8: ='Data Sheet'!E26 -> 7459.93 | F8: ='Data Sheet'!F26 -> 8669.03 | G8: ='Data Sheet'!G26 -> 10356.16 | H8: ='Data Sheet'!H26 -> 12450.31 | I8: ='Data Sheet'!I26 -> 13787.83 | ... K8: ='Data Sheet'!K26 -> 16203.63 | L8: =SUM(Quarters!H8:K8) -> 17008.88 | M8: =+$L8 -> 17008.88 | N8: =+$L8 -> 17008.88
A9: Interest | B9: ='Data Sheet'!B27 -> 3668.98 | C9: ='Data Sheet'!C27 -> 3366.03 | D9: ='Data Sheet'!D27 -> 3752.8 | E9: ='Data Sheet'!E27 -> 4446.59 | F9: ='Data Sheet'!F27 -> 5604.65 | G9: ='Data Sheet'!G27 -> 8189.01 | H9: ='Data Sheet'!H27 -> 9224.21 | I9: ='Data Sheet'!I27 -> 9375.68 | ... K9: ='Data Sheet'!K27 -> 12300.51 | L9: =SUM(Quarters!H9:K9) -> 12475.28 | M9: =+$L9 -> 12475.28 | N9: =+$L9 -> 12475.28
A10: Profit before tax | B10: ='Data Sheet'!B28 -> 10456.21 | C10: ='Data Sheet'!C28 -> 10617.92 | D10: ='Data Sheet'!D28 -> 13426.33 | E10: ='Data Sheet'!E28 -> 16154.44 | F10: ='Data Sheet'!F28 -> 11254.55 | G10: ='Data Sheet'!G28 -> 21249.52 | H10: ='Data Sheet'!H28 -> 17389.93 | I10: ='Data Sheet'!I28 -> 22007.39 | ... K10: ='Data Sheet'!K28 -> 28141.65 | L10: =SUM(Quarters!H10:K10) -> 29739.26 | M10: =M6+M7-SUM(M8:M9) -> 30241.566 | N10: =N6+N7-SUM(N8:N9) -> 21131.113
A11: Tax | B11: ='Data Sheet'!B29 -> 463.84 | C11: ='Data Sheet'!C29 -> -162.81 | D11: ='Data Sheet'!D29 -> 2712.39 | E11: ='Data Sheet'!E29 -> 5652.94 | F11: ='Data Sheet'!F29 -> -2779.94 | G11: ='Data Sheet'!G29 -> 9347.54 | H11: ='Data Sheet'!H29 -> 2420.53 | I11: ='Data Sheet'!I29 -> 5047.1 | ... K11: ='Data Sheet'!K29 -> 6809.2 | L11: =SUM(Quarters!H11:K11) -> 7193.2 | M11: =IF($L10>0,$L11/$L10,0) -> 0.24187555 | N11: =IF($L10>0,$L11/$L10,0) -> 0.24187555
A12: Net profit | B12: ='Data Sheet'!B30 -> 9986.34 | C12: ='Data Sheet'!C30 -> 10801.15 | D12: ='Data Sheet'!D30 -> 10719.64 | E12: ='Data Sheet'!E30 -> 10543.95 | F12: ='Data Sheet'!F30 -> 13736.68 | G12: ='Data Sheet'!G30 -> 11600.23 | H12: ='Data Sheet'!H30 -> 14634.63 | I12: ='Data Sheet'!I30 -> 16675.9 | ... K12: ='Data Sheet'!K30 -> 20811.89 | L12: =SUM(Quarters!H12:K12) -> 21979.97 | M12: =M10-M11*M10 -> 22926.871 | N12: =N10-N11*N10 -> 16020.013
A13: EPS | B13: =IF('Data Sheet'!B94>0,B12/'Data Sheet'!B94,0) -> 10.092717 | C13: =IF('Data Sheet'!C94>0,C12/'Data Sheet'!C94,0) -> 10.916207 | D13: =IF('Data Sheet'!D94>0,D12/'Data Sheet'!D94,0) -> 10.833829 | E13: =IF('Data Sheet'!E94>0,E12/'Data Sheet'!E94,0) -> 10.656267 | F13: =IF('Data Sheet'!F94>0,F12/'Data Sheet'!F94,0) -> 13.883007 | G13: =IF('Data Sheet'!G94>0,G12/'Data Sheet'!G94,0) -> 11.723799 | H13: =IF('Data Sheet'!H94>0,H12/'Data Sheet'!H94,0) -> 15.092382 | I13: =IF('Data Sheet'!I94>0,I12/'Data Sheet'!I94,0) -> 17.1975 | ... K13: =IF('Data Sheet'!K94>0,K12/'Data Sheet'!K94,0) -> 21.462858 | L13: =IF('Data Sheet'!$B6>0,'Profit & Loss'!L12/'Data Sheet'!$B6,0) -> 22.667551 | M13: =IF('Data Sheet'!$B6>0,'Profit & Loss'!M12/'Data Sheet'!$B6,0) -> 23.644073 | N13: =IF('Data Sheet'!$B6>0,'Profit & Loss'!N12/'Data Sheet'!$B6,0) -> 16.521154
A14: Price to earning | B14: =IF(B15>0,B15/B13,"") -> 12.124584 | C14: =IF(C15>0,C15/C13,"") -> 9.8358342 | D14: =IF(D15>0,D15/D13,"") -> 12.768339 | E14: =IF(E15>0,E15/E13,"") -> 13.271064 | F14: =IF(F15>0,F15/F13,"") -> 9.702509 | G14: =IF(G15>0,G15/G13,"") -> 7.1819724 | H14: =IF(H15>0,H15/H13,"") -> 7.0598531 | I14: =IF(I15>0,I15/I13,"") -> 7.8499781 | ... K14: =IF(K15>0,K15/K13,"") -> 15.645633 | L14: =IF(L13>0,L15/L13,0) -> 13.931809 | M14: =M25 -> 13.931809 | N14: =N25 -> 10.284748
A15: Price | B15: ='Data Sheet'!B91 -> 122.37 | C15: ='Data Sheet'!C91 -> 107.37 | D15: ='Data Sheet'!D91 -> 138.33 | E15: ='Data Sheet'!E91 -> 141.42 | F15: ='Data Sheet'!F91 -> 134.7 | G15: ='Data Sheet'!G91 -> 84.2 | H15: ='Data Sheet'!H91 -> 106.55 | I15: ='Data Sheet'!I91 -> 135 | ... K15: ='Data Sheet'!K91 -> 335.8 | L15: ='Data Sheet'!B8 -> 315.8 | M15: =M13*M14 -> 329.40471 | N15: =N13*N14 -> 169.91591
A17: RATIOS:
A18: Dividend Payout | B18: =IF('Data Sheet'!B30>0, 'Data Sheet'!B31/'Data Sheet'!B30, 0) -> 0.20641797 | C18: =IF('Data Sheet'!C30>0, 'Data Sheet'!C31/'Data Sheet'!C30, 0) -> 0.25573481 | D18: =IF('Data Sheet'!D30>0, 'Data Sheet'!D31/'Data Sheet'!D30, 0) -> 0.36767373 | E18: =IF('Data Sheet'!E30>0, 'Data Sheet'!E31/'Data Sheet'!E30, 0) -> 0.40038885 | F18: =IF('Data Sheet'!F30>0, 'Data Sheet'!F31/'Data Sheet'!F30, 0) -> 0.43794352 | G18: =IF('Data Sheet'!G30>0, 'Data Sheet'!G31/'Data Sheet'!G30, 0) -> 0.26868347 | H18: =IF('Data Sheet'!H30>0, 'Data Sheet'!H31/'Data Sheet'!H30, 0) -> 0.40748895 | I18: =IF('Data Sheet'!I30>0, 'Data Sheet'!I31/'Data Sheet'!I30, 0) -> 0.4070347 | ... K18: =IF('Data Sheet'!K30>0, 'Data Sheet'!K31/'Data Sheet'!K30, 0) -> 0.36108782
A19: OPM | B19: =IF(B6>0,B6/B4,0) -> 0.21701885 | C19: =IF(C6>0,C6/C4,0) -> 0.2529759 | D19: =IF(D6>0,D6/D4,0) -> 0.2632481 | E19: =IF(E6>0,E6/E4,0) -> 0.25527435 | F19: =IF(F6>0,F6/F4,0) -> 0.22645482 | G19: =IF(G6>0,G6/G4,0) -> 0.28854892 | H19: =IF(H6>0,H6/H4,0) -> 0.30523957 | I19: =IF(I6>0,I6/I4,0) -> 0.30422959 | ... L19: =IF(L6>0,L6/L4,0) -> 0.2818436
G22: TRENDS: | H22: 10 YEARS | I22: 7 YEARS | J22: 5 YEARS | K22: 3 YEARS | L22: RECENT | M22: BEST | N22: WORST
G23: Sales Growth | H23: =IF(B4=0,"",POWER($K4/B4,1/9)-1) -> 0.093336685 | I23: =IF(D4=0,"",POWER($K4/D4,1/7)-1) -> 0.11745178 | J23: =IF(F4=0,"",POWER($K4/F4,1/5)-1) -> 0.12222398 | K23: =IF(H4=0,"",POWER($K4/H4, 1/3)-1) -> 0.16971859 | L23: =IF(ISERROR(MAX(IF(J4=0,"",(K4-J4)/J4),IF(K4=0,"",(L4-K4)/K4))),"",MAX(IF(J4=0,"",(K4-J4)/J4),IF(K4=0,"",(L4-K4)/K4))) -> 0.04140523 | M23: =MAX(K23:L23) -> 0.16971859 | N23: =MIN(H23:L23) -> 0.04140523
G24: OPM | H24: =IF(SUM(B4:$K$4)=0,"",SUMPRODUCT(B19:$K$19,B4:$K$4)/SUM(B4:$K$4)) -> 0.27183608 | I24: =IF(SUM(E4:$K$4)=0,"",SUMPRODUCT(E19:$K$19,E4:$K$4)/SUM(E4:$K$4)) -> 0.27905315 | J24: =IF(SUM(G4:$K$4)=0,"",SUMPRODUCT(G19:$K$19,G4:$K$4)/SUM(G4:$K$4)) -> 0.28945647 | K24: =IF(SUM(I4:$K$4)=0, "", SUMPRODUCT(I19:$K$19,I4:$K$4)/SUM(I4:$K$4)) -> 0.28604851 | L24: =L19 -> 0.2818436 | M24: =MAX(K24:L24) -> 0.28604851 | N24: =MIN(H24:L24) -> 0.27183608
G25: Price to Earning | H25: =IF(ISERROR(AVERAGEIF(B14:$L14,">0")),"",AVERAGEIF(B14:$L14,">0")) -> 10.855529 | I25: =IF(ISERROR(AVERAGEIF(E14:$L14,">0")),"",AVERAGEIF(E14:$L14,">0")) -> 10.585258 | J25: =IF(ISERROR(AVERAGEIF(G14:$L14,">0")),"",AVERAGEIF(G14:$L14,">0")) -> 10.284748 | K25: =IF(ISERROR(AVERAGEIF(I14:$L14,">0")),"",AVERAGEIF(I14:$L14,">0")) -> 11.866666 | L25: =L14 -> 13.931809 | M25: =MAX(K25:L25) -> 13.931809 | N25: =MIN(H25:L25) -> 10.284748
A27: Sales Growth (YoY) | C27: =C4/B4-1 -> -0.082049618 | D27: =D4/C4-1 -> 0.11780114 | E27: =E4/D4-1 -> 0.073630383 | F27: =F4/E4-1 -> 0.13854191 | G27: =G4/F4-1 -> 0.091512779 | H27: =H4/G4-1 -> 0.018883918 | I27: =I4/H4-1 -> 0.18952669 | J27: =J4/I4-1 -> 0.32816866 | K27: =K4/J4-1 -> 0.013017063
A29: Dividend Growth (YoY) | C29: =HistoricalFS!D45/HistoricalFS!C45-1 -> 0.34000369 | D29: =HistoricalFS!E45/HistoricalFS!D45-1 -> 0.42686525 | E29: =HistoricalFS!F45/HistoricalFS!E45-1 -> 0.071130811 | F29: =HistoricalFS!G45/HistoricalFS!F45-1 -> 0.42499905 | G29: =HistoricalFS!H45/HistoricalFS!G45-1 -> -0.48190708 | H29: =HistoricalFS!I45/HistoricalFS!H45-1 -> 0.95237988 | I29: =HistoricalFS!J45/HistoricalFS!I45-1 -> 0.13821194 | J29: =HistoricalFS!K45/HistoricalFS!J45-1 -> 0.035714759 | K29: =HistoricalFS!L45/HistoricalFS!K45-1 -> 0.068964978
A31: Market Capitalization | B31: ='Data Sheet'!B94*'Data Sheet'!B91 -> 121080.22 | C31: ='Data Sheet'!C94*'Data Sheet'!C91 -> 106238.32 | D31: ='Data Sheet'!D94*'Data Sheet'!D91 -> 136872 | E31: ='Data Sheet'!E94*'Data Sheet'!E91 -> 139929.43 | F31: ='Data Sheet'!F94*'Data Sheet'!F91 -> 133280.26 | G31: ='Data Sheet'!G94*'Data Sheet'!G91 -> 83312.532 | H31: ='Data Sheet'!H94*'Data Sheet'!H91 -> 103318.34 | I31: ='Data Sheet'!I94*'Data Sheet'!I91 -> 130905.45 | ... K31: ='Data Sheet'!K94*'Data Sheet'!K91 -> 325615.19
A32: Debt | B32: ='Data Sheet'!B60 -> 102252 | C32: ='Data Sheet'!C60 -> 99423.55 | D32: ='Data Sheet'!D60 -> 113773.2 | E32: ='Data Sheet'!E60 -> 130048.56 | F32: ='Data Sheet'!F60 -> 173058.23 | G32: ='Data Sheet'!G60 -> 202984.31 | H32: ='Data Sheet'!H60 -> 210207.87 | I32: ='Data Sheet'!I60 -> 210706.56 | ... K32: ='Data Sheet'!K60 -> 237130.98
A33: Cash | B33: ='Data Sheet'!B70 -> 14251.61 | C33: ='Data Sheet'!C70 -> 4938.32 | D33: ='Data Sheet'!D70 -> 3301.46 | E33: ='Data Sheet'!E70 -> 4387.6 | F33: ='Data Sheet'!F70 -> 2933.43 | G33: ='Data Sheet'!G70 -> 3214.29 | H33: ='Data Sheet'!H70 -> 4387.8 | I33: ='Data Sheet'!I70 -> 4458.08 | ... K33: ='Data Sheet'!K70 -> 6847.34
A34: Enterprise Value | B34: =B31+B32-B33 -> 209080.61 | C34: =C31+C32-C33 -> 200723.55 | D34: =D31+D32-D33 -> 247343.74 | E34: =E31+E32-E33 -> 265590.39 | F34: =F31+F32-F33 -> 303405.06 | G34: =G31+G32-G33 -> 283082.55 | H34: =H31+H32-H33 -> 309138.41 | I34: =I31+I32-I33 -> 337153.93 | ... K34: =K31+K32-K33 -> 555898.83
A36: EV / EBITDA | B36: =B34/'Data Sheet'!B34 -> 10.62198 | C36: =C34/'Data Sheet'!C34 -> 10.150056 | D36: =D34/'Data Sheet'!D34 -> 10.663786 | E36: =E34/'Data Sheet'!E34 -> 9.4504686 | F36: =F34/'Data Sheet'!F34 -> 12.025367 | G36: =G34/'Data Sheet'!G34 -> 7.167928 | H36: =H34/'Data Sheet'!H34 -> 7.981951 | I36: =I34/'Data Sheet'!I34 -> 7.5112529 | ... K36: =K34/'Data Sheet'!K34 -> 9.9046156
A37: EV / Sales | B37: =B34/B4 -> 2.6149216 | C37: =C34/C4 -> 2.7347904 | D37: =D34/D4 -> 3.0148249 | E37: =E34/E4 -> 3.0152181 | F37: =F34/F4 -> 3.0253817 | G37: =G34/G4 -> 2.5860781 | H37: =H34/H4 -> 2.7717674 | I37: =I34/I4 -> 2.5413112 | ... K37: =K34/K4 -> 3.1142638
A39: Price / BV | B39: ='Profit & Loss'!B31/'Balance Sheet'!B26 -> 1.4748977 | C39: ='Profit & Loss'!C31/'Balance Sheet'!C26 -> 1.1601163 | D39: ='Profit & Loss'!D31/'Balance Sheet'!D26 -> 1.3989654 | E39: ='Profit & Loss'!E31/'Balance Sheet'!E26 -> 1.3511466 | F39: ='Profit & Loss'!F31/'Balance Sheet'!F26 -> 1.1968822 | G39: ='Profit & Loss'!G31/'Balance Sheet'!G26 -> 0.70105285 | H39: ='Profit & Loss'!H31/'Balance Sheet'!H26 -> 0.82169235 | I39: ='Profit & Loss'!I31/'Balance Sheet'!I26 -> 0.96699293 | ... K39: ='Profit & Loss'!K31/'Balance Sheet'!K26 -> 2.0261133

Sheet Balance Sheet
A1: ='Profit & Loss'!A1 -> NTPC LTD | E1: =UPDATE | J1: SCREENER.IN
A3: Narration | B3: ='Data Sheet'!B57 -> 42094 | C3: ='Data Sheet'!C57 -> 42460 | D3: ='Data Sheet'!D57 -> 42825 | E3: ='Data Sheet'!E57 -> 43190 | F3: ='Data Sheet'!F57 -> 43555 | G3: ='Data Sheet'!G57 -> 43921 | H3: ='Data Sheet'!H57 -> 44286 | I3: ='Data Sheet'!I57 -> 44651 | ... K3: ='Data Sheet'!K57 -> 45382
A4: Equity Share Capital | B4: ='Data Sheet'!B58 -> 8245.46 | C4: ='Data Sheet'!C58 -> 8245.46 | D4: ='Data Sheet'!D58 -> 8245.46 | E4: ='Data Sheet'!E58 -> 8245.46 | F4: ='Data Sheet'!F58 -> 9894.56 | G4: ='Data Sheet'!G58 -> 9894.56 | H4: ='Data Sheet'!H58 -> 9696.67 | I4: ='Data Sheet'!I58 -> 9696.67 | ... K4: ='Data Sheet'!K58 -> 9696.67
A5: Reserves | B5: ='Data Sheet'!B59 -> 73848.52 | C5: ='Data Sheet'!C59 -> 83330.12 | D5: ='Data Sheet'!D59 -> 89592.56 | E5: ='Data Sheet'!E59 -> 95318.01 | F5: ='Data Sheet'!F59 -> 101461.65 | G5: ='Data Sheet'!G59 -> 108944.6 | H5: ='Data Sheet'!H59 -> 116041.8 | I5: ='Data Sheet'!I59 -> 125677.07 | ... K5: ='Data Sheet'!K59 -> 151012.6
A6: Borrowings | B6: ='Data Sheet'!B60 -> 102252 | C6: ='Data Sheet'!C60 -> 99423.55 | D6: ='Data Sheet'!D60 -> 113773.2 | E6: ='Data Sheet'!E60 -> 130048.56 | F6: ='Data Sheet'!F60 -> 173058.23 | G6: ='Data Sheet'!G60 -> 202984.31 | H6: ='Data Sheet'!H60 -> 210207.87 | I6: ='Data Sheet'!I60 -> 210706.56 | ... K6: ='Data Sheet'!K60 -> 237130.98
A7: Other Liabilities | B7: ='Data Sheet'!B61 -> 35366.06 | C7: ='Data Sheet'!C61 -> 33665.93 | D7: ='Data Sheet'!D61 -> 36989.6 | E7: ='Data Sheet'!E61 -> 48880.23 | F7: ='Data Sheet'!F61 -> 62508.55 | G7: ='Data Sheet'!G61 -> 55745.53 | H7: ='Data Sheet'!H61 -> 62075.45 | I7: ='Data Sheet'!I61 -> 69751.12 | ... K7: ='Data Sheet'!K61 -> 81437.47
A8: Total | B8: ='Data Sheet'!B62 -> 219712.04 | C8: ='Data Sheet'!C62 -> 224665.06 | D8: ='Data Sheet'!D62 -> 248600.82 | E8: ='Data Sheet'!E62 -> 282492.26 | F8: ='Data Sheet'!F62 -> 346922.99 | G8: ='Data Sheet'!G62 -> 377569 | H8: ='Data Sheet'!H62 -> 398021.79 | I8: ='Data Sheet'!I62 -> 415831.42 | ... K8: ='Data Sheet'!K62 -> 479277.72
A10: Net Block | B10: ='Data Sheet'!B63 -> 91853.02 | C10: ='Data Sheet'!C63 -> 92929.36 | D10: ='Data Sheet'!D63 -> 104531.66 | E10: ='Data Sheet'!E63 -> 128245.42 | F10: ='Data Sheet'!F63 -> 150984.53 | G10: ='Data Sheet'!G63 -> 187802.79 | H10: ='Data Sheet'!H63 -> 203245.18 | I10: ='Data Sheet'!I63 -> 224923.02 | ... K10: ='Data Sheet'!K63 -> 258933.63
A11: Capital Work in Progress | B11: ='Data Sheet'!B64 -> 67554.69 | C11: ='Data Sheet'!C64 -> 75045.53 | D11: ='Data Sheet'!D64 -> 86895.71 | E11: ='Data Sheet'!E64 -> 83386.1 | F11: ='Data Sheet'!F64 -> 118396.86 | G11: ='Data Sheet'!G64 -> 98508.47 | H11: ='Data Sheet'!H64 -> 97506.03 | I11: ='Data Sheet'!I64 -> 91126.26 | ... K11: ='Data Sheet'!K64 -> 87664.45
A12: Investments | B12: ='Data Sheet'!B65 -> 1901.51 | C12: ='Data Sheet'!C65 -> 6473.36 | D12: ='Data Sheet'!D65 -> 7613.92 | E12: ='Data Sheet'!E65 -> 8875.61 | F12: ='Data Sheet'!F65 -> 8132.31 | G12: ='Data Sheet'!G65 -> 9306.59 | H12: ='Data Sheet'!H65 -> 10589.25 | I12: ='Data Sheet'!I65 -> 10626.24 | ... K12: ='Data Sheet'!K65 -> 15884.56
A13: Other Assets | B13: ='Data Sheet'!B66 -> 58402.82 | C13: ='Data Sheet'!C66 -> 50216.81 | D13: ='Data Sheet'!D66 -> 49559.53 | E13: ='Data Sheet'!E66 -> 61985.13 | F13: ='Data Sheet'!F66 -> 69409.29 | G13: ='Data Sheet'!G66 -> 81951.15 | H13: ='Data Sheet'!H66 -> 86681.33 | I13: ='Data Sheet'!I66 -> 89155.9 | ... K13: ='Data Sheet'!K66 -> 116795.08
A14: Total | B14: ='Data Sheet'!B67 -> 219712.04 | C14: ='Data Sheet'!C67 -> 224665.06 | D14: ='Data Sheet'!D67 -> 248600.82 | E14: ='Data Sheet'!E67 -> 282492.26 | F14: ='Data Sheet'!F67 -> 346922.99 | G14: ='Data Sheet'!G67 -> 377569 | H14: ='Data Sheet'!H67 -> 398021.79 | I14: ='Data Sheet'!I67 -> 415831.42 | ... K14: ='Data Sheet'!K67 -> 479277.72
A16: Working Capital | B16: =B13-B7 -> 23036.76 | C16: =C13-C7 -> 16550.88 | D16: =D13-D7 -> 12569.93 | E16: =E13-E7 -> 13104.9 | F16: =F13-F7 -> 6900.74 | G16: =G13-G7 -> 26205.62 | H16: =H13-H7 -> 24605.88 | I16: =I13-I7 -> 19404.78 | ... K16: =K13-K7 -> 35357.61
A17: Debtors | B17: ='Data Sheet'!B68 -> 9249.92 | C17: ='Data Sheet'!C68 -> 8288.79 | D17: ='Data Sheet'!D68 -> 8963.89 | E17: ='Data Sheet'!E68 -> 8812.19 | F17: ='Data Sheet'!F68 -> 12363.52 | G17: ='Data Sheet'!G68 -> 20314.59 | H17: ='Data Sheet'!H68 -> 28199.83 | I17: ='Data Sheet'!I68 -> 27970.87 | ... K17: ='Data Sheet'!K68 -> 33349.68
A18: Inventory | B18: ='Data Sheet'!B69 -> 8059.7 | C18: ='Data Sheet'!C69 -> 7144.55 | D18: ='Data Sheet'!D69 -> 6689.59 | E18: ='Data Sheet'!E69 -> 6270.88 | F18: ='Data Sheet'!F69 -> 8513.45 | G18: ='Data Sheet'!G69 -> 11318.7 | H18: ='Data Sheet'!H69 -> 10019.64 | I18: ='Data Sheet'!I69 -> 10370 | ... K18: ='Data Sheet'!K69 -> 18270.17
A20: Debtor Days | B20: =IF('Profit & Loss'!B4>0,'Balance Sheet'!B17/('Profit & Loss'!B4/365),0) -> 42.225593 | C20: =IF('Profit & Loss'!C4>0,'Balance Sheet'!C17/('Profit & Loss'!C4/365),0) -> 41.220164 | D20: =IF('Profit & Loss'!D4>0,'Balance Sheet'!D17/('Profit & Loss'!D4/365),0) -> 39.879578 | E20: =IF('Profit & Loss'!E4>0,'Balance Sheet'!E17/('Profit & Loss'!E4/365),0) -> 36.515991 | F20: =IF('Profit & Loss'!F4>0,'Balance Sheet'!F17/('Profit & Loss'!F4/365),0) -> 44.997911 | G20: =IF('Profit & Loss'!G4>0,'Balance Sheet'!G17/('Profit & Loss'!G4/365),0) -> 67.737545 | H20: =IF('Profit & Loss'!H4>0,'Balance Sheet'!H17/('Profit & Loss'!H4/365),0) -> 92.287562 | I20: =IF('Profit & Loss'!I4>0,'Balance Sheet'!I17/('Profit & Loss'!I4/365),0) -> 76.953516 | ... K20: =IF('Profit & Loss'!K4>0,'Balance Sheet'!K17/('Profit & Loss'!K4/365),0) -> 68.193687
A21: Inventory Turnover | B21: =IF('Balance Sheet'!B18>0,'Profit & Loss'!B4/'Balance Sheet'!B18,0) -> 9.9205603 | C21: =IF('Balance Sheet'!C18>0,'Profit & Loss'!C4/'Balance Sheet'!C18,0) -> 10.27305 | D21: =IF('Balance Sheet'!D18>0,'Profit & Loss'!D4/'Balance Sheet'!D18,0) -> 12.264203 | E21: =IF('Balance Sheet'!E18>0,'Profit & Loss'!E4/'Balance Sheet'!E18,0) -> 14.046403 | F21: =IF('Balance Sheet'!F18>0,'Profit & Loss'!F4/'Balance Sheet'!F18,0) -> 11.779777 | G21: =IF('Balance Sheet'!G18>0,'Profit & Loss'!G4/'Balance Sheet'!G18,0) -> 9.6710788 | H21: =IF('Balance Sheet'!H18>0,'Profit & Loss'!H4/'Balance Sheet'!H18,0) -> 11.131253 | I21: =IF('Balance Sheet'!I18>0,'Profit & Loss'!I4/'Balance Sheet'!I18,0) -> 12.793566 | ... K21: =IF('Balance Sheet'!K18>0,'Profit & Loss'!K4/'Balance Sheet'!K18,0) -> 9.7700722
A23: Return on Equity | B23: =IF(SUM('Balance Sheet'!B4:B5)>0,'Profit & Loss'!B12/SUM('Balance Sheet'!B4:B5),"") -> 0.12164522 | C23: =IF(SUM('Balance Sheet'!C4:C5)>0,'Profit & Loss'!C12/SUM('Balance Sheet'!C4:C5),"") -> 0.11794793 | D23: =IF(SUM('Balance Sheet'!D4:D5)>0,'Profit & Loss'!D12/SUM('Balance Sheet'!D4:D5),"") -> 0.10956518 | E23: =IF(SUM('Balance Sheet'!E4:E5)>0,'Profit & Loss'!E12/SUM('Balance Sheet'!E4:E5),"") -> 0.10181148 | F23: =IF(SUM('Balance Sheet'!F4:F5)>0,'Profit & Loss'!F12/SUM('Balance Sheet'!F4:F5),"") -> 0.12335801 | G23: =IF(SUM('Balance Sheet'!G4:G5)>0,'Profit & Loss'!G12/SUM('Balance Sheet'!G4:G5),"") -> 0.097612858 | H23: =IF(SUM('Balance Sheet'!H4:H5)>0,'Profit & Loss'!H12/SUM('Balance Sheet'!H4:H5),"") -> 0.11638944 | I23: =IF(SUM('Balance Sheet'!I4:I5)>0,'Profit & Loss'!I12/SUM('Balance Sheet'!I4:I5),"") -> 0.12318416 | ... K23: =IF(SUM('Balance Sheet'!K4:K5)>0,'Profit & Loss'!K12/SUM('Balance Sheet'!K4:K5),"") -> 0.12950025
A24: Return on Capital Emp | C24: =IF((B4+B5+B6+C4+C5+C6)>0,('Profit & Loss'!C10+'Profit & Loss'!C9)*2/(B4+B5+B6+C4+C5+C6),"") -> 0.074512493 | D24: =IF((C4+C5+C6+D4+D5+D6)>0,('Profit & Loss'!D10+'Profit & Loss'!D9)*2/(C4+C5+C6+D4+D5+D6),"") -> 0.08533874 | E24: =IF((D4+D5+D6+E4+E5+E6)>0,('Profit & Loss'!E10+'Profit & Loss'!E9)*2/(D4+D5+D6+E4+E5+E6),"") -> 0.092542472 | F24: =IF((E4+E5+E6+F4+F5+F6)>0,('Profit & Loss'!F10+'Profit & Loss'!F9)*2/(E4+E5+E6+F4+F5+F6),"") -> 0.06509011 | G24: =IF((F4+F5+F6+G4+G5+G6)>0,('Profit & Loss'!G10+'Profit & Loss'!G9)*2/(F4+F5+F6+G4+G5+G6),"") -> 0.097118737 | H24: =IF((G4+G5+G6+H4+H5+H6)>0,('Profit & Loss'!H10+'Profit & Loss'!H9)*2/(G4+G5+G6+H4+H5+H6),"") -> 0.080922352 | I24: =IF((H4+H5+H6+I4+I5+I6)>0,('Profit & Loss'!I10+'Profit & Loss'!I9)*2/(H4+H5+H6+I4+I5+I6),"") -> 0.092028869 | J24: =IF((I4+I5+I6+J4+J5+J6)>0,('Profit & Loss'!J10+'Profit & Loss'!J9)*2/(I4+I5+I6+J4+J5+J6),"") -> 0.09878156 | K24: =IF((J4+J5+J6+K4+K5+K6)>0,('Profit & Loss'!K10+'Profit & Loss'!K9)*2/(J4+J5+J6+K4+K5+K6),"") -> 0.10534877
A26: Book Value | B26: =B4+B5 -> 82093.98 | C26: =C4+C5 -> 91575.58 | D26: =D4+D5 -> 97838.02 | E26: =E4+E5 -> 103563.47 | F26: =F4+F5 -> 111356.21 | G26: =G4+G5 -> 118839.16 | H26: =H4+H5 -> 125738.47 | I26: =I4+I5 -> 135373.74 | ... K26: =K4+K5 -> 160709.27

Sheet Cash Flow
A1: ='Balance Sheet'!A1 -> NTPC LTD | E1: =UPDATE | J1: SCREENER.IN
A3: Narration | B3: ='Data Sheet'!B82 -> 42094 | C3: ='Data Sheet'!C82 -> 42460 | D3: ='Data Sheet'!D82 -> 42825 | E3: ='Data Sheet'!E82 -> 43190 | F3: ='Data Sheet'!F82 -> 43555 | G3: ='Data Sheet'!G82 -> 43921 | H3: ='Data Sheet'!H82 -> 44286 | I3: ='Data Sheet'!I82 -> 44651 | ... K3: ='Data Sheet'!K82 -> 45382
A4: Cash from Operating Activity | B4: ='Data Sheet'!B83 -> 14888.53 | C4: ='Data Sheet'!C83 -> 24124.87 | D4: ='Data Sheet'!D83 -> 20166.56 | E4: ='Data Sheet'!E83 -> 19669.61 | F4: ='Data Sheet'!F83 -> 18685.65 | G4: ='Data Sheet'!G83 -> 23889.67 | H4: ='Data Sheet'!H83 -> 32444.06 | I4: ='Data Sheet'!I83 -> 41788.23 | ... K4: ='Data Sheet'!K83 -> 40784.59
A5: Cash from Investing Activity | B5: ='Data Sheet'!B84 -> -15977.16 | C5: ='Data Sheet'!C84 -> -19161.54 | D5: ='Data Sheet'!D84 -> -24480.13 | E5: ='Data Sheet'!E84 -> -20678.11 | F5: ='Data Sheet'!F84 -> -24063.28 | G5: ='Data Sheet'!G84 -> -29628.15 | H5: ='Data Sheet'!H84 -> -21034.45 | I5: ='Data Sheet'!I84 -> -22890.92 | ... K5: ='Data Sheet'!K84 -> -32141.37
A6: Cash from Financing Activity | B6: ='Data Sheet'!B85 -> -1474.5 | C6: ='Data Sheet'!C85 -> -3899.34 | D6: ='Data Sheet'!D85 -> 3137.96 | E6: ='Data Sheet'!E85 -> 1027.78 | F6: ='Data Sheet'!F85 -> 4926.75 | G6: ='Data Sheet'!G85 -> 6004.26 | H6: ='Data Sheet'!H85 -> -11049.11 | I6: ='Data Sheet'!I85 -> -19171.56 | ... K6: ='Data Sheet'!K85 -> -8245.53
A7: Net Cash Flow | B7: ='Data Sheet'!B86 -> -2563.13 | C7: ='Data Sheet'!C86 -> 1063.99 | D7: ='Data Sheet'!D86 -> -1175.61 | E7: ='Data Sheet'!E86 -> 19.28 | F7: ='Data Sheet'!F86 -> -450.88 | G7: ='Data Sheet'!G86 -> 265.78 | H7: ='Data Sheet'!H86 -> 360.5 | I7: ='Data Sheet'!I86 -> -274.25 | ... K7: ='Data Sheet'!K86 -> 397.69

Sheet Forecasting
B3: ="Forecasting" & "- " & 'Data Sheet'!B1 -> Forecasting- NTPC LTD
B7: ='Data Sheet'!$B$1&" - " & 'Data Sheet'!A17 & " Forecasting" -> NTPC LTD - Sales Forecasting | G7: ='Data Sheet'!$B$1&" - " &HistoricalFS!B22 & " Forecasting" -> NTPC LTD - EBITDA Forecasting | L7: ='Data Sheet'!$B$1&" - " &HistoricalFS!B42 & " Forecasting" -> NTPC LTD - EPS Forecasting
B8: Year Growth | C8: Year | D8: Sales | E8: Sales Growth | G8: Year Growth | H8: Year | I8: Sales | J8: Sales Growth | L8: Year Growth | M8: Year | N8: Sales | O8: Sales Growth
B9: 1 | C9: ='Data Sheet'!$B$16 -> 42094 | D9: {=TRANSPOSE('Data Sheet'!B17:K17)} -> 79956.74 | E9: - | G9: 1 | H9: ='Data Sheet'!$B$16 -> 42094 | I9: {=TRANSPOSE(HistoricalFS!C22:L22)} -> 17352.12 | J9: - | L9: 1 | M9: ='Data Sheet'!$B$16 -> 42094 | N9: {=TRANSPOSE(HistoricalFS!C42:L42)} -> 7.7362299 | O9: -
B10: 2 | C10: =C9+365 -> 42459 | D10: 73396.32 | E10: =D10/D9-1 -> -0.082049618 | G10: 2 | H10: =H9+365 -> 42459 | I10: 18567.5 | J10: =I10/I9-1 -> 0.070042162 | L10: 2 | M10: =M9+365 -> 42459 | N10: 9.6952277 | O10: =N10/N9-1 -> 0.25322384
B11: 3 | C11: =C10+365 -> 42824 | D11: 82042.49 | E11: =D11/D10-1 -> 0.11780114 | G11: 3 | H11: =H10+365 -> 42824 | I11: 21597.53 | J11: =I11/I10-1 -> 0.16318998 | L11: 3 | M11: =M10+365 -> 42824 | N11: 9.2196046 | O11: =N11/N10-1 -> -0.049057442
B12: 4 | C12: =C11+365 -> 43189 | D12: 88083.31 | E12: =D12/D11-1 -> 0.073630383 | G12: 4 | H12: =H11+365 -> 43189 | I12: 22485.41 | J12: =I12/I11-1 -> 0.041110257 | L12: 4 | M12: =M11+365 -> 43189 | N12: 4.9784226 | O12: =N12/N11-1 -> -0.46001778
B13: 5 | C13: =C12+365 -> 43554 | D13: 100286.54 | E13: =D13/D12-1 -> 0.13854191 | G13: 5 | H13: =H12+365 -> 43554 | I13: 22710.37 | J13: =I13/I12-1 -> 0.01000471 | L13: 5 | M13: =M12+365 -> 43554 | N13: 11.336113 | O13: =N13/N12-1 -> 1.2770491
B14: 6 | C14: =C13+365 -> 43919 | D14: 109464.04 | E14: =D14/D13-1 -> 0.091512779 | G14: 6 | H14: =H13+365 -> 43919 | I14: 31585.73 | J14: =I14/I13-1 -> 0.39080649 | L14: 6 | M14: =M13+365 -> 43919 | N14: 3.7323591 | O14: =N14/N13-1 -> -0.67075494
B15: 7 | C15: =C14+365 -> 44284 | D15: 111531.15 | E15: =D15/D14-1 -> 0.018883918 | G15: 7 | H15: =H14+365 -> 44284 | I15: 34043.72 | J15: =I15/I14-1 -> 0.077819636 | L15: 7 | M15: =M14+365 -> 44284 | N15: 10.259851 | O15: =N15/N14-1 -> 1.7488918
B16: 8 | C16: =C15+365 -> 44649 | D16: 132669.28 | E16: =D16/D15-1 -> 0.18952669 | G16: 8 | H16: =H15+365 -> 44649 | I16: 40361.92 | J16: =I16/I15-1 -> 0.18559076 | L16: 8 | M16: =M15+365 -> 44649 | N16: 12.531387 | O16: =N16/N15-1 -> 0.22140045
B17: 9 | C17: =C16+365 -> 45014 | D17: 176207.18 | E17: =D17/D16-1 -> 0.32816866 | G17: 9 | H17: =H16+365 -> 45014 | I17: 47595.95 | J17: =I17/I16-1 -> 0.17922909 | L17: 9 | M17: =M16+365 -> 45014 | N17: 15.01584 | O17: =N17/N16-1 -> 0.19825846
B18: 10 | C18: =C17+365 -> 45379 | D18: 178500.88 | E18: =D18/D17-1 -> 0.013017063 | G18: 10 | H18: =H17+365 -> 45379 | I18: 51455.69 | J18: =I18/I17-1 -> 0.081093875 | L18: 10 | M18: =M17+365 -> 45379 | N18: 16.647261 | O18: =N18/N17-1 -> 0.10864667
B19: 11 | C19: =C18+365 -> 45744 | D19: =FORECAST(B19,$D$9:$D$18,$B$9:$B$18) -> 177854.73 | E19: =D19/D18-1 -> -0.003619844 | G19: 11 | H19: =H18+365 -> 45744 | I19: =FORECAST(G19,I9:I18,G9:G18) -> 52359.045 | J19: =I19/I18-1 -> 0.017555972 | L19: 11 | M19: =M18+365 -> 45744 | N19: =FORECAST(L19,$N$9:$N$18,$L$9:$L$18) -> 14.856664 | O19: =N19/N18-1 -> -0.10756111
B20: 12 | C20: =C19+365 -> 46109 | D20: =FORECAST(B20,$D$9:$D$18,$B$9:$B$18) -> 189607.63 | E20: =D20/D19-1 -> 0.066081448 | G20: 12 | H20: =H19+365 -> 46109 | I20: =FORECAST(G20,I10:I19,G10:G19) -> 57412.832 | J20: =I20/I19-1 -> 0.096521761 | L20: 12 | M20: =M19+365 -> 46109 | N20: =FORECAST(L20,$N$9:$N$18,$L$9:$L$18) -> 15.718742 | O20: =N20/N19-1 -> 0.058026413
B21: 13 | C21: =C20+365 -> 46474 | D21: =FORECAST(B21,$D$9:$D$18,$B$9:$B$18) -> 201360.53 | E21: =D21/D20-1 -> 0.061985366 | G21: 13 | H21: =H20+365 -> 46474 | I21: =FORECAST(G21,I11:I20,G11:G20) -> 62478.44 | J21: =I21/I20-1 -> 0.088231294 | L21: 13 | M21: =M20+365 -> 46474 | N21: =FORECAST(L21,$N$9:$N$18,$L$9:$L$18) -> 16.580821 | O21: =N21/N20-1 -> 0.054844012
B22: 14 | C22: =C21+365 -> 46839 | D22: =FORECAST(B22,$D$9:$D$18,$B$9:$B$18) -> 213113.43 | E22: =D22/D21-1 -> 0.058367439 | G22: 14 | H22: =H21+365 -> 46839 | I22: =FORECAST(G22,I12:I21,G12:G21) -> 67788.611 | J22: =I22/I21-1 -> 0.084992055 | L22: 14 | M22: =M21+365 -> 46839 | N22: =FORECAST(L22,$N$9:$N$18,$L$9:$L$18) -> 17.4429 | O22: =N22/N21-1 -> 0.051992533
B23: 15 | C23: =C22+365 -> 47204 | D23: =FORECAST(B23,$D$9:$D$18,$B$9:$B$18) -> 224866.33 | E23: =D23/D22-1 -> 0.055148559 | G23: 15 | H23: =H22+365 -> 47204 | I23: =FORECAST(G23,I13:I22,G13:G22) -> 72734.225 | J23: =I23/I22-1 -> 0.072956405 | L23: 15 | M23: =M22+365 -> 47204 | N23: =FORECAST(L23,$N$9:$N$18,$L$9:$L$18) -> 18.304979 | O23: =N23/N22-1 -> 0.04942291
C47: 2023A | D47: 176207.18 | H47: 2023A | I47: 47595.95 | M47: 2023A | N47: 15.01584
C48: 2024A | D48: 178500.88 | H48: 2024A | I48: 51455.69 | M48: 2024A | N48: 16.647261
C49: 2025E | D49: 177854.73 | H49: 2025E | I49: 52359.045 | M49: 2025E | N49: 14.856664
C50: 2026E | D50: 189607.63 | H50: 2026E | I50: 57412.832 | M50: 2026E | N50: 15.718742
C51: 2027E | D51: 201360.53 | H51: 2027E | I51: 62478.44 | M51: 2027E | N51: 16.580821

Sheet Beta - Regression
B3: ="Regression Analysis" & "- " & 'Data Sheet'!B1 -> Regression Analysis- NTPC LTD
B7: Regression Beta - 2 Years Weekly
B9: ='Data Sheet'!B1 & " " & "Weekly returns" -> NTPC LTD Weekly returns | F9: NIFTY Returns | I9: Beta Drifting | N9: Beta 1 | O9: =SLOPE(D13:D120,G13:G120) -> 1.209762
N10: Beta 2 | O10: =COVAR(D12:D120,G12:G120)/VAR(G12:G120) -> 1.1982405
B11: Date | C11: Closing Price | D11: Return | F11: Closing Price | G11: Return | I11: Levererd Raw Beta | K11: =O12 -> 3.2082359
B12: ='<Regression Data>'!B7 -> 45691 | C12: ='<Regression Data>'!C7 -> 316.95001 | D12: - | F12: ='<Regression Data>'!F7 -> 23559.949 | G12: - | I12: Raw Beta Weight | K12: 0.75 | N12: Beta 3 | O12: =O34 -> 3.2082359
B13: ='<Regression Data>'!B8 -> 45684 | C13: ='<Regression Data>'!C8 -> 315.24103 | D13: =C13/C12-1 -> -0.0053919682 | F13: ='<Regression Data>'!F8 -> 23508.4 | G13: =F13/F12-1 -> -0.0021879855
B14: ='<Regression Data>'!B9 -> 45677 | C14: ='<Regression Data>'!C9 -> 321.14496 | D14: =C14/C13-1 -> 0.018728307 | F14: ='<Regression Data>'!F9 -> 23092.199 | G14: =F14/F13-1 -> -0.01770436 | I14: Market Beta | K14: 1
B15: ='<Regression Data>'!B10 -> 45670 | C15: ='<Regression Data>'!C10 -> 323.62561 | D15: =C15/C14-1 -> 0.0077243992 | F15: ='<Regression Data>'!F10 -> 23203.199 | G15: =F15/F14-1 -> 0.004806818 | I15: Market Beta Weight | K15: 0.25
B16: ='<Regression Data>'!B11 -> 45663 | C16: ='<Regression Data>'!C11 -> 305.86417 | D16: =C16/C15-1 -> -0.05488269 | F16: ='<Regression Data>'!F11 -> 23431.5 | G16: =F16/F15-1 -> 0.0098391941
B17: ='<Regression Data>'!B12 -> 45656 | C17: ='<Regression Data>'!C12 -> 337.21957 | D17: =C17/C16-1 -> 0.10251416 | F17: ='<Regression Data>'!F12 -> 24004.75 | G17: =F17/F16-1 -> 0.02446493 | I17: Adjusted Beta | K17: =(K11*K12)+(K14*K15) -> 2.6561769 | N17: SUMMARY OUTPUT
B18: ='<Regression Data>'!B13 -> 45649 | C18: ='<Regression Data>'!C13 -> 332.4071 | D18: =C18/C17-1 -> -0.014271027 | F18: ='<Regression Data>'!F13 -> 23813.4 | G18: =F18/F17-1 -> -0.0079713227
B19: ='<Regression Data>'!B14 -> 45642 | C19: ='<Regression Data>'!C14 -> 330.67065 | D19: =C19/C18-1 -> -0.0052238661 | F19: ='<Regression Data>'!F14 -> 23587.5 | G19: =F19/F18-1 -> -0.0094862719 | N19: Regression Statistics
B20: ='<Regression Data>'!B15 -> 45635 | C20: ='<Regression Data>'!C15 -> 354.38568 | D20: =C20/C19-1 -> 0.071717966 | F20: ='<Regression Data>'!F15 -> 24768.301 | G20: =F20/F19-1 -> 0.050060446 | N20: Multiple R | O20: 0.024153784
B21: ='<Regression Data>'!B16 -> 45628 | C21: ='<Regression Data>'!C16 -> 366.64008 | D21: =C21/C20-1 -> 0.03457926 | F21: ='<Regression Data>'!F16 -> 24677.801 | G21: =F21/F20-1 -> -0.0036538639 | N21: R Square | O21: 0.00058340528
B22: ='<Regression Data>'!B17 -> 45621 | C22: ='<Regression Data>'!C17 -> 360.83536 | D22: =C22/C21-1 -> -0.015832197 | F22: ='<Regression Data>'!F17 -> 24131.1 | G22: =F22/F21-1 -> -0.022153561 | N22: Adjusted R Square | O22: -0.0091196685
B23: ='<Regression Data>'!B18 -> 45614 | C23: ='<Regression Data>'!C18 -> 362.62143 | D23: =C23/C22-1 -> 0.0049498247 | F23: ='<Regression Data>'!F18 -> 23907.25 | G23: =F23/F22-1 -> -0.0092763949 | N23: Standard Error | O23: 2.0813229
B24: ='<Regression Data>'!B19 -> 45607 | C24: ='<Regression Data>'!C19 -> 369.61685 | D24: =C24/C23-1 -> 0.019291255 | F24: ='<Regression Data>'!F19 -> 23532.699 | G24: =F24/F23-1 -> -0.015666828 | N24: Observations | O24: 105
B25: ='<Regression Data>'!B20 -> 45600 | C25: ='<Regression Data>'!C20 -> 394.5722 | D25: =C25/C24-1 -> 0.067516815 | F25: ='<Regression Data>'!F20 -> 24148.199 | G25: =F25/F24-1 -> 0.026155096
B26: ='<Regression Data>'!B21 -> 45593 | C26: ='<Regression Data>'!C21 -> 405.66821 | D26: =C26/C25-1 -> 0.028121617 | F26: ='<Regression Data>'!F21 -> 24304.35 | G26: =F26/F25-1 -> 0.0064663369 | N26: ANOVA
B27: ='<Regression Data>'!B22 -> 45586 | C27: ='<Regression Data>'!C22 -> 393.39017 | D27: =C27/C26-1 -> -0.030266226 | F27: ='<Regression Data>'!F22 -> 24180.801 | G27: =F27/F26-1 -> -0.005083404 | O27: df | P27: SS | Q27: MS | R27: F | S27: Significance F
B28: ='<Regression Data>'!B23 -> 45579 | C28: ='<Regression Data>'!C23 -> 419.08035 | D28: =C28/C27-1 -> 0.065304595 | F28: ='<Regression Data>'!F23 -> 24854.051 | G28: =F28/F27-1 -> 0.027842337 | N28: Regression | O28: 1 | P28: 0.26045935 | Q28: 0.26045935 | R28: 0.060125821 | S28: 0.80678507
B29: ='<Regression Data>'!B24 -> 45572 | C29: ='<Regression Data>'!C24 -> 416.66418 | D29: =C29/C28-1 -> -0.0057654056 | F29: ='<Regression Data>'!F24 -> 24964.25 | G29: =F29/F28-1 -> 0.0044338534 | N29: Residual | O29: 103 | P29: 446.18622 | Q29: 4.331905
B30: ='<Regression Data>'!B25 -> 45565 | C30: ='<Regression Data>'!C25 -> 424.50439 | D30: =C30/C29-1 -> 0.018816616 | F30: ='<Regression Data>'!F25 -> 25014.6 | G30: =F30/F29-1 -> 0.0020168685 | N30: Total | O30: 104 | P30: 446.44668
B31: ='<Regression Data>'!B26 -> 45558 | C31: ='<Regression Data>'!C26 -> 430.86526 | D31: =C31/C30-1 -> 0.014984227 | F31: ='<Regression Data>'!F26 -> 26178.949 | G31: =F31/F30-1 -> 0.046546802
B32: ='<Regression Data>'!B27 -> 45551 | C32: ='<Regression Data>'!C27 -> 418.09418 | D32: =C32/C31-1 -> -0.02964056 | F32: ='<Regression Data>'!F27 -> 25790.949 | G32: =F32/F31-1 -> -0.014821069 | O32: Coefficients | P32: Standard Error | Q32: t Stat | R32: P-value | S32: Lower 95% | T32: Upper 95% | U32: Lower 95.0% | V32: Upper 95.0%
B33: ='<Regression Data>'!B28 -> 45544 | C33: ='<Regression Data>'!C28 -> 395.85565 | D33: =C33/C32-1 -> -0.05319023 | F33: ='<Regression Data>'!F28 -> 25356.5 | G33: =F33/F32-1 -> -0.016845026 | N33: Intercept | O33: 0.2040587 | P33: 0.20577027 | Q33: 0.99168215 | R33: 0.32367658 | S33: -0.20403809 | T33: 0.61215549 | U33: -0.20403809 | V33: 0.61215549
B34: ='<Regression Data>'!B29 -> 45537 | C34: ='<Regression Data>'!C29 -> 389.34677 | D34: =C34/C33-1 -> -0.016442561 | F34: ='<Regression Data>'!F29 -> 24852.15 | G34: =F34/F33-1 -> -0.019890348 | N34: X Variable 1 | O34: 3.2082359 | P34: 13.083857 | Q34: 0.24520567 | R34: 0.80678507 | S34: -22.740508 | T34: 29.15698 | U34: -22.740508 | V34: 29.15698
B35: ='<Regression Data>'!B30 -> 45530 | C35: ='<Regression Data>'!C30 -> 410.45123 | D35: =C35/C34-1 -> 0.054204794 | F35: ='<Regression Data>'!F30 -> 25235.9 | G35: =F35/F34-1 -> 0.01544132
B36: ='<Regression Data>'!B31 -> 45523 | C36: ='<Regression Data>'!C31 -> 396.39804 | D36: =C36/C35-1 -> -0.034238397 | F36: ='<Regression Data>'!F31 -> 24823.15 | G36: =F36/F35-1 -> -0.016355668
B37: ='<Regression Data>'!B32 -> 45516 | C37: ='<Regression Data>'!C32 -> 392.55188 | D37: =C37/C36-1 -> -0.0097027747 | F37: ='<Regression Data>'!F32 -> 24541.15 | G37: =F37/F36-1 -> -0.011360363
B38: ='<Regression Data>'!B33 -> 45509 | C38: ='<Regression Data>'!C33 -> 401.80637 | D38: =C38/C37-1 -> 0.023575192 | F38: ='<Regression Data>'!F33 -> 24367.5 | G38: =F38/F37-1 -> -0.0070758863
B39: ='<Regression Data>'!B34 -> 45502 | C39: ='<Regression Data>'!C34 -> 410.66147 | D39: =C39/C38-1 -> 0.022038234 | F39: ='<Regression Data>'!F34 -> 24717.699 | G39: =F39/F38-1 -> 0.014371569
B40: ='<Regression Data>'!B35 -> 45495 | C40: ='<Regression Data>'!C35 -> 387.76541 | D40: =C40/C39-1 -> -0.055754092 | F40: ='<Regression Data>'!F35 -> 24834.85 | G40: =F40/F39-1 -> 0.0047395346
B41: ='<Regression Data>'!B36 -> 45488 | C41: ='<Regression Data>'!C36 -> 356.797 | D41: =C41/C40-1 -> -0.079863787 | F41: ='<Regression Data>'!F36 -> 24530.9 | G41: =F41/F40-1 -> -0.012238819
B42: ='<Regression Data>'!B37 -> 45481 | C42: ='<Regression Data>'!C37 -> 369.0278 | D42: =C42/C41-1 -> 0.034279449 | F42: ='<Regression Data>'!F37 -> 24502.15 | G42: =F42/F41-1 -> -0.0011719912
B43: ='<Regression Data>'!B38 -> 45474 | C43: ='<Regression Data>'!C38 -> 371.62073 | D43: =C43/C42-1 -> 0.0070263704 | F43: ='<Regression Data>'!F38 -> 24323.85 | G43: =F43/F42-1 -> -0.0072769442
B44: ='<Regression Data>'!B39 -> 45467 | C44: ='<Regression Data>'!C39 -> 370.20197 | D44: =C44/C43-1 -> -0.0038177693 | F44: ='<Regression Data>'!F39 -> 24010.6 | G44: =F44/F43-1 -> -0.012878307
B45: ='<Regression Data>'!B40 -> 45460 | C45: ='<Regression Data>'!C40 -> 352.05142 | D45: =C45/C44-1 -> -0.04902876 | F45: ='<Regression Data>'!F40 -> 23501.1 | G45: =F45/F44-1 -> -0.021219795
B46: ='<Regression Data>'!B41 -> 45453 | C46: ='<Regression Data>'!C41 -> 360.51517 | D46: =C46/C45-1 -> 0.024041218 | F46: ='<Regression Data>'!F41 -> 23465.6 | G46: =F46/F45-1 -> -0.0015105676
... B61: ='<Regression Data>'!B56 -> 45348 | C61: ='<Regression Data>'!C56 -> 336.10248 | D61: =C61/C60-1 -> -0.02470186 | F61: ='<Regression Data>'!F56 -> 22338.75 | G61: =F61/F60-1 -> -0.0068820073
B65: ='<Regression Data>'!B57 -> 45341 | C65: ='<Regression Data>'!C57 -> 330.47632 | D65: =C65/C61-1 -> -0.016739417 | F65: ='<Regression Data>'!F57 -> 22212.699 | G65: =F65/F61-1 -> -0.0056426963
B66: ='<Regression Data>'!B58 -> 45334 | C66: ='<Regression Data>'!C58 -> 330.47632 | D66: =C66/C65-1 -> 0 | F66: ='<Regression Data>'!F58 -> 22040.699 | G66: =F66/F65-1 -> -0.0077433183
B67: ='<Regression Data>'!B59 -> 45327 | C67: ='<Regression Data>'!C59 -> 314.82898 | D67: =C67/C66-1 -> -0.047347837 | F67: ='<Regression Data>'!F59 -> 21782.5 | G67: =F67/F66-1 -> -0.011714656
B68: ='<Regression Data>'!B60 -> 45320 | C68: ='<Regression Data>'!C60 -> 322.19345 | D68: =C68/C67-1 -> 0.023391974 | F68: ='<Regression Data>'!F60 -> 21853.801 | G68: =F68/F67-1 -> 0.0032733057
B69: ='<Regression Data>'!B61 -> 45313 | C69: ='<Regression Data>'!C61 -> 304.99362 | D69: =C69/C68-1 -> -0.053383547 | F69: ='<Regression Data>'!F61 -> 21352.6 | G69: =F69/F68-1 -> -0.022934279
B70: ='<Regression Data>'!B62 -> 45306 | C70: ='<Regression Data>'!C62 -> 298.88895 | D70: =C70/C69-1 -> -0.020015747 | F70: ='<Regression Data>'!F62 -> 21622.4 | G70: =F70/F69-1 -> 0.0126355
B71: ='<Regression Data>'!B63 -> 45299 | C71: ='<Regression Data>'!C63 -> 302.95871 | D71: =C71/C70-1 -> 0.013616305 | F71: ='<Regression Data>'!F63 -> 21894.551 | G71: =F71/F70-1 -> 0.012586502
B72: ='<Regression Data>'!B64 -> 45292 | C72: ='<Regression Data>'!C64 -> 305.18744 | D72: =C72/C71-1 -> 0.0073565446 | F72: ='<Regression Data>'!F64 -> 21710.801 | G72: =F72/F71-1 -> -0.0083924992
B73: ='<Regression Data>'!B65 -> 45285 | C73: ='<Regression Data>'!C65 -> 301.50525 | D73: =C73/C72-1 -> -0.012065339 | F73: ='<Regression Data>'!F65 -> 21731.4 | G73: =F73/F72-1 -> 0.0009488185
B74: ='<Regression Data>'!B66 -> 45278 | C74: ='<Regression Data>'!C66 -> 293.41403 | D74: =C74/C73-1 -> -0.026836074 | F74: ='<Regression Data>'!F66 -> 21349.4 | G74: =F74/F73-1 -> -0.017578251
B75: ='<Regression Data>'!B67 -> 45271 | C75: ='<Regression Data>'!C67 -> 295.64276 | D75: =C75/C74-1 -> 0.0075958509 | F75: ='<Regression Data>'!F67 -> 21456.65 | G75: =F75/F74-1 -> 0.0050235603
B76: ='<Regression Data>'!B68 -> 45264 | C76: ='<Regression Data>'!C68 -> 276.2142 | D76: =C76/C75-1 -> -0.065716334 | F76: ='<Regression Data>'!F68 -> 20969.4 | G76: =F76/F75-1 -> -0.022708577
B77: ='<Regression Data>'!B69 -> 45257 | C77: ='<Regression Data>'!C69 -> 260.61334 | D77: =C77/C76-1 -> -0.056481022 | F77: ='<Regression Data>'!F69 -> 20267.9 | G77: =F77/F76-1 -> -0.033453508
... B120: ='<Regression Data>'!B112 -> 44956 | C120: ='<Regression Data>'!C112 -> 152.7 | D120: =C120/C119-1 -> -0.022225861 | F120: ='<Regression Data>'!F112 -> 17854.05 | G120: =F120/F119-1 -> -0.00013720494

Sheet Intrinic Growth
B3: ="Intrinsic Growth" & "- " & 'Data Sheet'!B1 -> Intrinsic Growth- NTPC LTD
B7: Calculation of ROIC | G7: ='Raw FS'!J$2 -> 43891 | H7: ='Raw FS'!K$2 -> 44256 | I7: ='Raw FS'!L$2 -> 44621 | J7: ='Raw FS'!M$2 -> 44986 | K7: ='Raw FS'!N$2 -> 45352
B9: Current Assets
B10: ='Raw FS'!B36 -> Other Assets | G10: ='Raw FS'!J36 -> 81951 | H10: ='Raw FS'!K36 -> 86681 | I10: ='Raw FS'!L36 -> 89156 | J10: ='Raw FS'!M36 -> 103651 | K10: ='Raw FS'!N36 -> 116795
B11: ='Raw FS'!B37 -> Inventories | G11: ='Raw FS'!J37 -> 11319 | H11: ='Raw FS'!K37 -> 10020 | I11: ='Raw FS'!L37 -> 10370 | J11: ='Raw FS'!M37 -> 14454 | K11: ='Raw FS'!N37 -> 18270
B12: ='Raw FS'!B42 -> Cash Equivalents | G12: ='Raw FS'!J42 -> 3214 | H12: ='Raw FS'!K42 -> 4388 | I12: ='Raw FS'!L42 -> 4458 | J12: ='Raw FS'!M42 -> 4949 | K12: ='Raw FS'!N42 -> 6847
B13: ='Raw FS'!B43 -> Loans n Advances | G13: ='Raw FS'!J43 -> 2095 | H13: ='Raw FS'!K43 -> 3652 | I13: ='Raw FS'!L43 -> 3566 | J13: ='Raw FS'!M43 -> 5227 | K13: ='Raw FS'!N43 -> 4861
B14: Total Currrent Assets | G14: =SUM(G10:G13) -> 98579 | H14: =SUM(H10:H13) -> 104741 | I14: =SUM(I10:I13) -> 107550 | J14: =SUM(J10:J13) -> 128281 | K14: =SUM(K10:K13) -> 146773
B16: Current Liabilities
B17: ='Raw FS'!B13 -> Trade Payables | G17: ='Raw FS'!J13 -> 10109 | H17: ='Raw FS'!K13 -> 8726 | I17: ='Raw FS'!L13 -> 11277 | J17: ='Raw FS'!M13 -> 11356 | K17: ='Raw FS'!N13 -> 11338
B18: ='Raw FS'!B14 -> Advance from Customers | G18: ='Raw FS'!J14 -> 781 | H18: ='Raw FS'!K14 -> 864 | I18: ='Raw FS'!L14 -> 758 | J18: ='Raw FS'!M14 -> 625 | K18: ='Raw FS'!N14 -> 686
B19: ='Raw FS'!B15 -> Other liability items | G19: ='Raw FS'!J15 -> 41539 | H19: ='Raw FS'!K15 -> 48962 | I19: ='Raw FS'!L15 -> 53956 | J19: ='Raw FS'!M15 -> 61341 | K19: ='Raw FS'!N15 -> 65000
B20: Total Currrent Liabilities | G20: =SUM(G17:G19) -> 52429 | H20: =SUM(H17:H19) -> 58552 | I20: =SUM(I17:I19) -> 65991 | J20: =SUM(J17:J19) -> 73322 | K20: =SUM(K17:K19) -> 77024
A22: # | B22: Net Working Capital | G22: =G14-G20 -> 46150 | H22: =H14-H20 -> 46189 | I22: =I14-I20 -> 41559 | J22: =J14-J20 -> 54959 | K22: =K14-K20 -> 69749
B24: Non Current Assets
B25: ='Raw FS'!B19 -> Land | G25: ='Raw FS'!J19 -> 8760 | H25: ='Raw FS'!K19 -> 9009 | I25: ='Raw FS'!L19 -> 13280 | J25: ='Raw FS'!M19 -> 20214 | K25: ='Raw FS'!N19 -> 22550
B26: ='Raw FS'!B20 -> Building | G26: ='Raw FS'!J20 -> 16871 | H26: ='Raw FS'!K20 -> 19597 | I26: ='Raw FS'!L20 -> 21573 | J26: ='Raw FS'!M20 -> 23175 | K26: ='Raw FS'!N20 -> 24835
B27: ='Raw FS'!B21 -> Plant Machinery | G27: ='Raw FS'!J21 -> 178428 | H27: ='Raw FS'!K21 -> 208674 | I27: ='Raw FS'!L21 -> 239535 | J27: ='Raw FS'!M21 -> 263953 | K27: ='Raw FS'!N21 -> 282147
B28: ='Raw FS'!B22 -> Equipments | G28: ='Raw FS'!J22 -> 1047 | H28: ='Raw FS'!K22 -> 1187 | I28: ='Raw FS'!L22 -> 1275 | J28: ='Raw FS'!M22 -> 1442 | K28: ='Raw FS'!N22 -> 1585
B29: ='Raw FS'!B24 -> Furniture n fittings | G29: ='Raw FS'!J24 -> 2617 | H29: ='Raw FS'!K24 -> 3103 | I29: ='Raw FS'!L24 -> 3375 | J29: ='Raw FS'!M24 -> 3735 | K29: ='Raw FS'!N24 -> 4276
B30: ='Raw FS'!B25 -> Railway sidings | G30: ='Raw FS'!J25 -> 3255 | H30: ='Raw FS'!K25 -> 3359 | I30: ='Raw FS'!L25 -> 3689 | J30: ='Raw FS'!M25 -> 9713 | K30: ='Raw FS'!N25 -> 10448
B31: ='Raw FS'!B26 -> Vehicles | G31: ='Raw FS'!J26 -> 90 | H31: ='Raw FS'!K26 -> 143 | I31: ='Raw FS'!L26 -> 236 | J31: ='Raw FS'!M26 -> 270 | K31: ='Raw FS'!N26 -> 230
B32: ='Raw FS'!B27 -> Intangible Assets | G32: ='Raw FS'!J27 -> 385 | H32: ='Raw FS'!K27 -> 420 | I32: ='Raw FS'!L27 -> 0 | J32: ='Raw FS'!M27 -> 0 | K32: ='Raw FS'!N27 -> 0
B34: Gross Block | G34: =SUM(G25:G32) -> 211453 | H34: =SUM(H25:H32) -> 245492 | I34: =SUM(I25:I32) -> 282963 | J34: =SUM(J25:J32) -> 322502 | K34: =SUM(K25:K32) -> 346071
B35: ='Raw FS'!B29 -> Gross Block | G35: =-'Raw FS'!J29 -> -236879 | H35: =-'Raw FS'!K29 -> -273547 | I35: =-'Raw FS'!L29 -> -308960 | J35: =-'Raw FS'!M29 -> -339283 | K35: =-'Raw FS'!N29 -> -374546
A36: # | B36: Net Non Current Assets | G36: =SUM(G34:G35) -> -25426 | H36: =SUM(H34:H35) -> -28055 | I36: =SUM(I34:I35) -> -25997 | J36: =SUM(J34:J35) -> -16781 | K36: =SUM(K34:K35) -> -28475
A38: # | B38: Invested Capital | G38: =G36+G22 -> 20724 | H38: =H36+H22 -> 18134 | I38: =I36+I22 -> 15562 | J38: =J36+J22 -> 38178 | K38: =K36+K22 -> 41274
B39: EBIT | G39: =HistoricalFS!H31+HistoricalFS!H25 -> 21229.57 | H39: =HistoricalFS!I31+HistoricalFS!I25 -> 21593.41 | I39: =HistoricalFS!J31+HistoricalFS!J25 -> 26574.09 | J39: =HistoricalFS!K31+HistoricalFS!K25 -> 32803.68 | K39: =HistoricalFS!L31+HistoricalFS!L25 -> 35252.06
B41: ROIC | G41: =G39/G38 -> 1.0243954 | H41: =H39/H38 -> 1.1907693 | I41: =I39/I38 -> 1.7076269 | J41: =J39/J38 -> 0.85922992 | K41: =K39/K38 -> 0.85409846
B44: Calculation of Reinvestment Rate | G44: ='Raw FS'!J$2 -> 43891 | H44: ='Raw FS'!K$2 -> 44256 | I44: ='Raw FS'!L$2 -> 44621 | J44: ='Raw FS'!M$2 -> 44986 | K44: ='Raw FS'!N$2 -> 45352
B46: Net Apex | G46: =-SUM('Raw FS'!J61:J62) -> 47858 | H46: =-SUM('Raw FS'!K61:K62) -> 44346 | I46: =-SUM('Raw FS'!L61:L62) -> 47335 | J46: =-SUM('Raw FS'!M61:M62) -> 50964 | K46: =-SUM('Raw FS'!N61:N62) -> 62957
B47: Change in Working Capital | H47: =H22-G22 -> 39 | I47: =I22-H22 -> -4630 | J47: =J22-I22 -> 13400 | K47: =K22-J22 -> 14790
B49: EBIT | G49: =G39 -> 21229.57 | H49: =H39 -> 21593.41 | I49: =I39 -> 26574.09 | J49: =J39 -> 32803.68 | K49: =K39 -> 35252.06
B50: Marginal Tax Rate | G50: 0.25 | H50: 0.25 | I50: 0.25 | J50: 0.25 | K50: 0.25
B51: EBIT(1-T) | G51: =G49*(1-G50) -> 15922.177 | H51: =H49*(1-H50) -> 16195.057 | I51: =I49*(1-I50) -> 19930.567 | J51: =J49*(1-J50) -> 24602.76 | K51: =K49*(1-K50) -> 26439.045
B53: Reinvestment | H53: =SUM(H46:H47) -> 44385 | I53: =SUM(I46:I47) -> 42705 | J53: =SUM(J46:J47) -> 64364 | K53: =SUM(K46:K47) -> 77747
B55: Reinvestment Rate | H55: =H53/H51 -> 2.740651 | I55: =I53/I51 -> 2.1426886 | J55: =J53/J51 -> 2.6161292 | K55: =K53/K51 -> 2.940613
J57: 4 Year Average | K57: =AVERAGE(H55:K55) -> 2.6100205
J58: 4 Year Median | K58: =MEDIAN(H55:K55) -> 2.6783901
B60: Calculation of Growh Rate | G60: ='Raw FS'!J$2 -> 43891 | H60: ='Raw FS'!K$2 -> 44256 | I60: ='Raw FS'!L$2 -> 44621 | J60: ='Raw FS'!M$2 -> 44986 | K60: ='Raw FS'!N$2 -> 45352
B62: Reinvestment Rate | H62: =H55 -> 2.740651 | I62: =I55 -> 2.1426886 | J62: =J55 -> 2.6161292 | K62: =K55 -> 2.940613
B63: ROIC | H63: =H41 -> 1.1907693 | I63: =I41 -> 1.7076269 | J63: =J41 -> 0.85922992 | K63: =K41 -> 0.85409846
B65: Intrinsic Growth | H65: =H63*H62 -> 3.263483 | I65: =I63*I62 -> 3.6589127 | J65: =J63*J62 -> 2.2478565 | K65: =K63*K62 -> 2.5115731
J67: 4 Year Average | K67: =AVERAGE(H65:K65) -> 2.9204563
J68: 4 Year Median | K68: =MEDIAN(H65:K65) -> 2.887528

Sheet WACC
B5: =B9 -> Weighted Average Cost of Capital - NTPC LTD
B9: ="Weighted Average Cost of Capital" & " - " & 'Data Sheet'!B1 -> Weighted Average Cost of Capital - NTPC LTD
B11: All figures are in INR unless stated otherwise
B13: Peer Comps
H14: Debt/ | I14: Debt/ | J14: Levered | K14: Unlevered
B15: Name | D15: Country | E15: Total Debt | F15: Total Equity | G15: Tax Rate 1 | H15: Equity | I15: Capital | J15: Beta 2 | K15: Beta 3
B17: ='Beta - Comps'!C3 -> NTPC | D17: India | E17: ='Beta - Comps'!F3 -> 242009.49 | F17: ='Beta - Comps'!E3 -> 307238.9 | G17: 0.3 | H17: ='Beta - Comps'!G3 -> 1.44 | I17: =E17/(F17+E17) -> 0.44061939 | J17: ='Beta - Regression'!O10 -> 1.1982405 | K17: =J17/(1+(1-G17)*H17) -> 0.59673332
B18: ='Beta - Comps'!C4 -> Power Grid Corpn | D18: India | E18: ='Beta - Comps'!F4 -> 122567.5 | F18: ='Beta - Comps'!E4 -> 259021.9 | G18: 0.3 | H18: ='Beta - Comps'!G4 -> 1.33 | I18: =E18/(F18+E18) -> 0.32120258 | J18: 0.971 | K18: =J18/(1+(1-G18)*H18) -> 0.50284827
B19: ='Beta - Comps'!C5 -> Adani Power | D19: India | E19: ='Beta - Comps'!F5 -> 37704.97 | F19: ='Beta - Comps'!E5 -> 190725.8 | G19: 0.3 | H19: ='Beta - Comps'!G5 -> 0.67 | I19: =E19/(F19+E19) -> 0.16506082 | J19: 1.43 | K19: =J19/(1+(1-G19)*H19) -> 0.97345133
B20: ='Beta - Comps'!C6 -> Adani Green | D20: India | E20: ='Beta - Comps'!F6 -> 67430 | F20: ='Beta - Comps'!E6 -> 156819.22 | G20: 0.3 | H20: ='Beta - Comps'!G6 -> 6.38 | I20: =E20/(F20+E20) -> 0.30069224 | J20: 1.93 | K20: =J20/(1+(1-G20)*H20) -> 0.35309184
B21: ='Beta - Comps'!C7 -> Tata Power Co. | D21: India | E21: ='Beta - Comps'!F7 -> 58313.94 | F21: ='Beta - Comps'!E7 -> 117380.68 | G21: 0.3 | H21: ='Beta - Comps'!G7 -> 1.73 | I21: =E21/(F21+E21) -> 0.3319051 | J21: 1.6 | K21: =J21/(1+(1-G21)*H21) -> 0.72365445
F23: Average | G23: =AVERAGE(G17:G21) -> 0.3 | H23: =AVERAGE(H17:H21) -> 2.31 | I23: =AVERAGE(I17:I21) -> 0.31189602 | J23: =AVERAGE(J17:J21) -> 1.4258481 | K23: =AVERAGE(K17:K21) -> 0.62995584
F24: Median | G24: =MEDIAN(G17:G21) -> 0.3 | H24: =MEDIAN(H17:H21) -> 1.44 | I24: =MEDIAN(I17:I21) -> 0.32120258 | J24: =MEDIAN(J17:J21) -> 1.43 | K24: =MEDIAN(K17:K21) -> 0.59673332
B27: Cost of Debt | G27: Cost of Equity
B29: Pre-Tax Cost of Debt | E29: =8189/242009.49 -> 0.033837516 | G29: Risk Free Rate | K29: 0.06748
B30: Tax Rate | E30: 0.3 | G30: Equity Risk Premium | K30: ='Return on Markets'!G10-WACC!K29 -> 0.085868
B31: Post Tax Cost of Debt | E31: =E29*(1-E30) -> 0.023686261 | G31: Levered Beta 4 | K31: =K41 -> 0.78606971
G32: Cost of Equity | K32: =K29+(K30*K31) -> 0.13497823
B36: Capital Structure | G36: Levered Beta
D38: Current | E38: Target | G38: Comps Median Unlevered Data | K38: =K24 -> 0.59673332
B39: Total Debt | C39: =E17 -> 242009.49 | D39: =C39/$C$41 -> 0.44061939 | E39: =I23 -> 0.31189602 | G39: Target Debt / Equity | K39: =E43 -> 0.45326874
B40: Market Capitalization | C40: =F17 -> 307238.9 | D40: =C40/$C$41 -> 0.55938061 | E40: =E41-E39 -> 0.68810398 | G40: Tax Rate | K40: =E30 -> 0.3
B41: Total Capital | C41: =SUM(C39:C40) -> 549248.39 | D41: =C41/$C$41 -> 1 | E41: =D41 -> 1 | G41: Levered Beta | K41: =K38*(1+(1-K40)*K39) -> 0.78606971
B43: Debt / Equity | D43: =D39/D40 -> 0.78769157 | E43: =E39/E40 -> 0.45326874 | G43: Weighted Average Cost of Capital
G45: Cost of Debt | K45: =E31 -> 0.023686261
B46: Notes: | G46: Debt Weight | K46: =E39 -> 0.31189602
B47: 1. Tax rate considered as Marginal Tax rate for the Country
B48: 2. Levered beta is based on 5 year monthly data | G48: Cost of Equity | K48: =K32 -> 0.13497823
B49: 3. Unlevered Beta = Levered Beta/(1+(1-Tax Rate)*Debt/Equity) | G49: Equity Weight | K49: =E40 -> 0.68810398
B50: 4. Levered Beta = Unlevered Beta/(1+(1-Tax Rate)*Debt/Equity)
B51: 5. Pre Tax Cost = Interest/Total Debt | G51: WACC | K51: =(K45*K46)+(K48*K49) -> 0.10026671
B58: Source:
B59: Leverd Beta - | C59: https://www.topstockresearch.com/rt/Stock/ADANIPOWER/BetaAndVolatility
B60: Pre Tax Cost of Debt | C60: Interest/Debt | D60: Screener
B61: Risk Free Rate Source - | C61: https://in.investing.com/
C62: investing.com bonds

Sheet DCF>

Sheet DCF
B4: ="Discount Cash Flow" & "- " & 'Data Sheet'!B1 -> Discount Cash Flow- NTPC LTD
B7: DCF Valuation
B9: Calculation of PV of FCFF | E9: ='Intrinic Growth'!K7 -> 45352 | F9: =E9+365 -> 45717 | G9: =F9+365 -> 46082 | H9: =G9+365 -> 46447 | I9: =H9+366 -> 46813 | J9: =I9+365 -> 47178
B11: EBIT | E11: ='Data Sheet'!B35 -> 14119.16 | F11: =E11*(1+$E$22) -> 14878.771 | G11: =F11*(1+$E$22) -> 15679.249 | H11: =G11*(1+$E$22) -> 16522.792 | I11: =H11*(1+$E$22) -> 17411.718 | J11: =I11*(1+$E$22) -> 18348.469
B12: Tax Rate | E12: 0.25 | F12: =E12 -> 0.25 | G12: =F12 -> 0.25 | H12: =G12 -> 0.25 | I12: =H12 -> 0.25 | J12: =I12 -> 0.25
B13: EBIT(1-T) | E13: =E11*(1-E12) -> 10589.37 | F13: =F11*(1-F12) -> 11159.078 | G13: =G11*(1-G12) -> 11759.437 | H13: =H11*(1-H12) -> 12392.094 | I13: =I11*(1-I12) -> 13058.789 | J13: =J11*(1-J12) -> 13761.352
B14: Less: Reinvestment Rate | E14: ='Intrinic Growth'!K58 -> 2.6783901 | F14: =E14+(($J$14-$E$14)/4) -> 2.1439676 | G14: =F14+(($J$14-$E$14)/4) -> 1.6095451 | H14: =G14+(($J$14-$E$14)/4) -> 1.0751225 | I14: =H14+(($J$14-$E$14)/5) -> 0.64758451 | J14: 0.5407
B15: Free Cash Flow to Firm (FCFF) | E15: =E13-(1-E14) -> 10591.048 | F15: =F13-(1-F14) -> 11160.222 | G15: =G13-(1-G14) -> 11760.046 | H15: =H13-(1-H14) -> 12392.169 | I15: =I13-(1-I14) -> 13058.436 | J15: =J13-(1-J14) -> 13760.892
B16: Mid Year Convention | F16: 0.5 | G16: =F16+1 -> 1.5 | H16: =G16+1 -> 2.5 | I16: =H16+1 -> 3.5 | J16: =I16+1 -> 4.5
B17: Disounting factor | F17: =1/(1+$E$23)^F16 -> 0.95334702 | G17: =1/(1+$E$23)^G16 -> 0.86646902 | H17: =1/(1+$E$23)^H16 -> 0.78750817 | I17: =1/(1+$E$23)^I16 -> 0.71574298 | J17: =1/(1+$E$23)^J16 -> 0.6505177
B19: PV of FCFF | F19: =F15*F17 -> 10639.564 | G19: =G15*G17 -> 10189.716 | H19: =H15*H17 -> 9758.9346 | I19: =I15*I17 -> 9346.4841 | J19: =J15*J17 -> 8951.7041
B21: Expected Growth | E21: 0.1316
B22: Terminal Growth | E22: 0.0538
B23: WACC | E23: =WACC!K51 -> 0.10026671
B26: Calculation of Terminal Value | F26: Sensistivity Analysis
F27: =D39 -> 266886.52 | G27: 0.1 | H27: 0.1373 | I27: 0.19 | J27: 0.22
B28: FCFF (n+1) | D28: =J15*(1+E21) -> 15571.826 | F28: 0.03 | G28: 193597.09 | H28: 143292.26 | I28: 112197.33 | J28: 102200.87
B29: WACC | D29: =E23 -> 0.10026671 | F29: 0.04 | G29: 217715.54 | H29: 152994.81 | I29: 116418.06 | J29: 105162.78
B30: Terminal Growth Rate | D30: =E22 -> 0.0538 | F30: 0.0538 | G30: 268145.03 | H30: 170200.76 | I30: 123260.47 | J30: 109835.55
F31: 0.06 | G31: 302130.11 | H31: 179931.01 | I31: 126807.54 | J31: 112197.33
B32: Terminal Value | D32: =D28/(D29-D30) -> 335117.89 | F32: 0.07 | G32: 386544.68 | H32: 199402.72 | I32: 133300.97 | J32: 116418.06
B35: Calculation of Equity Value per Share | F35: Share Price
F36: =D46 -> 39.904291 | G36: 0.1 | H36: 0.1373 | I36: 0.19 | J36: 0.22
B37: FCFF (n+1) | D37: =SUM(F19:J19) -> 48886.403 | F37: 0.03 | G37: -35.67779 | H37: -87.556269 | I37: -119.62392 | J37: -129.93309
B38: Terminal Value | D38: =D32*J17 -> 218000.12 | F38: 0.04 | G38: -10.804864 | H38: -77.550198 | I38: -115.27115 | J38: -126.87852
B39: Value of Operating Assets | D39: =SUM(D37:D38) -> 266886.52 | F39: 0.0538 | G39: 41.202163 | H39: -59.806018 | I39: -108.21469 | J39: -122.05958
F40: 0.06 | G40: 76.250377 | H40: -49.771376 | I40: -104.55666 | J40: -119.62392
B41: Add: Cash | D41: ='Data Sheet'!K70 -> 6847.34 | F41: 0.07 | G41: 163.30562 | H41: -29.690548 | I41: -97.860105 | J41: -115.27115
B42: Less: Debt | D42: =SUM('Raw FS'!N7:N8) -> 235040
B44: Value of Equity | D44: =D39+D41-D42 -> 38693.863
B45: No of Share | D45: ='Data Sheet'!B6 -> 969.66672
B46: Value of Share | D46: =D44/D45 -> 39.904291
B48: Equity Value per Share | D48: =D44/D45 -> 39.904291
B50: Share Price | D50: 316
B51: Discount/Premium | D51: =D50/D48 -> 7.9189479
B57: Source
B58: Terminal Growth Rate | D58: RBI
B59: Share Price | D59: Screener
B60: Debt | D60: Raw FS

Sheet Beta - Comps
B2: S.No. | C2: Name | D2: CMP Rs. | E2: Mar Cap Rs.Cr. | F2: Debt Rs.Cr. | G2: Debt / Eq
B3: 1 | C3: NTPC | D3: 316.85 | E3: 307238.9 | F3: 242009.49 | G3: 1.44
B4: 2 | C4: Power Grid Corpn | D4: 278.5 | E4: 259021.9 | F4: 122567.5 | G4: 1.33
B5: 3 | C5: Adani Power | D5: 494.5 | E5: 190725.8 | F5: 37704.97 | G5: 0.67
B6: 4 | C6: Adani Green | D6: 990 | E6: 156819.22 | F6: 67430 | G6: 6.38
B7: 5 | C7: Tata Power Co. | D7: 367.35 | E7: 117380.68 | F7: 58313.94 | G7: 1.73
B10: Source - | C10: https://www.screener.in/company/compare/00000054/
B12: Risk Free Rate Source - | D12: https://in.investing.com/

Sheet Return on Markets
B2: Return on Markets
B4: Year | C4: Annual
B5: ='Nifty Returns'!B4 -> 2000 | C5: -0.1465
B6: ='Nifty Returns'!B5 -> 2001 | C6: -0.1618
B7: ='Nifty Returns'!B6 -> 2002 | C7: 0.0325
B8: ='Nifty Returns'!B7 -> 2003 | C8: 0.719 | F8: Average Return | G8: =AVERAGE(C5:C29) -> 0.153348
B9: ='Nifty Returns'!B8 -> 2004 | C9: 0.1068 | F9: Dividend Yield | G9: 1.27% 1
B10: ='Nifty Returns'!B9 -> 2005 | C10: 0.3634 | F10: Total Market Return | G10: =SUM(G8:G9) -> 0.153348
B11: ='Nifty Returns'!B10 -> 2006 | C11: 0.3983
B12: ='Nifty Returns'!B11 -> 2007 | C12: 0.5477
B13: ='Nifty Returns'!B12 -> 2008 | C13: -0.5179
B14: ='Nifty Returns'!B13 -> 2009 | C14: 0.7576
B15: ='Nifty Returns'!B14 -> 2010 | C15: 0.1795
B16: ='Nifty Returns'!B15 -> 2011 | C16: -0.2462
B17: ='Nifty Returns'!B16 -> 2012 | C17: 0.277
B18: ='Nifty Returns'!B17 -> 2013 | C18: 0.0676
B19: ='Nifty Returns'!B18 -> 2014 | C19: 0.3139
B20: ='Nifty Returns'!B19 -> 2015 | C20: -0.0406
B21: ='Nifty Returns'!B20 -> 2016 | C21: 0.0301
B22: ='Nifty Returns'!B21 -> 2017 | C22: 0.2865
... B29: ='Nifty Returns'!B28 -> 2024 | C29: 0.0875

Sheet Comps Value
B4: ="Discount Cash Flow" & "- " & 'Data Sheet'!B1 -> Discount Cash Flow- NTPC LTD
B7: Comparable Valuation
B8: Amount in crores
B9: Comparable Company Valuation
D11: Market Data | K11: Financials | O11: Valuation
B12: Company | C12: Ticker | D12: Share Price | E12: Shares Outstanding | F12: Equity Value | G12: Net Debt | H12: Enterprise Value | K12: Revenue | L12: EBITDA | M12: Net Income | O12: EV/Revenue | P12: Ev/EBITDA | Q12: P/E
B14: ='Peers Data'!C3 -> NTPC | C14: NTPC.NS | D14: ='Peers Data'!D3 -> 315.1 | E14: ='Peers Data'!E3 -> 969.67 | F14: =E14*D14 -> 305543.02 | G14: ='Peers Data'!I3 -> 235162.15 | H14: =F14+G14 -> 540705.17 | K14: ='Peers Data'!L3 -> 185891.75 | L14: ='Peers Data'!M3 -> 59485.36 | M14: ='Peers Data'!N3 -> 22546.06 | O14: =$H14/K14 -> 2.9087099 | P14: =$H14/L14 -> 9.0897183 | Q14: =F14/M14 -> 13.551947
B15: ='Peers Data'!C4 -> Power Grid Corpn | C15: POWERGRID.NS | D15: ='Peers Data'!D4 -> 282.15 | E15: ='Peers Data'!E4 -> 930.06 | F15: =E15*D15 -> 262416.43 | G15: ='Peers Data'!I4 -> 115072.38 | H15: =F15+G15 -> 377488.81 | K15: ='Peers Data'!L4 -> 45495.08 | L15: ='Peers Data'!M4 -> 40490.621 | M15: ='Peers Data'!N4 -> 15544.9 | O15: =$H15/K15 -> 8.2973545 | P15: =$H15/L15 -> 9.3228703 | Q15: =F15/M15 -> 16.881191
B16: ='Peers Data'!C5 -> Adani Power | C16: ADANIPOWER.NS | D16: ='Peers Data'!D5 -> 503.65 | E16: ='Peers Data'!E5 -> 385.69 | F16: =E16*D16 -> 194252.77 | G16: ='Peers Data'!I5 -> 30493.21 | H16: =F16+G16 -> 224745.98 | K16: ='Peers Data'!L5 -> 55329.38 | L16: ='Peers Data'!M5 -> 24344.927 | M16: ='Peers Data'!N5 -> 12887.62 | O16: =$H16/K16 -> 4.0619645 | P16: =$H16/L16 -> 9.2317375 | Q16: =F16/M16 -> 15.072819
B17: ='Peers Data'!C6 -> Adani Green | C17: ADANIGREEN.NS | D17: ='Peers Data'!D6 -> 1000.25 | E17: ='Peers Data'!E6 -> 158.4 | F17: =E17*D17 -> 158439.6 | G17: ='Peers Data'!I6 -> 58666 | H17: =F17+G17 -> 217105.6 | K17: ='Peers Data'!L6 -> 10782 | L17: ='Peers Data'!M6 -> 9272.52 | M17: ='Peers Data'!N6 -> 1928 | O17: =$H17/K17 -> 20.13593 | P17: =$H17/L17 -> 23.413872 | Q17: =F17/M17 -> 82.178216
B18: ='Peers Data'!C7 -> Tata Power Co. | C18: TATAPOWERNS | D18: ='Peers Data'!D7 -> 365.95 | E18: ='Peers Data'!E7 -> 319.53 | F18: =E18*D18 -> 116932 | G18: ='Peers Data'!I7 -> 49162.03 | H18: =F18+G18 -> 166094.03 | K18: ='Peers Data'!L7 -> 64228.93 | L18: ='Peers Data'!M7 -> 14772.654 | M18: ='Peers Data'!N7 -> 4514.84 | O18: =$H18/K18 -> 2.5859692 | P18: =$H18/L18 -> 11.243344 | Q18: =F18/M18 -> 25.899479
B19: ='Peers Data'!C8 -> NTPC Green | C19: - | D19: ='Peers Data'!D8 -> 112 | E19: ='Peers Data'!E8 -> 842.63 | F19: =E19*D19 -> 94374.56 | G19: ='Peers Data'!I8 -> 13384.44 | H19: =F19+G19 -> 107759 | K19: ='Peers Data'!L8 -> 1962.6 | L19: ='Peers Data'!M8 -> 1825.218 | M19: ='Peers Data'!N8 -> 344.72 | O19: =$H19/K19 -> 54.906247 | P19: =$H19/L19 -> 59.038975 | Q19: =F19/M19 -> 273.77164
B20: ='Peers Data'!C9 -> Adani Energy Sol | C20: - | D20: ='Peers Data'!D9 -> 775.75 | E20: ='Peers Data'!E9 -> 120.13 | F20: =E20*D20 -> 93190.848 | G20: ='Peers Data'!I9 -> 36780.58 | H20: =F20+G20 -> 129971.43 | K20: ='Peers Data'!L9 -> 22099.36 | L20: ='Peers Data'!M9 -> 7292.7888 | M20: ='Peers Data'!N9 -> 589.32 | O20: =$H20/K20 -> 5.8812304 | P20: =$H20/L20 -> 17.82191 | Q20: =F20/M20 -> 158.13284
B21: ='Peers Data'!C10 -> JSW Energy | C21: JSWENERGY.NS | D21: ='Peers Data'!D10 -> 493.5 | E21: ='Peers Data'!E10 -> 174.78 | F21: =E21*D21 -> 86253.93 | G21: ='Peers Data'!I10 -> 26646.46 | H21: =F21+G21 -> 112900.39 | K21: ='Peers Data'!L10 -> 11311.87 | L21: ='Peers Data'!M10 -> 5882.1724 | M21: ='Peers Data'!N10 -> 1913.64 | O21: =$H21/K21 -> 9.9807008 | P21: =$H21/L21 -> 19.193655 | Q21: =F21/M21 -> 45.073227
B22: ='Peers Data'!C11 -> NHPC Ltd | C22: NHPC.NS | D22: ='Peers Data'!D11 -> 78.5 | E22: ='Peers Data'!E11 -> 1004.5 | F22: =E22*D22 -> 78853.25 | G22: ='Peers Data'!I11 -> 30587.92 | H22: =F22+G22 -> 109441.17 | K22: ='Peers Data'!L11 -> 9689.77 | L22: ='Peers Data'!M11 -> 7073.5321 | M22: ='Peers Data'!N11 -> 3417.11 | O22: =$H22/K22 -> 11.294506 | P22: =$H22/L22 -> 15.471927 | Q22: =F22/M22 -> 23.076006
B23: ='Peers Data'!C12 -> Torrent Power | C23: TORNTOWER.NS | D23: ='Peers Data'!D12 -> 1373.55 | E23: ='Peers Data'!E12 -> 50.39 | F23: =E23*D23 -> 69213.185 | G23: ='Peers Data'!I12 -> 11148.7 | H23: =F23+G23 -> 80361.885 | K23: ='Peers Data'!L12 -> 29237.5 | L23: ='Peers Data'!M12 -> 5847.5 | M23: ='Peers Data'!N12 -> 2428.43 | O23: =$H23/K23 -> 2.7485895 | P23: =$H23/L23 -> 13.742947 | Q23: =F23/M23 -> 28.501206
B26: High | O26: =MAX(O14:O23) -> 54.906247 | P26: =MAX(P14:P23) -> 59.038975 | Q26: =MAX(Q14:Q23) -> 273.77164
B27: 75th Percntile | O27: =QUARTILE(O14:O23,3) -> 10.966055 | P27: =QUARTILE(P14:P23,3) -> 18.850719 | Q27: =QUARTILE(Q14:Q23,3) -> 72.901969
B28: Average | O28: =AVERAGE(O14:O23) -> 12.28012 | P28: =AVERAGE(P14:P23) -> 18.757096 | Q28: =AVERAGE(Q14:Q23) -> 68.213858
B29: Median | O29: =MEDIAN(O14:O23) -> 7.0892925 | P29: =MEDIAN(P14:P23) -> 14.607437 | Q29: =MEDIAN(Q14:Q23) -> 27.200343
B30: 25th percentile | O30: =QUARTILE(O14:O23,1) -> 3.1970235 | P30: =QUARTILE(P14:P23,1) -> 9.8029888 | Q30: =QUARTILE(Q14:Q23,1) -> 18.429895
B31: Low | O31: =MIN(O14:O23) -> 2.5859692 | P31: =MIN(P14:P23) -> 9.0897183 | Q31: =MIN(Q14:Q23) -> 13.551947
B34: Cipla Comparable Company Valuation | O34: EV/Revenue | P34: Ev/EBITDA | Q34: P/E
B36: Implied Enterprise Value | O36: =O$29*K14 -> 1317841 | P36: =P$29*L14 -> 868928.65 | Q36: =Q$29*M14 -> 613260.56
B37: Net Debt | O37: =$G$14 -> 235162.15 | P37: =$G$14 -> 235162.15 | Q37: =$G$14 -> 235162.15
B38: Implied Market Value | O38: =O36-O37 -> 1082678.8 | P38: =P36-P37 -> 633766.5 | Q38: =Q37+Q36 -> 848422.71
B39: Shares Outstanding | O39: =$E$14 -> 969.67 | P39: =$E$14 -> 969.67 | Q39: =$E$14 -> 969.67
B41: Implie Value Per share | O41: =O38/O39 -> 1116.5436 | P41: =P38/P39 -> 653.58988 | Q41: =Q38/Q39 -> 874.96025
B43: Source: The Valuation School, Screener.in | O43: =IF(O41>$D$14,"Under Valued","Overvalued") -> Under Valued | P43: =IF(P41>$D$14,"Under Valued","Overvalued") -> Under Valued | Q43: =IF(Q41>$D$14,"Under Valued","Overvalued") -> Under Valued

Sheet Football Analysis
B4: =B9 & "- " & 'Data Sheet'!B1 -> Football Field Analysis- NTPC LTD
B7: =B9 -> Football Field Analysis
B9: Football Field Analysis
D10: Open Low | E10: Low | F10: Open High | G10: High
B11: Comps | D11: =E11 -> 162.5 | E11: 162.5 | F11: =G11 -> 184.7 | G11: 184.7
B12: DCF Bear | D12: =DCF!$J$37 -> -129.93309 | E12: =D12 -> -129.93309 | F12: =DCF!J41 -> -115.27115 | G12: =F12 -> -115.27115
B13: DCF Base | D13: =E13 -> -87.556269 | E13: =DCF!H37 -> -87.556269 | F13: =DCF!H41 -> -29.690548 | G13: =F13 -> -29.690548
B14: DCF Bull | D14: =DCF!G37 -> -35.67779 | E14: =D14 -> -35.67779 | F14: =DCF!G41 -> 163.30562 | G14: =G13 -> -29.690548
B15: 52W H/L | D15: 126 | E15: 126 | F15: 199 | G15: 199

Sheet VAR>

Sheet Historical Approach
B4: ="VAR Analysis" & "- " & 'Data Sheet'!B1 -> VAR Analysis- NTPC LTD
B7: Value at Risk Calculation
A9: # | B9: ='Historical VAR Data'!B3 -> Date | C9: ='Historical VAR Data'!F3 -> Adj Close | D9: Return | E9: Sorted Return | H9: ="Calculation of Value at Risk" & " - " & 'Data Sheet'!B1 & " (Historical) " -> Calculation of Value at Risk - NTPC LTD (Historical)
B10: ='Historical VAR Data'!B4 -> 45706 | C10: ='Historical VAR Data'!F4 -> 311.20 | D10: =(C10-C11)/C11 -> 0.029270713 | E10: 0.029270713
B11: ='Historical VAR Data'!B5 -> 45705 | C11: ='Historical VAR Data'!F5 -> 302.35 | D11: =(C11-C12)/C12 -> 0.006658898 | E11: 0.006658898 | H11: Historical Approach
B12: ='Historical VAR Data'!B6 -> 45702 | C12: ='Historical VAR Data'!F6 -> 300.35 | D12: =(C12-C13)/C13 -> -0.020704271 | E12: -0.020704271 | H12: Mean | L12: =AVERAGE(E10:E5022) -> 0.00062571169
B13: ='Historical VAR Data'!B7 -> 45701 | C13: ='Historical VAR Data'!F7 -> 306.70 | D13: =(C13-C14)/C14 -> 0.0014693878 | E13: 0.0014693878 | H13: Std. Deviation | L13: =_xlfn.STDEV.S(E10:E5022) -> 0.018559534
B14: ='Historical VAR Data'!B8 -> 45700 | C14: ='Historical VAR Data'!F8 -> 306.25 | D14: =(C14-C15)/C15 -> 0.0021269634 | E14: 0.0021269634 | H14: Min | L14: =MIN(E10:E5022) -> -0.15452838
B15: ='Historical VAR Data'!B9 -> 45699 | C15: ='Historical VAR Data'!F9 -> 305.60 | D15: =(C15-C16)/C16 -> -0.015780998 | E15: -0.015780998 | H15: Max | L15: =MAX(E10:E5022) -> 0.12832551
B16: ='Historical VAR Data'!B10 -> 45698 | C16: ='Historical VAR Data'!F10 -> 310.50 | D16: =(C16-C17)/C17 -> -0.020350213 | E16: -0.020350213 | H16: CMP | L16: 314.8
B17: ='Historical VAR Data'!B11 -> 45695 | C17: ='Historical VAR Data'!F11 -> 316.95 | D17: =(C17-C18)/C18 -> 0.013267263 | E17: 0.013267263
B18: ='Historical VAR Data'!B12 -> 45694 | C18: ='Historical VAR Data'!F12 -> 312.80 | D18: =(C18-C19)/C19 -> -0.021276596 | E18: -0.021276596 | H18: Percentile | I18: Confidence | J18: VAR% | K18: Stock Price | L18: VAR (INR)
B19: ='Historical VAR Data'!B13 -> 45693 | C19: ='Historical VAR Data'!F13 -> 319.60 | D19: =(C19-C20)/C20 -> 0.0015669069 | E19: 0.0015669069 | H19: 0.05 | I19: =100%-H19 -> 0.95 | J19: =_xlfn.PERCENTILE.INC($E$10:$E$5022,H19) -> -0.026836193 | K19: =$L$16*(1-$J$19) -> 323.24803 | L19: =$L$16-K19 -> -8.4480335
B20: ='Historical VAR Data'!B14 -> 45692 | C20: ='Historical VAR Data'!F14 -> 319.10 | D20: =(C20-C21)/C21 -> 0.025220884 | E20: 0.025220884 | H20: 0.01 | I20: =100%-H20 -> 0.99 | J20: =_xlfn.PERCENTILE.INC($E$10:$E$5022,H20) -> -0.047004272 | K20: =$L$16*(1-J20) -> 329.59694 | L20: =$L$16-K20 -> -14.796945
B21: ='Historical VAR Data'!B15 -> 45691 | C21: ='Historical VAR Data'!F15 -> 311.25 | D21: =(C21-C22)/C22 -> -0.020302172 | E21: -0.020302172 | H21: 0.005 | I21: =100%-H21 -> 0.995 | J21: =_xlfn.PERCENTILE.INC($E$10:$E$5022,H21) -> -0.059542111 | K21: =$L$16*(1-J21) -> 333.54386 | L21: =$L$16-K21 -> -18.743857
B22: ='Historical VAR Data'!B16 -> 45689 | C22: ='Historical VAR Data'!F16 -> 317.70 | D22: =(C22-C23)/C23 -> -0.019444444 | E22: -0.019444444 | H22: 0.1 | I22: =100%-H22 -> 0.9 | J22: =_xlfn.PERCENTILE.INC($E$10:$E$5022,H22) -> -0.019483954 | K22: =$L$16*(1-J22) -> 320.93355 | L22: =$L$16-K22 -> -6.1335486
B23: ='Historical VAR Data'!B17 -> 45688 | C23: ='Historical VAR Data'!F17 -> 324.00 | D23: =(C23-C24)/C24 -> 0.010920437 | E23: 0.010920437
B24: ='Historical VAR Data'!B18 -> 45687 | C24: ='Historical VAR Data'!F18 -> 320.50 | D24: =(C24-C25)/C25 -> 0.0054586523 | E24: 0.0054586523
B25: ='Historical VAR Data'!B19 -> 45686 | C25: ='Historical VAR Data'!F19 -> 318.76 | D25: =(C25-C26)/C26 -> 0.0094049843 | E25: 0.0094049843
B26: ='Historical VAR Data'!B20 -> 45685 | C26: ='Historical VAR Data'!F20 -> 315.79 | D26: =(C26-C27)/C27 -> -0.012261112 | E26: -0.012261112
B27: ='Historical VAR Data'!B21 -> 45684 | C27: ='Historical VAR Data'!F21 -> 319.71 | D27: =(C27-C28)/C28 -> -0.0044528866 | E27: -0.0044528866
B28: ='Historical VAR Data'!B22 -> 45681 | C28: ='Historical VAR Data'!F22 -> 321.14 | D28: =(C28-C29)/C29 -> 0 | E28: 0
B29: ='Historical VAR Data'!B23 -> 45680 | C29: ='Historical VAR Data'!F23 -> 321.14 | D29: =(C29-C30)/C30 -> 0.0038762113 | E29: 0.0038762113
B30: ='Historical VAR Data'!B24 -> 45679 | C30: ='Historical VAR Data'!F24 -> 319.90 | D30: =(C30-C31)/C31 -> -0.0058733957 | E30: -0.0058733957
B31: ='Historical VAR Data'!B25 -> 45678 | C31: ='Historical VAR Data'!F25 -> 321.79 | D31: =(C31-C32)/C32 -> -0.034967761 | E31: -0.034967761
B32: ='Historical VAR Data'!B26 -> 45677 | C32: ='Historical VAR Data'!F26 -> 333.45 | D32: =(C32-C33)/C33 -> 0.030343293 | E32: 0.030343293
B33: ='Historical VAR Data'!B27 -> 45674 | C33: ='Historical VAR Data'!F27 -> 323.63 | D33: =(C33-C34)/C34 -> 0.0020125085 | E33: 0.0020125085
B34: ='Historical VAR Data'!B28 -> 45673 | C34: ='Historical VAR Data'!F28 -> 322.98 | D34: =(C34-C35)/C35 -> 0.012921031 | E34: 0.012921031
... B37: ='Historical VAR Data'!B31 -> 45670 | C37: ='Historical VAR Data'!F31 -> 295.89 | D37: =(C37-C38)/C38 -> -0.032596613 | E37: -0.032596613
B38: ='Historical VAR Data'!B32 -> 45667 | C38: ='Historical VAR Data'!F32 -> 305.86 | D38: =(C38-C42)/C42 -> -0.037782741 | E38: -0.037782741
B42: ='Historical VAR Data'!B33 -> 45666 | C42: ='Historical VAR Data'!F33 -> 317.87 | D42: =(C42-C43)/C43 -> -0.015516601 | E42: -0.015516601
B43: ='Historical VAR Data'!B34 -> 45665 | C43: ='Historical VAR Data'!F34 -> 322.88 | D43: =(C43-C44)/C44 -> -0.0097528062 | E43: -0.0097528062
B44: ='Historical VAR Data'!B35 -> 45664 | C44: ='Historical VAR Data'!F35 -> 326.06 | D44: =(C44-C45)/C45 -> 0.0033541558 | E44: 0.0033541558
B45: ='Historical VAR Data'!B36 -> 45663 | C45: ='Historical VAR Data'!F36 -> 324.97 | D45: =(C45-C46)/C46 -> -0.036326434 | E45: -0.036326434
B46: ='Historical VAR Data'!B37 -> 45660 | C46: ='Historical VAR Data'!F37 -> 337.22 | D46: =(C46-C47)/C47 -> 0.005486314 | E46: 0.005486314
B47: ='Historical VAR Data'!B38 -> 45659 | C47: ='Historical VAR Data'!F38 -> 335.38 | D47: =(C47-C48)/C48 -> 0.013018395 | E47: 0.013018395
B48: ='Historical VAR Data'!B39 -> 45658 | C48: ='Historical VAR Data'!F39 -> 331.07 | D48: =(C48-C49)/C49 -> 0.00090697463 | E48: 0.00090697463
B49: ='Historical VAR Data'!B40 -> 45657 | C49: ='Historical VAR Data'!F40 -> 330.77 | D49: =(C49-C50)/C50 -> 0.005899705 | E49: 0.005899705
B50: ='Historical VAR Data'!B41 -> 45656 | C50: ='Historical VAR Data'!F41 -> 328.83 | D50: =(C50-C51)/C51 -> -0.010769832 | E50: -0.010769832
B51: ='Historical VAR Data'!B42 -> 45653 | C51: ='Historical VAR Data'!F42 -> 332.41 | D51: =(C51-C52)/C52 -> 0.0010540264 | E51: 0.0010540264
B52: ='Historical VAR Data'!B43 -> 45652 | C52: ='Historical VAR Data'!F43 -> 332.06 | D52: =(C52-C53)/C53 -> -0.0019236549 | E52: -0.0019236549
B53: ='Historical VAR Data'!B44 -> 45650 | C53: ='Historical VAR Data'!F44 -> 332.70 | D53: =(C53-C54)/C54 -> 0.0049234301 | E53: 0.0049234301
... B5022: ='Historical VAR Data'!B5013 -> 38299 | C5022: ='Historical VAR Data'!F5013 -> 31.97 | D5022: =(C5022-C5023)/C5023 -> #DIV/0! | E5022: -0.0046699875

Sheet Dupont Analysis
B3: ='Data Sheet'!B1 -> NTPC LTD
B4: =CONCATENATE(" ","(",VLOOKUP(B3,'List of Stocks'!A2:C5442,3,1)," | ","BSE Code: ",VLOOKUP(B3,'List of Stocks'!A2:B5442,2,1),")") -> (NTPC | BSE Code: 532555)
B5: =CONCATENATE(" ","INR " & 'Data Sheet'!B8) -> INR 315.8
B6: 52 Week (High - INR 448.45 & Low - 292.80)
B8: About the Company
B10: NTPC (National Thermal Power Corporation) Ltd along with its subsidiaries/ associates & JVs is primarily involved in generation and sale of bulk power to State power utilities. Other business of the group includes providing consultancy, project management & supervision, energy trading, oil & gas exploration and coal mining. NTPC's core function is the generation and distribution of electricity to State Electricity Boards in India.It is the largest power company in India with an installed capacity of 76442.78 MW.
B14: Financial Summary
B59: Return on Equity(ROE)
C60: =HistoricalFS!F8 -> 43190 | D60: =HistoricalFS!G8 -> 43555 | E60: =HistoricalFS!H8 -> 43921 | F60: =HistoricalFS!I8 -> 44286 | G60: =HistoricalFS!J8 -> 44651 | H60: =HistoricalFS!K8 -> 45016 | I60: =HistoricalFS!L8 -> 45382
B61: Net Profit | C61: ='Data Sheet'!E30 -> 10543.95 | D61: ='Data Sheet'!F30 -> 13736.68 | E61: ='Data Sheet'!G30 -> 11600.23 | F61: ='Data Sheet'!H30 -> 14634.63 | G61: ='Data Sheet'!I30 -> 16675.9 | H61: ='Data Sheet'!J30 -> 16912.55 | I61: ='Data Sheet'!K30 -> 20811.89
B62: Average Shareholder Equity | C62: =(('Data Sheet'!E58+'Data Sheet'!E59)+('Data Sheet'!D58+'Data Sheet'!D59))/2 -> 100700.74 | D62: =(('Data Sheet'!F58+'Data Sheet'!F59)+('Data Sheet'!E58+'Data Sheet'!E59))/2 -> 107459.84 | E62: =(('Data Sheet'!G58+'Data Sheet'!G59)+('Data Sheet'!F58+'Data Sheet'!F59))/2 -> 115097.68 | F62: =(('Data Sheet'!H58+'Data Sheet'!H59)+('Data Sheet'!G58+'Data Sheet'!G59))/2 -> 122288.82 | G62: =(('Data Sheet'!I58+'Data Sheet'!I59)+('Data Sheet'!H58+'Data Sheet'!H59))/2 -> 130556.11 | H62: =(('Data Sheet'!J58+'Data Sheet'!J59)+('Data Sheet'!I58+'Data Sheet'!I59))/2 -> 141198.46 | I62: =(('Data Sheet'!K58+'Data Sheet'!K59)+('Data Sheet'!J58+'Data Sheet'!J59))/2 -> 153866.22
B63: Return on Equity(ROE) | C63: =C61/C62 -> 0.10470578 | D63: =D61/D62 -> 0.12783082 | E63: =E61/E62 -> 0.10078595 | F63: =F61/F62 -> 0.11967268 | G63: =G61/G62 -> 0.12772976 | H63: =H61/H62 -> 0.11977858 | I63: =I61/I62 -> 0.13525964
B65: ROE - Dupont Equation
C66: =C60 -> 43190 | D66: =D60 -> 43555 | E66: =E60 -> 43921 | F66: =F60 -> 44286 | G66: =G60 -> 44651 | H66: =H60 -> 45016 | I66: =I60 -> 45382
B67: =B61 -> Net Profit | C67: =C61 -> 10543.95 | D67: =D61 -> 13736.68 | E67: =E61 -> 11600.23 | F67: =F61 -> 14634.63 | G67: =G61 -> 16675.9 | H67: =H61 -> 16912.55 | I67: =I61 -> 20811.89
B68: Revenue | C68: ='Data Sheet'!E17 -> 88083.31 | D68: ='Data Sheet'!F17 -> 100286.54 | E68: ='Data Sheet'!G17 -> 109464.04 | F68: ='Data Sheet'!H17 -> 111531.15 | G68: ='Data Sheet'!I17 -> 132669.28 | H68: ='Data Sheet'!J17 -> 176207.18 | I68: ='Data Sheet'!K17 -> 178500.88
B69: Net Profit Margin (A) | C69: =C67/C68 -> 0.11970429 | D69: =D67/D68 -> 0.13697431 | E69: =E67/E68 -> 0.10597298 | F69: =F67/F68 -> 0.13121563 | G69: =G67/G68 -> 0.12569526 | H69: =H67/H68 -> 0.095981049 | I69: =I67/I68 -> 0.11659265
B71: Revenue | C71: =C68 -> 88083.31 | D71: =D68 -> 100286.54 | E71: =E68 -> 109464.04 | F71: =F68 -> 111531.15 | G71: =G68 -> 132669.28 | H71: =H68 -> 176207.18 | I71: =I68 -> 178500.88
B72: Average Total Asset | C72: =('Data Sheet'!E67+'Data Sheet'!D67)/2 -> 265546.54 | D72: =('Data Sheet'!F67+'Data Sheet'!E67)/2 -> 314707.62 | E72: =('Data Sheet'!G67+'Data Sheet'!F67)/2 -> 362245.99 | F72: =('Data Sheet'!H67+'Data Sheet'!G67)/2 -> 387795.4 | G72: =('Data Sheet'!I67+'Data Sheet'!H67)/2 -> 406926.6 | H72: =('Data Sheet'!J67+'Data Sheet'!I67)/2 -> 431510.16 | I72: =('Data Sheet'!K67+'Data Sheet'!J67)/2 -> 463233.3
B73: Asset Turnover Ratio (B) | C73: =C71/C72 -> 0.33170573 | D73: =D71/D72 -> 0.31866575 | E73: =E71/E72 -> 0.30218151 | F73: =F71/F72 -> 0.28760308 | G73: =G71/G72 -> 0.32602754 | H73: =H71/H72 -> 0.40835002 | I73: =I71/I72 -> 0.38533689
B75: Average Total Asset | C75: =C72 -> 265546.54 | D75: =D72 -> 314707.62 | E75: =E72 -> 362245.99 | F75: =F72 -> 387795.4 | G75: =G72 -> 406926.6 | H75: =H72 -> 431510.16 | I75: =I72 -> 463233.3
B76: Average Shareholder Equity | C76: =C62 -> 100700.74 | D76: =D62 -> 107459.84 | E76: =E62 -> 115097.68 | F76: =F62 -> 122288.82 | G76: =G62 -> 130556.11 | H76: =H62 -> 141198.46 | I76: =I62 -> 153866.22
B77: Equity Multiplier (C) | C77: =C75/C76 -> 2.6369868 | D77: =D75/D76 -> 2.9286069 | E77: =E75/E76 -> 3.1472918 | F77: =F75/F76 -> 3.1711436 | G77: =G75/G76 -> 3.1168715 | H77: =H75/H76 -> 3.0560544 | I77: =I75/I76 -> 3.0106238
B79: Return on Equity (A*B*C) | C79: =C77*C73*C69 -> 0.10470578 | D79: =D77*D73*D69 -> 0.12783082 | E79: =E77*E73*E69 -> 0.10078595 | F79: =F77*F73*F69 -> 0.11967268 | G79: =G77*G73*G69 -> 0.12772976 | H79: =H77*H73*H69 -> 0.11977858 | I79: =I77*I73*I69 -> 0.13525964
B81: Return on Asset
C82: =C60 -> 43190 | D82: =D60 -> 43555 | E82: =E60 -> 43921 | F82: =F60 -> 44286 | G82: =G60 -> 44651 | H82: =H60 -> 45016 | I82: =I60 -> 45382
B83: =B67 -> Net Profit | C83: =C67 -> 10543.95 | D83: =D67 -> 13736.68 | E83: =E67 -> 11600.23 | F83: =F67 -> 14634.63 | G83: =G67 -> 16675.9 | H83: =H67 -> 16912.55 | I83: =I67 -> 20811.89
B84: =B76 -> Average Shareholder Equity | C84: =C76 -> 100700.74 | D84: =D76 -> 107459.84 | E84: =E76 -> 115097.68 | F84: =F76 -> 122288.82 | G84: =G76 -> 130556.11 | H84: =H76 -> 141198.46 | I84: =I76 -> 153866.22
B85: Return on Asset | C85: =C83/C84 -> 0.10470578 | D85: =D83/D84 -> 0.12783082 | E85: =E83/E84 -> 0.10078595 | F85: =F83/F84 -> 0.11967268 | G85: =G83/G84 -> 0.12772976 | H85: =H83/H84 -> 0.11977858 | I85: =I83/I84 -> 0.13525964
B87: ROA - Dupont Equation
C88: =C82 -> 43190 | D88: =D82 -> 43555 | E88: =E82 -> 43921 | F88: =F82 -> 44286 | G88: =G82 -> 44651 | H88: =H82 -> 45016 | I88: =I82 -> 45382
B89: =B83 -> Net Profit | C89: =C83 -> 10543.95 | D89: =D83 -> 13736.68 | E89: =E83 -> 11600.23 | F89: =F83 -> 14634.63 | G89: =G83 -> 16675.9 | H89: =H83 -> 16912.55 | I89: =I83 -> 20811.89
B90: Revenue | C90: =C71 -> 88083.31 | D90: =D71 -> 100286.54 | E90: =E71 -> 109464.04 | F90: =F71 -> 111531.15 | G90: =G71 -> 132669.28 | H90: =H71 -> 176207.18 | I90: =I71 -> 178500.88
B91: Net Profit Margin (A) | C91: =C89/C90 -> 0.11970429 | D91: =D89/D90 -> 0.13697431 | E91: =E89/E90 -> 0.10597298 | F91: =F89/F90 -> 0.13121563 | G91: =G89/G90 -> 0.12569526 | H91: =H89/H90 -> 0.095981049 | I91: =I89/I90 -> 0.11659265
B93: Revenue | C93: =C90 -> 88083.31 | D93: =D90 -> 100286.54 | E93: =E90 -> 109464.04 | F93: =F90 -> 111531.15 | G93: =G90 -> 132669.28 | H93: =H90 -> 176207.18 | I93: =I90 -> 178500.88
B94: Average Total Asset | C94: =C75 -> 265546.54 | D94: =D75 -> 314707.62 | E94: =E75 -> 362245.99 | F94: =F75 -> 387795.4 | G94: =G75 -> 406926.6 | H94: =H75 -> 431510.16 | I94: =I75 -> 463233.3
B95: Asset Turnover Ratio (B) | C95: =C93/C94 -> 0.33170573 | D95: =D93/D94 -> 0.31866575 | E95: =E93/E94 -> 0.30218151 | F95: =F93/F94 -> 0.28760308 | G95: =G93/G94 -> 0.32602754 | H95: =H93/H94 -> 0.40835002 | I95: =I93/I94 -> 0.38533689
B97: Return on Asset (A*B) | C97: =C91*C95 -> 0.039706599 | D97: =D91*D95 -> 0.043649022 | E97: =E91*E95 -> 0.032023073 | F97: =F91*F95 -> 0.037738019 | G97: =G91*G95 -> 0.040980117 | H97: =H91*H95 -> 0.039193863 | I97: =I91*I95 -> 0.044927448
B120: Sources:
B121: 52 High week Low | C121: https://www.nseindia.com/market-data/52-week-high-equity-market

Sheet Monte Carlo Simulation
B4: ="Monte Carlo Simulation" & "- " & 'Data Sheet'!B1 -> Monte Carlo Simulation- NTPC LTD
B7: Monte Carlo Simulation Calculation
A9: # | B9: ='Historical VAR Data'!B3 -> Date | C9: ='Historical VAR Data'!F3 -> Adj Close | D9: Return | E9: Sorted Return | G9: Replication | H9: Simulated Returns | J9: ="Calculation of Value at Risk" & " - " & 'Data Sheet'!B1 & " (Simulation) " -> Calculation of Value at Risk - NTPC LTD (Simulation)
B10: ='Historical VAR Data'!B4212 -> 39470 | C10: ='Historical VAR Data'!F4212 -> 100.94 | D10: =(C10-C11)/C11 -> 0.29310787 | E10: 0.12832551 | G10: 1 | H10: =_xlfn.NORM.INV(RAND(),N$12,N$13) -> -0.033723088
B11: ='Historical VAR Data'!B2658 -> 41778 | C11: ='Historical VAR Data'!F2658 -> 78.06 | D11: =(C11-C12)/C12 -> -0.19716137 | E11: 0.10644933 | G11: 2 | H11: =_xlfn.NORM.INV(RAND(),N$12,N$13) -> 0.021703108 | J11: Historical Approach
B12: ='Historical VAR Data'!B3896 -> 39951 | C12: ='Historical VAR Data'!F3896 -> 97.23 | D12: =(C12-C13)/C13 -> -0.024382902 | E12: 0.10163154 | G12: 3 | H12: =_xlfn.NORM.INV(RAND(),N$12,N$13) -> -0.0074621138 | J12: Mean | N12: =AVERAGE(E10:E5021) -> 0.00062571169
B13: ='Historical VAR Data'!B4275 -> 39378 | C13: ='Historical VAR Data'!F4275 -> 99.66 | D13: =(C13-C14)/C14 -> -0.018031333 | E13: 0.096128465 | G13: 4 | H13: =_xlfn.NORM.INV(RAND(),N$12,N$13) -> 0.0070134049 | J13: Std. Deviation | N13: =_xlfn.STDEV.S(E10:E5021) -> 0.018559534
B14: ='Historical VAR Data'!B4210 -> 39472 | C14: ='Historical VAR Data'!F4210 -> 101.49 | D14: =(C14-C15)/C15 -> -0.73526189 | E14: 0.09458585 | G14: 5 | H14: =_xlfn.NORM.INV(RAND(),N$12,N$13) -> -0.017372469 | J14: Min | N14: =MIN(E10:E5021) -> -0.15452838
B15: ='Historical VAR Data'!B184 -> 45446 | C15: ='Historical VAR Data'!F184 -> 383.36 | D15: =(C15-C16)/C16 -> 4.4914769 | E15: 0.091354229 | G15: 6 | H15: =_xlfn.NORM.INV(RAND(),N$12,N$13) -> 0.036568528 | J15: Max | N15: =MAX(E10:E5021) -> 0.12832551
B16: ='Historical VAR Data'!B4009 -> 39773 | C16: ='Historical VAR Data'!F4009 -> 69.81 | D16: =(C16-C17)/C17 -> 0.45104968 | E16: 0.086536965 | G16: 7 | H16: =_xlfn.NORM.INV(RAND(),N$12,N$13) -> 0.0016264259 | J16: CMP | N16: 314.8
B17: ='Historical VAR Data'!B4617 -> 38877 | C17: ='Historical VAR Data'!F4617 -> 48.11 | D17: =(C17-C18)/C18 -> -0.42314149 | E17: 0.084291188 | G17: 8 | H17: =_xlfn.NORM.INV(RAND(),N$12,N$13) -> -0.021626695
B18: ='Historical VAR Data'!B3973 -> 39829 | C18: ='Historical VAR Data'!F3973 -> 83.40 | D18: =(C18-C19)/C19 -> 0.11467522 | E18: 0.078913325 | G18: 9 | H18: =_xlfn.NORM.INV(RAND(),N$12,N$13) -> 0.0047071225 | J18: Monte Carlo Simulation
B19: ='Historical VAR Data'!B1122 -> 44060 | C19: ='Historical VAR Data'!F1122 -> 74.82 | D19: =(C19-C20)/C20 -> -0.093310713 | E19: 0.07794266 | G19: 10 | H19: =_xlfn.NORM.INV(RAND(),N$12,N$13) -> -0.017224285 | J19: Mean | N19: =AVERAGE(H10:H5021) -> 0.00061100341
B20: ='Historical VAR Data'!B4035 -> 39734 | C20: ='Historical VAR Data'!F4035 -> 82.52 | D20: =(C20-C21)/C21 -> 0.092690678 | E20: 0.076862847 | G20: 11 | H20: =_xlfn.NORM.INV(RAND(),N$12,N$13) -> 0.037400122 | J20: Std. Deviation | N20: =_xlfn.STDEV.S(H10:H5021) -> 0.018386664
B21: ='Historical VAR Data'!B4017 -> 39762 | C21: ='Historical VAR Data'!F4017 -> 75.52 | D21: =(C21-C22)/C22 -> -0.39949109 | E21: 0.075630252 | G21: 12 | H21: =_xlfn.NORM.INV(RAND(),N$12,N$13) -> 0.0060060035 | J21: Min | N21: =MIN(H10:H5021) -> -0.064064046
B22: ='Historical VAR Data'!B4226 -> 39450 | C22: ='Historical VAR Data'!F4226 -> 125.76 | D22: =(C22-C23)/C23 -> 0.014438977 | E22: 0.073862181 | G22: 13 | H22: =_xlfn.NORM.INV(RAND(),N$12,N$13) -> -0.013840598 | J22: Max | N22: =MAX(H10:H5021) -> 0.06418125
B23: ='Historical VAR Data'!B4261 -> 39399 | C23: ='Historical VAR Data'!F4261 -> 123.97 | D23: =(C23-C24)/C24 -> 0.16469372 | E23: 0.073798181 | G23: 14 | H23: =_xlfn.NORM.INV(RAND(),N$12,N$13) -> 0.00019823772 | J23: CMP | N23: 314.8
B24: ='Historical VAR Data'!B853 -> 44454 | C24: ='Historical VAR Data'!F853 -> 106.44 | D24: =(C24-C25)/C25 -> 0.14760108 | E24: 0.071579583 | G24: 15 | H24: =_xlfn.NORM.INV(RAND(),N$12,N$13) -> -0.013107676
B25: ='Historical VAR Data'!B4196 -> 39492 | C25: ='Historical VAR Data'!F4196 -> 92.75 | D25: =(C25-C26)/C26 -> -0.14571244 | E25: 0.070027688 | G25: 16 | H25: =_xlfn.NORM.INV(RAND(),N$12,N$13) -> 0.024319271 | J25: Percentile | K25: Confidence | L25: VAR% | M25: Stock Price | N25: VAR (INR)
B26: ='Historical VAR Data'!B3744 -> 40170 | C26: ='Historical VAR Data'!F3744 -> 108.57 | D26: =(C26-C27)/C27 -> 0.551 | E26: 0.069865983 | G26: 17 | H26: =_xlfn.NORM.INV(RAND(),N$12,N$13) -> -0.0012415187 | J26: 0.05 | K26: =100%-J26 -> 0.95 | L26: =_xlfn.PERCENTILE.INC($H$10:$H$5021,J26) -> -0.02953625 | M26: =$N$23*(1-$L$26) -> 324.09801 | N26: =$N$23-M26 -> -9.2980117
B27: ='Historical VAR Data'!B4022 -> 39755 | C27: ='Historical VAR Data'!F4022 -> 70.00 | D27: =(C27-C28)/C28 -> -0.17091081 | E27: 0.069845637 | G27: 18 | H27: =_xlfn.NORM.INV(RAND(),N$12,N$13) -> -0.0018435083 | J27: 0.01 | K27: =100%-J27 -> 0.99 | L27: =_xlfn.PERCENTILE.INC($H$10:$H$5021,J27) -> -0.044056089 | M27: =$N$16*(1-L27) -> 328.66886 | N27: =$N$16-M27 -> -13.868857
B28: ='Historical VAR Data'!B4310 -> 39328 | C28: ='Historical VAR Data'!F4310 -> 84.43 | D28: =(C28-C29)/C29 -> 0.10684321 | E28: 0.069275583 | G28: 19 | H28: =_xlfn.NORM.INV(RAND(),N$12,N$13) -> -0.012700606 | J28: 0.005 | K28: =100%-J28 -> 0.995 | L28: =_xlfn.PERCENTILE.INC($H$10:$H$5021,J28) -> -0.049348245 | M28: =$N$16*(1-L28) -> 330.33483 | N28: =$N$16-M28 -> -15.534827
B29: ='Historical VAR Data'!B4006 -> 39778 | C29: ='Historical VAR Data'!F4006 -> 76.28 | D29: =(C29-C30)/C30 -> -0.039052658 | E29: 0.068796413 | G29: 20 | H29: =_xlfn.NORM.INV(RAND(),N$12,N$13) -> 0.020007932 | J29: 0.1 | K29: =100%-J29 -> 0.9 | L29: =_xlfn.PERCENTILE.INC($H$10:$H$5021,J29) -> -0.023002968 | M29: =$N$16*(1-L29) -> 322.04133 | N29: =$N$16-M29 -> -7.2413344
B30: ='Historical VAR Data'!B1119 -> 44063 | C30: ='Historical VAR Data'!F1119 -> 79.38 | D30: =(C30-C31)/C31 -> -0.10577898 | E30: 0.068227695 | G30: 21 | H30: =_xlfn.NORM.INV(RAND(),N$12,N$13) -> 0.022351394
B31: ='Historical VAR Data'!B3449 -> 40603 | C31: ='Historical VAR Data'!F3449 -> 88.77 | D31: =(C31-C32)/C32 -> -0.042084817 | E31: 0.067717104 | G31: 22 | H31: =_xlfn.NORM.INV(RAND(),N$12,N$13) -> 0.014800584
B32: ='Historical VAR Data'!B3921 -> 39911 | C32: ='Historical VAR Data'!F3921 -> 92.67 | D32: =(C32-C33)/C33 -> -0.25078826 | E32: 0.066643646 | G32: 23 | H32: =_xlfn.NORM.INV(RAND(),N$12,N$13) -> 0.015605483
B33: ='Historical VAR Data'!B843 -> 44468 | C33: ='Historical VAR Data'!F843 -> 123.69 | D33: =(C33-C34)/C34 -> 0.99050531 | E33: 0.066017409 | G33: 24 | H33: =_xlfn.NORM.INV(RAND(),N$12,N$13) -> -0.00014733312
B34: ='Historical VAR Data'!B4024 -> 39750 | C34: ='Historical VAR Data'!F4024 -> 62.14 | D34: =(C34-C35)/C35 -> -0.4243098 | E34: 0.065683416 | G34: 25 | H34: =_xlfn.NORM.INV(RAND(),N$12,N$13) -> 0.016294155
B35: ='Historical VAR Data'!B3886 -> 39965 | C35: ='Historical VAR Data'!F3886 -> 107.94 | D35: =(C35-C36)/C36 -> 0.086243333 | E35: 0.064812075 | G35: 26 | H35: =_xlfn.NORM.INV(RAND(),N$12,N$13) -> 0.00073359655
B36: ='Historical VAR Data'!B4285 -> 39364 | C36: ='Historical VAR Data'!F4285 -> 99.37 | D36: =(C36-C37)/C37 -> 0.056453328 | E36: 0.064716597 | G36: 27 | H36: =_xlfn.NORM.INV(RAND(),N$12,N$13) -> 0.023645147
B37: ='Historical VAR Data'!B4290 -> 39356 | C37: ='Historical VAR Data'!F4290 -> 94.06 | D37: =(C37-C38)/C38 -> -0.36316858 | E37: 0.064629315 | G37: 28 | H37: =_xlfn.NORM.INV(RAND(),N$12,N$13) -> 0.00082824002
B38: ='Historical VAR Data'!B708 -> 44669 | C38: ='Historical VAR Data'!F708 -> 147.70 | D38: =(C38-C39)/C39 -> 0.14168664 | E38: 0.060073207 | G38: 29 | H38: =_xlfn.NORM.INV(RAND(),N$12,N$13) -> 0.021350159
B39: ='Historical VAR Data'!B717 -> 44652 | C39: ='Historical VAR Data'!F717 -> 129.37 | D39: =(C39-C40)/C40 -> 0.56489658 | E39: 0.058847602 | G39: 30 | H39: =_xlfn.NORM.INV(RAND(),N$12,N$13) -> -0.0022494543
B40: ='Historical VAR Data'!B2655 -> 41781 | C40: ='Historical VAR Data'!F2655 -> 82.67 | D40: =(C40-C41)/C41 -> 0.14137788 | E40: 0.058785861 | G40: 31 | H40: =_xlfn.NORM.INV(RAND(),N$12,N$13) -> -0.025878432
B41: ='Historical VAR Data'!B1207 -> 43937 | C41: ='Historical VAR Data'!F1207 -> 72.43 | D41: =(C41-C44)/C44 -> 0.03753044 | E41: 0.057835548 | G41: 32 | H41: =_xlfn.NORM.INV(RAND(),N$12,N$13) -> 0.032125135
B44: ='Historical VAR Data'!B1190 -> 43963 | C44: ='Historical VAR Data'!F1190 -> 69.81 | D44: =(C44-C45)/C45 -> -0.29520444 | E44: 0.057727273 | G44: 33 | H44: =_xlfn.NORM.INV(RAND(),N$12,N$13) -> 0.014319836
B45: ='Historical VAR Data'!B4204 -> 39482 | C45: ='Historical VAR Data'!F4204 -> 99.05 | D45: =(C45-C46)/C46 -> 0.28569574 | E45: 0.057435678 | G45: 34 | H45: =_xlfn.NORM.INV(RAND(),N$12,N$13) -> -0.024212184
B46: ='Historical VAR Data'!B4123 -> 39604 | C46: ='Historical VAR Data'!F4123 -> 77.04 | D46: =(C46-C47)/C47 -> 0.0039093041 | E46: 0.057370299 | G46: 35 | H46: =_xlfn.NORM.INV(RAND(),N$12,N$13) -> 0.0048671934
B47: ='Historical VAR Data'!B1161 -> 44005 | C47: ='Historical VAR Data'!F1161 -> 76.74 | D47: =(C47-C48)/C48 -> -0.12953721 | E47: 0.057170409 | G47: 36 | H47: =_xlfn.NORM.INV(RAND(),N$12,N$13) -> -0.012963725
B48: ='Historical VAR Data'!B3967 -> 39840 | C48: ='Historical VAR Data'!F3967 -> 88.16 | D48: =(C48-C49)/C49 -> 0.31601732 | E48: 0.057074341 | G48: 37 | H48: =_xlfn.NORM.INV(RAND(),N$12,N$13) -> 0.016440291
B49: ='Historical VAR Data'!B2334 -> 42256 | C49: ='Historical VAR Data'!F2334 -> 66.99 | D49: =(C49-C50)/C50 -> 0.089268293 | E49: 0.056457972 | G49: 38 | H49: =_xlfn.NORM.INV(RAND(),N$12,N$13) -> -0.0083935022
B50: ='Historical VAR Data'!B4510 -> 39034 | C50: ='Historical VAR Data'!F4510 -> 61.50 | D50: =(C50-C51)/C51 -> -0.37595129 | E50: 0.05615662 | G50: 39 | H50: =_xlfn.NORM.INV(RAND(),N$12,N$13) -> 0.034169595
B51: ='Historical VAR Data'!B2006 -> 42747 | C51: ='Historical VAR Data'!F2006 -> 98.55 | D51: =(C51-C52)/C52 -> -0.14638372 | E51: 0.055930569 | G51: 40 | H51: =_xlfn.NORM.INV(RAND(),N$12,N$13) -> -0.015772316
B52: ='Historical VAR Data'!B4262 -> 39398 | C52: ='Historical VAR Data'!F4262 -> 115.45 | D52: =(C52-C53)/C53 -> 1.0099234 | E52: 0.055591113 | G52: 41 | H52: =_xlfn.NORM.INV(RAND(),N$12,N$13) -> -0.013044075
B53: ='Historical VAR Data'!B4689 -> 38770 | C53: ='Historical VAR Data'!F4689 -> 57.44 | D53: =(C53-C54)/C54 -> -0.14191814 | E53: 0.054912764 | G53: 42 | H53: =_xlfn.NORM.INV(RAND(),N$12,N$13) -> 0.028341353
B54: ='Historical VAR Data'!B4501 -> 39045 | C54: ='Historical VAR Data'!F4501 -> 66.94 | D54: =(C54-C55)/C55 -> -0.22198977 | E54: 0.054837693 | G54: 43 | H54: =_xlfn.NORM.INV(RAND(),N$12,N$13) -> -0.0081770599
B55: ='Historical VAR Data'!B2649 -> 41789 | C55: ='Historical VAR Data'!F2649 -> 86.04 | D55: =(C55-C56)/C56 -> -0.26379738 | E55: 0.054799559 | G55: 44 | H55: =_xlfn.NORM.INV(RAND(),N$12,N$13) -> 0.019907514
B56: ='Historical VAR Data'!B777 -> 44565 | C56: ='Historical VAR Data'!F777 -> 116.87 | D56: =(C56-C57)/C57 -> 0.41130298 | E56: 0.054783394 | G56: 45 | H56: =_xlfn.NORM.INV(RAND(),N$12,N$13) -> -0.011008312
B57: ='Historical VAR Data'!B1040 -> 44176 | C57: ='Historical VAR Data'!F1040 -> 82.81 | D57: =(C57-C58)/C58 -> 0.14378453 | E57: 0.054098778 | G57: 46 | H57: =_xlfn.NORM.INV(RAND(),N$12,N$13) -> -0.010374162
B58: ='Historical VAR Data'!B1197 -> 43951 | C58: ='Historical VAR Data'!F1197 -> 72.40 | D58: =(C58-C59)/C59 -> 0.10652606 | E58: 0.053857351 | G58: 47 | H58: =_xlfn.NORM.INV(RAND(),N$12,N$13) -> 0.028171456
B59: ='Historical VAR Data'!B4023 -> 39752 | C59: ='Historical VAR Data'!F4023 -> 65.43 | D59: =(C59-C60)/C60 -> -0.22896535 | E59: 0.052944963 | G59: 48 | H59: =_xlfn.NORM.INV(RAND(),N$12,N$13) -> -0.01166638
B60: ='Historical VAR Data'!B3991 -> 39800 | C60: ='Historical VAR Data'!F3991 -> 84.86 | D60: =(C60-C61)/C61 -> 0.21645642 | E60: 0.052853598 | G60: 49 | H60: =_xlfn.NORM.INV(RAND(),N$12,N$13) -> -0.0034544921
B61: ='Historical VAR Data'!B2331 -> 42261 | C61: ='Historical VAR Data'!F2331 -> 69.76 | D61: =(C61-C62)/C62 -> 0.89668298 | E61: 0.052187029 | G61: 50 | H61: =_xlfn.NORM.INV(RAND(),N$12,N$13) -> 0.0075244029
B62: ='Historical VAR Data'!B4955 -> 38383 | C62: ='Historical VAR Data'!F4955 -> 36.78 | D62: =(C62-C63)/C63 -> -0.54151085 | E62: 0.05175865 | G62: 51 | H62: =_xlfn.NORM.INV(RAND(),N$12,N$13) -> 0.018188778
B63: ='Historical VAR Data'!B4092 -> 39647 | C63: ='Historical VAR Data'!F4092 -> 80.22 | D63: =(C63-C64)/C64 -> -0.054455446 | E63: 0.051376147 | G63: 52 | H63: =_xlfn.NORM.INV(RAND(),N$12,N$13) -> 0.017518938
B64: ='Historical VAR Data'!B4049 -> 39710 | C64: ='Historical VAR Data'!F4049 -> 84.84 | D64: =(C64-C65)/C65 -> -0.49406643 | E64: 0.051170859 | G64: 53 | H64: =_xlfn.NORM.INV(RAND(),N$12,N$13) -> 0.0029776486
B65: ='Historical VAR Data'!B573 -> 44866 | C65: ='Historical VAR Data'!F573 -> 167.69 | D65: =(C65-C66)/C66 -> 2.2310212 | E65: 0.050228596 | G65: 54 | H65: =_xlfn.NORM.INV(RAND(),N$12,N$13) -> -0.017385237
B66: ='Historical VAR Data'!B4630 -> 38860 | C66: ='Historical VAR Data'!F4630 -> 51.90 | D66: =(C66-C67)/C67 -> -0.37985422 | E66: 0.050182113 | G66: 55 | H66: =_xlfn.NORM.INV(RAND(),N$12,N$13) -> 0.03957007
B67: ='Historical VAR Data'!B2468 -> 42061 | C67: ='Historical VAR Data'!F2468 -> 83.69 | D67: =(C67-C68)/C68 -> -0.15250633 | E67: 0.049931 | G67: 56 | H67: =_xlfn.NORM.INV(RAND(),N$12,N$13) -> -0.0055446632
B68: ='Historical VAR Data'!B4289 -> 39358 | C68: ='Historical VAR Data'!F4289 -> 98.75 | D68: =(C68-C69)/C69 -> 0.64145612 | E68: 0.04986179 | G68: 57 | H68: =_xlfn.NORM.INV(RAND(),N$12,N$13) -> -0.035177835
B69: ='Historical VAR Data'!B4646 -> 38835 | C69: ='Historical VAR Data'!F4646 -> 60.16 | D69: =(C69-C70)/C70 -> 0.4364852 | E69: 0.049363335 | G69: 58 | H69: =_xlfn.NORM.INV(RAND(),N$12,N$13) -> -0.021557876
B70: ='Historical VAR Data'!B4832 -> 38558 | C70: ='Historical VAR Data'!F4832 -> 41.88 | D70: =(C70-C71)/C71 -> -0.011798018 | E70: 0.049098196 | G70: 59 | H70: =_xlfn.NORM.INV(RAND(),N$12,N$13) -> 0.016710609
B71: ='Historical VAR Data'!B4827 -> 38565 | C71: ='Historical VAR Data'!F4827 -> 42.38 | D71: =(C71-C72)/C72 -> -0.54756059 | E71: 0.049009901 | G71: 60 | H71: =_xlfn.NORM.INV(RAND(),N$12,N$13) -> -0.0017438691
B72: ='Historical VAR Data'!B4205 -> 39479 | C72: ='Historical VAR Data'!F4205 -> 93.67 | D72: =(C72-C73)/C73 -> 0.33414044 | E72: 0.04893617 | G72: 61 | H72: =_xlfn.NORM.INV(RAND(),N$12,N$13) -> 0.010795078
B73: ='Historical VAR Data'!B4018 -> 39759 | C73: ='Historical VAR Data'!F4018 -> 70.21 | D73: =(C73-C74)/C74 -> -0.21535539 | E73: 0.04853644 | G73: 62 | H73: =_xlfn.NORM.INV(RAND(),N$12,N$13) -> 0.006382314
B74: ='Historical VAR Data'!B4295 -> 39349 | C74: ='Historical VAR Data'!F4295 -> 89.48 | D74: =(C74-C75)/C75 -> 0.085527114 | E74: 0.048511835 | G74: 63 | H74: =_xlfn.NORM.INV(RAND(),N$12,N$13) -> 0.011536359
B75: ='Historical VAR Data'!B1234 -> 43893 | C75: ='Historical VAR Data'!F1234 -> 82.43 | D75: =(C75-C76)/C76 -> -0.028062728 | E75: 0.048194303 | G75: 64 | H75: =_xlfn.NORM.INV(RAND(),N$12,N$13) -> -0.014271405
B76: ='Historical VAR Data'!B3313 -> 40802 | C76: ='Historical VAR Data'!F3313 -> 84.81 | D76: =(C76-C77)/C77 -> 0.019596057 | E76: 0.047942667 | G76: 65 | H76: =_xlfn.NORM.INV(RAND(),N$12,N$13) -> -0.017108044
B77: ='Historical VAR Data'!B1118 -> 44064 | C77: ='Historical VAR Data'!F1118 -> 83.18 | D77: =(C77-C78)/C78 -> -0.29490548 | E77: 0.047871 | G77: 66 | H77: =_xlfn.NORM.INV(RAND(),N$12,N$13) -> 0.018316268
B78: ='Historical VAR Data'!B740 -> 44617 | C78: ='Historical VAR Data'!F740 -> 117.97 | D78: =(C78-C79)/C79 -> 0.30729167 | E78: 0.047783995 | G78: 67 | H78: =_xlfn.NORM.INV(RAND(),N$12,N$13) -> -0.0055751815
B79: ='Historical VAR Data'!B2045 -> 42692 | C79: ='Historical VAR Data'!F2045 -> 90.24 | D79: =(C79-C80)/C80 -> 0.10277404 | E79: 0.047718565 | G79: 68 | H79: =_xlfn.NORM.INV(RAND(),N$12,N$13) -> 0.027105172
B80: ='Historical VAR Data'!B4038 -> 39728 | C80: ='Historical VAR Data'!F4038 -> 81.83 | D80: =(C80-C81)/C81 -> 0.74925182 | E80: 0.047491039 | G80: 69 | H80: =_xlfn.NORM.INV(RAND(),N$12,N$13) -> 0.0067118533
B81: ='Historical VAR Data'!B4613 -> 38883 | C81: ='Historical VAR Data'!F4613 -> 46.78 | D81: =(C81-C82)/C82 -> -0.3297034 | E81: 0.047469772 | G81: 70 | H81: =_xlfn.NORM.INV(RAND(),N$12,N$13) -> 0.015585594
B82: ='Historical VAR Data'!B4415 -> 39175 | C82: ='Historical VAR Data'!F4415 -> 69.79 | D82: =(C82-C83)/C83 -> 0.26937068 | E82: 0.047426084 | G82: 71 | H82: =_xlfn.NORM.INV(RAND(),N$12,N$13) -> -0.0046009528
B83: ='Historical VAR Data'!B4694 -> 38763 | C83: ='Historical VAR Data'!F4694 -> 54.98 | D83: =(C83-C84)/C84 -> -0.7516824 | E83: 0.047238095 | G83: 72 | H83: =_xlfn.NORM.INV(RAND(),N$12,N$13) -> 0.0076650745
B84: ='Historical VAR Data'!B365 -> 45170 | C84: ='Historical VAR Data'!F365 -> 221.41 | D84: =(C84-C85)/C85 -> 1.6730653 | E84: 0.047202384 | G84: 73 | H84: =_xlfn.NORM.INV(RAND(),N$12,N$13) -> 0.034273795
B85: ='Historical VAR Data'!B2985 -> 41292 | C85: ='Historical VAR Data'!F2985 -> 82.83 | D85: =(C85-C86)/C86 -> 0.1338809 | E85: 0.047023132 | G85: 74 | H85: =_xlfn.NORM.INV(RAND(),N$12,N$13) -> 0.023209815
B86: ='Historical VAR Data'!B4414 -> 39176 | C86: ='Historical VAR Data'!F4414 -> 73.05 | D86: =(C86-C87)/C87 -> -0.18869391 | E86: 0.046711563 | G86: 75 | H86: =_xlfn.NORM.INV(RAND(),N$12,N$13) -> 0.032700848
B87: ='Historical VAR Data'!B988 -> 44252 | C87: ='Historical VAR Data'!F988 -> 90.04 | D87: =(C87-C88)/C88 -> -0.041719881 | E87: 0.046490005 | G87: 76 | H87: =_xlfn.NORM.INV(RAND(),N$12,N$13) -> -0.03998419
B88: ='Historical VAR Data'!B940 -> 44327 | C88: ='Historical VAR Data'!F940 -> 93.96 | D88: =(C88-C89)/C89 -> 0.11604704 | E88: 0.046441697 | G88: 77 | H88: =_xlfn.NORM.INV(RAND(),N$12,N$13) -> -0.014212808
B89: ='Historical VAR Data'!B4058 -> 39699 | C89: ='Historical VAR Data'!F4058 -> 84.19 | D89: =(C89-C90)/C90 -> -0.33309569 | E89: 0.046358439 | G89: 78 | H89: =_xlfn.NORM.INV(RAND(),N$12,N$13) -> 0.020533447
B90: ='Historical VAR Data'!B4222 -> 39456 | C90: ='Historical VAR Data'!F4222 -> 126.24 | D90: =(C90-C91)/C91 -> 0.40266667 | E90: 0.046245649 | G90: 79 | H90: =_xlfn.NORM.INV(RAND(),N$12,N$13) -> 0.021908649
B91: ='Historical VAR Data'!B4176 -> 39521 | C91: ='Historical VAR Data'!F4176 -> 90.00 | D91: =(C91-C92)/C92 -> 0.06672988 | E91: 0.046025105 | G91: 80 | H91: =_xlfn.NORM.INV(RAND(),N$12,N$13) -> -0.016188267
B92: ='Historical VAR Data'!B4080 -> 39665 | C92: ='Historical VAR Data'!F4080 -> 84.37 | D92: =(C92-C93)/C93 -> -0.34929816 | E92: 0.045995537 | G92: 81 | H92: =_xlfn.NORM.INV(RAND(),N$12,N$13) -> -0.018758224
B93: ='Historical VAR Data'!B4219 -> 39461 | C93: ='Historical VAR Data'!F4219 -> 129.66 | D93: =(C93-C94)/C94 -> 1.6866971 | E93: 0.045560842 | G93: 82 | H93: =_xlfn.NORM.INV(RAND(),N$12,N$13) -> -0.018115957
B94: ='Historical VAR Data'!B4732 -> 38706 | C94: ='Historical VAR Data'!F4732 -> 48.26 | D94: =(C94-C95)/C95 -> -0.46650453 | E94: 0.045493934 | G94: 83 | H94: =_xlfn.NORM.INV(RAND(),N$12,N$13) -> -0.0067118981
B95: ='Historical VAR Data'!B973 -> 44274 | C95: ='Historical VAR Data'!F973 -> 90.46 | D95: =(C95-C96)/C96 -> 0.023534736 | E95: 0.045296972 | G95: 84 | H95: =_xlfn.NORM.INV(RAND(),N$12,N$13) -> -0.031082258
B96: ='Historical VAR Data'!B3403 -> 40673 | C96: ='Historical VAR Data'!F3403 -> 88.38 | D96: =(C96-C97)/C97 -> -0.14674648 | E96: 0.044927879 | G96: 85 | H96: =_xlfn.NORM.INV(RAND(),N$12,N$13) -> 0.0070548949
B97: ='Historical VAR Data'!B4281 -> 39370 | C97: ='Historical VAR Data'!F4281 -> 103.58 | D97: =(C97-C98)/C98 -> 0.59623979 | E97: 0.044785152 | G97: 86 | H97: =_xlfn.NORM.INV(RAND(),N$12,N$13) -> -0.024612503
B98: ='Historical VAR Data'!B1211 -> 43929 | C98: ='Historical VAR Data'!F1211 -> 64.89 | D98: =(C98-C99)/C99 -> 0.39368557 | E98: 0.044759298 | G98: 87 | H98: =_xlfn.NORM.INV(RAND(),N$12,N$13) -> -0.034425028
B99: ='Historical VAR Data'!B4789 -> 38621 | C99: ='Historical VAR Data'!F4789 -> 46.56 | D99: =(C99-C100)/C100 -> -0.49522984 | E99: 0.044648867 | G99: 88 | H99: =_xlfn.NORM.INV(RAND(),N$12,N$13) -> 0.018916906
B100: ='Historical VAR Data'!B4171 -> 39532 | C100: ='Historical VAR Data'!F4171 -> 92.24 | D100: =(C100-C101)/C101 -> 0.18636656 | E100: 0.044384058 | G100: 89 | H100: =_xlfn.NORM.INV(RAND(),N$12,N$13) -> -0.0035175939
B101: ='Historical VAR Data'!B4099 -> 39638 | C101: ='Historical VAR Data'!F4099 -> 77.75 | D101: =(C101-C102)/C102 -> -0.071863436 | E101: 0.04432505 | G101: 90 | H101: =_xlfn.NORM.INV(RAND(),N$12,N$13) -> -0.023030395
B102: ='Historical VAR Data'!B4091 -> 39650 | C102: ='Historical VAR Data'!F4091 -> 83.77 | D102: =(C102-C103)/C103 -> -0.18748788 | E102: 0.044253303 | G102: 91 | H102: =_xlfn.NORM.INV(RAND(),N$12,N$13) -> 0.0025475642
B103: ='Historical VAR Data'!B4288 -> 39359 | C103: ='Historical VAR Data'!F4288 -> 103.10 | D103: =(C103-C104)/C104 -> 0.78837814 | E103: 0.044050633 | G103: 92 | H103: =_xlfn.NORM.INV(RAND(),N$12,N$13) -> -0.011962526
B104: ='Historical VAR Data'!B4550 -> 38973 | C104: ='Historical VAR Data'!F4550 -> 57.65 | D104: =(C104-C105)/C105 -> -0.21639255 | E104: 0.04325009 | G104: 93 | H104: =_xlfn.NORM.INV(RAND(),N$12,N$13) -> -0.006548273
B105: ='Historical VAR Data'!B4381 -> 39226 | C105: ='Historical VAR Data'!F4381 -> 73.57 | D105: =(C105-C106)/C106 -> 0.65140292 | E105: 0.043102226 | G105: 94 | H105: =_xlfn.NORM.INV(RAND(),N$12,N$13) -> -0.0094038174
B106: ='Historical VAR Data'!B4761 -> 38664 | C106: ='Historical VAR Data'!F4761 -> 44.55 | D106: =(C106-C107)/C107 -> -0.053336167 | E106: 0.042837079 | G106: 95 | H106: =_xlfn.NORM.INV(RAND(),N$12,N$13) -> 0.0036369213
B107: ='Historical VAR Data'!B4792 -> 38616 | C107: ='Historical VAR Data'!F4792 -> 47.06 | D107: =(C107-C108)/C108 -> -0.45425026 | E107: 0.042534338 | G107: 96 | H107: =_xlfn.NORM.INV(RAND(),N$12,N$13) -> -0.027935612
B108: ='Historical VAR Data'!B3971 -> 39833 | C108: ='Historical VAR Data'!F3971 -> 86.23 | D108: =(C108-C109)/C109 -> 0.022651803 | E108: 0.042306298 | G108: 97 | H108: =_xlfn.NORM.INV(RAND(),N$12,N$13) -> -0.0022430035
...

Sheet Altman Z-Score
B3: ='Data Sheet'!B1 -> NTPC LTD
B4: =CONCATENATE(" ","(",VLOOKUP(B3,'List of Stocks'!A2:C5442,3,1)," | ","BSE Code: ",VLOOKUP(B3,'List of Stocks'!A2:B5442,2,1),")") -> (NTPC | BSE Code: 532555)
B5: =CONCATENATE(" ","INR " & 'Data Sheet'!B8) -> INR 315.8
B6: 52 Week (High - INR 448.45 & Low - 292.80)
B8: Altman's Z Score Analysis
B10: NTPC (National Thermal Power Corporation) Ltd along with its subsidiaries/ associates & JVs is primarily involved in generation and sale of bulk power to State power utilities. Other business of the group includes providing consultancy, project management & supervision, energy trading, oil & gas exploration and coal mining. NTPC's core function is the generation and distribution of electricity to State Electricity Boards in India.It is the largest power company in India with an installed capacity of 76442.78 MW.
B14: Financial Summary
B59: Working Capital / Total Asset
C60: =HistoricalFS!F8 -> 43190 | D60: =HistoricalFS!G8 -> 43555 | E60: =HistoricalFS!H8 -> 43921 | F60: =HistoricalFS!I8 -> 44286 | G60: =HistoricalFS!J8 -> 44651 | H60: =HistoricalFS!K8 -> 45016 | I60: =HistoricalFS!L8 -> 45382
B61: Working Capital | C61: ='Data Sheet'!E66-'Data Sheet'!E61 -> 13104.9 | D61: ='Data Sheet'!F66-'Data Sheet'!F61 -> 6900.74 | E61: ='Data Sheet'!G66-'Data Sheet'!G61 -> 26205.62 | F61: ='Data Sheet'!H66-'Data Sheet'!H61 -> 24605.88 | G61: ='Data Sheet'!I66-'Data Sheet'!I61 -> 19404.78 | H61: ='Data Sheet'!J66-'Data Sheet'!J61 -> 26398.12 | I61: ='Data Sheet'!K66-'Data Sheet'!K61 -> 35357.61
B62: Total Assets | C62: ='Data Sheet'!E62 -> 282492.26 | D62: ='Data Sheet'!F62 -> 346922.99 | E62: ='Data Sheet'!G62 -> 377569 | F62: ='Data Sheet'!H62 -> 398021.79 | G62: ='Data Sheet'!I62 -> 415831.42 | H62: ='Data Sheet'!J62 -> 447188.89 | I62: ='Data Sheet'!K62 -> 479277.72
B63: W.C. / T.A. (A) | C63: =C61/C62 -> 0.046390298 | D63: =D61/D62 -> 0.019891273 | E63: =E61/E62 -> 0.069406175 | F63: =F61/F62 -> 0.061820435 | G63: =G61/G62 -> 0.046665016 | H63: =H61/H62 -> 0.059031252 | I63: =I61/I62 -> 0.073772697
B65: Retained Earnings / Total Asset
C66: =C60 -> 43190 | D66: =D60 -> 43555 | E66: =E60 -> 43921 | F66: =F60 -> 44286 | G66: =G60 -> 44651 | H66: =H60 -> 45016 | I66: =I60 -> 45382
B67: Retained Earnings | C67: =HistoricalFS!F40*HistoricalFS!F42*HistoricalFS!F48 -> 704.27 | D67: =HistoricalFS!G40*HistoricalFS!G42*HistoricalFS!G48 -> 5200.74 | E67: =HistoricalFS!H40*HistoricalFS!H42*HistoricalFS!H48 -> 576.23 | F67: =HistoricalFS!I40*HistoricalFS!I42*HistoricalFS!I48 -> 3985.22 | G67: =HistoricalFS!J40*HistoricalFS!J42*HistoricalFS!J48 -> 5363.64 | H67: =HistoricalFS!K40*HistoricalFS!K42*HistoricalFS!K48 -> 7530.32 | I67: =HistoricalFS!L40*HistoricalFS!L42*HistoricalFS!L48 -> 8627.43
B68: =B62 -> Total Assets | C68: =C62 -> 282492.26 | D68: =D62 -> 346922.99 | E68: =E62 -> 377569 | F68: =F62 -> 398021.79 | G68: =G62 -> 415831.42 | H68: =H62 -> 447188.89 | I68: =I62 -> 479277.72
B69: Retained Earnings / T.A. (B) | C69: =C67/C68 -> 0.0024930595 | D69: =D67/D68 -> 0.01499105 | E69: =E67/E68 -> 0.0015261581 | F69: =F67/F68 -> 0.010012567 | G69: =G67/G68 -> 0.012898592 | H69: =H67/H68 -> 0.016839238 | I69: =I67/I68 -> 0.018000899
B72: EBIT / Total Asset
B73: EBIT | C73: ='Data Sheet'!E35 -> 20643.48 | D73: ='Data Sheet'!F35 -> 16561.39 | E73: ='Data Sheet'!G35 -> 29136.78 | F73: ='Data Sheet'!H35 -> 26279.37 | G73: ='Data Sheet'!I35 -> 31098.68 | H73: ='Data Sheet'!J35 -> 35155.82 | I73: ='Data Sheet'!K35 -> 39921.6
B74: =B68 -> Total Assets | C74: =C68 -> 282492.26 | D74: =D68 -> 346922.99 | E74: =E68 -> 377569 | F74: =F68 -> 398021.79 | G74: =G68 -> 415831.42 | H74: =H68 -> 447188.89 | I74: =I68 -> 479277.72
B75: EBIT / Total Asset (C) | C75: =C73/C74 -> 0.073076268 | D75: =D73/D74 -> 0.047737943 | E75: =E73/E74 -> 0.077169418 | F75: =F73/F74 -> 0.066024953 | G75: =G73/G74 -> 0.074786749 | H75: =H73/H74 -> 0.078615146 | I75: =I73/I74 -> 0.083295339
B77: Market Cap / Long Term Liability
B78: Market Cap | C78: =('Data Sheet'!E71*'Data Sheet'!E91)/10000000 -> 116607.36 | D78: =('Data Sheet'!F71*'Data Sheet'!F91)/10000000 -> 133279.69 | E78: =('Data Sheet'!G71*'Data Sheet'!G91)/10000000 -> 83312.172 | F78: =('Data Sheet'!H71*'Data Sheet'!H91)/10000000 -> 103317.98 | G78: =('Data Sheet'!I71*'Data Sheet'!I91)/10000000 -> 130904.99 | H78: =('Data Sheet'!J71*'Data Sheet'!J91)/10000000 -> 169788.62 | I78: =('Data Sheet'!K71*'Data Sheet'!K91)/10000000 -> 325614.05
B79: Liability | C79: ='Data Sheet'!E60 -> 130048.56 | D79: ='Data Sheet'!F60 -> 173058.23 | E79: ='Data Sheet'!G60 -> 202984.31 | F79: ='Data Sheet'!H60 -> 210207.87 | G79: ='Data Sheet'!I60 -> 210706.56 | H79: ='Data Sheet'!J60 -> 222913.16 | I79: ='Data Sheet'!K60 -> 237130.98
B80: M.C. / Long Term Liability (D) | C80: =C78/C79 -> 0.89664474 | D80: =D78/D79 -> 0.77014359 | E80: =E78/E79 -> 0.41043651 | F80: =F78/F79 -> 0.49150385 | G80: =G78/G79 -> 0.62126681 | H80: =H78/H79 -> 0.76168058 | I80: =I78/I79 -> 1.3731401
B82: Sales / Total Sales
C83: =C60 -> 43190 | D83: =D60 -> 43555 | E83: =E60 -> 43921 | F83: =F60 -> 44286 | G83: =G60 -> 44651 | H83: =H60 -> 45016 | I83: =I60 -> 45382
B84: Total Sales | C84: ='Data Sheet'!E17 -> 88083.31 | D84: ='Data Sheet'!F17 -> 100286.54 | E84: ='Data Sheet'!G17 -> 109464.04 | F84: ='Data Sheet'!H17 -> 111531.15 | G84: ='Data Sheet'!I17 -> 132669.28 | H84: ='Data Sheet'!J17 -> 176207.18 | I84: ='Data Sheet'!K17 -> 178500.88
B85: =B74 -> Total Assets | C85: =C74 -> 282492.26 | D85: =D74 -> 346922.99 | E85: =E74 -> 377569 | F85: =F74 -> 398021.79 | G85: =G74 -> 415831.42 | H85: =H74 -> 447188.89 | I85: =I74 -> 479277.72
B86: Sales / Total Sales (E) | C86: =C84/C85 -> 0.31180787 | D86: =D84/D85 -> 0.28907436 | E86: =E84/E85 -> 0.28991798 | F86: =F84/F85 -> 0.28021368 | G86: =G84/G85 -> 0.31904583 | H86: =H84/H85 -> 0.394033 | I86: =I84/I85 -> 0.37243726
B88: Altman's Z Score
C89: =C83 -> 43190 | D89: =D83 -> 43555 | E89: =E83 -> 43921 | F89: =F83 -> 44286 | G89: =G83 -> 44651 | H89: =H83 -> 45016 | I89: =I83 -> 45382
B90: Final Score | C90: =(C63*1.2)+(C69*1.4)+(C75*3.3)+(C80*0.6)+(C86*1) -> 1.150105 | D90: =(D63*1.2)+(D69*1.4)+(D75*3.3)+(D80*0.6)+(D86*1) -> 0.95355272 | E90: =(E63*1.2)+(E69*1.4)+(E75*3.3)+(E80*0.6)+(E86*1) -> 0.87626299 | F90: =(F63*1.2)+(F69*1.4)+(F75*3.3)+(F80*0.6)+(F86*1) -> 0.88120045 | G90: =(G63*1.2)+(G69*1.4)+(G75*3.3)+(G80*0.6)+(G86*1) -> 1.0126582 | H90: =(H63*1.2)+(H69*1.4)+(H75*3.3)+(H80*0.6)+(H86*1) -> 1.2048838 | I90: =(I63*1.2)+(I69*1.4)+(I75*3.3)+(I80*0.6)+(I86*1) -> 1.5849244
B91: Financial Stability | C91: =IF(C90<1.81,"Distressed", IF(C90>3,"Strong", "Grey Zone")) -> Distressed | D91: =IF(D90<1.81,"Distressed", IF(D90>3,"Strong", "Grey Zone")) -> Distressed | E91: =IF(E90<1.81,"Distressed", IF(E90>3,"Strong", "Grey Zone")) -> Distressed | F91: =IF(F90<1.81,"Distressed", IF(F90>3,"Strong", "Grey Zone")) -> Distressed | G91: =IF(G90<1.81,"Distressed", IF(G90>3,"Strong", "Grey Zone")) -> Distressed | H91: =IF(H90<1.81,"Distressed", IF(H90>3,"Strong", "Grey Zone")) -> Distressed | I91: =IF(I90<1.81,"Distressed", IF(I90>3,"Strong", "Grey Zone")) -> Distressed
B104: Sources:
B105: 52 High week Low | C105: https://www.nseindia.com/market-data/52-week-high-equity-market

Sheet Data Room>

Sheet <Regression Data>
B2: DATA - | C2: https://finance.yahoo.com/quote/NTPC.NS/history/?period1=1675728000&period2=1738924492&frequency=1wk
B3: DATA 2 - | C3: https://finance.yahoo.com/quote/%5ENSEI/history/?frequency=1wk
B5: ='Data Sheet'!B1 & " - " & "Share Price" -> NTPC LTD - Share Price | E5: NIFTY 50 - 1 Week
B6: Date | C6: Adj Close | E6: Date | F6: Closing Price
B7: 45691 | C7: 316.95001 | E7: 45691 | F7: 23559.949
B8: 45684 | C8: 315.24103 | E8: 45684 | F8: 23508.4
B9: 45677 | C9: 321.14496 | E9: 45677 | F9: 23092.199
B10: 45670 | C10: 323.62561 | E10: 45670 | F10: 23203.199
B11: 45663 | C11: 305.86417 | E11: 45663 | F11: 23431.5
B12: 45656 | C12: 337.21957 | E12: 45656 | F12: 24004.75
B13: 45649 | C13: 332.4071 | E13: 45649 | F13: 23813.4
B14: 45642 | C14: 330.67065 | E14: 45642 | F14: 23587.5
B15: 45635 | C15: 354.38568 | E15: 45635 | F15: 24768.301
B16: 45628 | C16: 366.64008 | E16: 45628 | F16: 24677.801
B17: 45621 | C17: 360.83536 | E17: 45621 | F17: 24131.1
B18: 45614 | C18: 362.62143 | E18: 45614 | F18: 23907.25
... B112: 44956 | C112: 152.7 | E112: 44956 | F112: 17854.05

Sheet Historical VAR Data
B2: MAX DATA
A3: # | B3: Date | C3: Open | D3: High | E3: Low | F3: Adj Close | G3: Volume | H3: Dividends
B4: 45706 | C4: 301.15 | D4: 312.40 | E4: 297.50 | F4: 311.20 | G4: 15792612 | H4: -
B5: 45705 | C5: 297.50 | D5: 303.20 | E5: 292.80 | F5: 302.35 | G5: 6464173 | H5: -
B6: 45702 | C6: 306.85 | D6: 308.25 | E6: 298.35 | F6: 300.35 | G6: 7446248 | H6: -
B7: 45701 | C7: 306.15 | D7: 308.60 | E7: 303.10 | F7: 306.70 | G7: 9086906 | H7: -
B8: 45700 | C8: 306.20 | D8: 307.50 | E8: 300.00 | F8: 306.25 | G8: 7616083 | H8: -
B9: 45699 | C9: 312.35 | D9: 312.35 | E9: 304.15 | F9: 305.60 | G9: 13241830 | H9: -
B10: 45698 | C10: 316.50 | D10: 316.85 | E10: 309.00 | F10: 310.50 | G10: 6806132 | H10: -
B11: 45695 | C11: 313.50 | D11: 319.25 | E11: 312.10 | F11: 316.95 | G11: 8937447 | H11: -
B12: 45694 | C12: 322.60 | D12: 322.70 | E12: 311.40 | F12: 312.80 | G12: 13384442 | H12: -
B13: 45693 | C13: 321.00 | D13: 323.05 | E13: 318.40 | F13: 319.60 | G13: 12226722 | H13: -
B14: 45692 | C14: 314.85 | D14: 320.45 | E14: 310.30 | F14: 319.10 | G14: 12141064 | H14: -
B15: 45691 | C15: 310.10 | D15: 314.05 | E15: 304.00 | F15: 311.25 | G15: 15881217 | H15: -
B16: 45689 | C16: 326.05 | D16: 330.80 | E16: 316.75 | F16: 317.70 | G16: 10097627 | H16: -
B17: 45688 | C17: 322.45 | D17: 326.25 | E17: 317.55 | F17: 324.00 | G17: 13195557 | H17: 2.5
B18: 45687 | C18: 319.76 | D18: 324.27 | E18: 318.66 | F18: 320.50 | G18: 10375720 | H18: -
B19: 45686 | C19: 317.52 | D19: 320.40 | E19: 310.88 | F19: 318.76 | G19: 16056888 | H19: -
B20: 45685 | C20: 320.00 | D20: 321.34 | E20: 305.76 | F20: 315.79 | G20: 22008929 | H20: -
B21: 45684 | C21: 321.14 | D21: 322.53 | E21: 312.56 | F21: 319.71 | G21: 13803855 | H21: -
B22: 45681 | C22: 322.29 | D22: 327.35 | E22: 319.61 | F22: 321.14 | G22: 7492600 | H22: -
B23: 45680 | C23: 318.52 | D23: 322.58 | E23: 317.08 | F23: 321.14 | G23: 6477347 | H23: -
B24: 45679 | C24: 324.47 | D24: 324.47 | E24: 314.89 | F24: 319.90 | G24: 11068145 | H24: -
B25: 45678 | C25: 335.19 | D25: 335.63 | E25: 321.29 | F25: 321.79 | G25: 12774630 | H25: -
B26: 45677 | C26: 323.68 | D26: 334.39 | E26: 322.04 | F26: 333.45 | G26: 17991880 | H26: -
B27: 45674 | C27: 322.78 | D27: 326.45 | E27: 320.85 | F27: 323.63 | G27: 7129232 | H27: -
B28: 45673 | C28: 322.19 | D28: 324.77 | E28: 319.16 | F28: 322.98 | G28: 14865186 | H28: -
B29: 45672 | C29: 310.13 | D29: 321.79 | E29: 310.13 | F29: 318.86 | G29: 21894626 | H29: -
... B5013: 38299 | C5013: 32.65 | D5013: 33.42 | E5013: 31.89 | F5013: 31.97 | G5013: 82638332 | H5013: -
A5014: # | B5014: 38296 | C5014: 37.41 | D5014: 37.41 | E5014: 29.76 | F5014: 32.12 | G5014: 279042883 | H5014: -

Sheet List of Stocks
A2: COMPANY_NAME | B2: BSE | C2: NSE | D2: Industry
A3: 20 MICRONS LTD | B3: 533022 | C3: 20MICRONS | D3: Mining
A4: 21ST CENTURY MANAGEMENT SERVICES LTD | B4: 526921 | C4: 21STCENMGM | D4: Other Financial Services
A5: 3I INFOTECH LTD | B5: 532628 | C5: 3IINFOTECH | D5: IT Consulting & Software
A6: 3M (INDIA) LTD | B6: 523395 | C6: 3M(INDIA) | D6: Diversified
A7: 3M INDIA LTD | B7: 523395 | C7: 3MINDIA | D7: Diversified
A8: 3P LAND HOLDINGS LTD | B8: 516092 | C8: 3PLAND | D8: Paper & Paper Products
A9: 5PAISA CAPITAL LTD | B9: 540776 | C9: 5PAISA | D9: Other Financial Services
A10: 63 MOONS TECHNOLOGIES LTD | B10: 526881 | C10: 63MOONS | D10: IT Consulting & Software
A11: 7NR RETAIL LTD | B11: 540615 | C11: Not Listed | D11: Specialty Retail
A12: 7SEAS ENTERTAINMENT LTD | B12: 540874 | C12: Not Listed | D12: Movies & Entertainment
A13: 8K MILES SOFTWARE SERVICES LTD | B13: 512161 | C13: 8KMILES | D13: Internet Software & Services
